Workbook
Name Ability_Component_Tags: _xlfn.ANCHORARRAY(tags!$B$2)
Name Action_Tags: _xlfn.ANCHORARRAY(tags!$D$2)
Name Attack_Tags: _xlfn.ANCHORARRAY(tags!$E$2)
Name Bonus_Action_Tags: _xlfn.ANCHORARRAY(tags!$K$2)
Name Condition_Effect_Tags: _xlfn.ANCHORARRAY(tags!$F$2)
Name Damage_Effect_Tags: _xlfn.ANCHORARRAY(tags!$G$2)
Name Duration_Descs: durations!$D$2:$D$125
Name Duration_Names: durations!$B$2:$B$125
Name Feature_Ability_Tags: _xlfn.ANCHORARRAY(tags!$A$2)
Name Filtered_Templates: _xlfn.ANCHORARRAY(tags!#REF!)
Name Outcome_Tags: _xlfn.ANCHORARRAY(tags!$C$2)
Name Reaction_Tags: _xlfn.ANCHORARRAY(tags!$L$2)
Name Save_Effect_Tags: _xlfn.ANCHORARRAY(tags!$H$2)
Name Secondary_Effect_Tags: _xlfn.ANCHORARRAY(tags!$I$2)
Name Target_Effect_Tags: _xlfn.ANCHORARRAY(tags!$J$2)

Sheet ASSEMBLY
A1: ok | B1: [#]
A2: ok | B2: [#dX]
A3: ok | B3: [DISEASE]
A4: ok | B4: [DMG_EFFECT]
A5: ok | B5: [DMG_MOD]
A6: ok | B6: [DMG_TYPE]
A7: ok | B7: [DURATION]
A9: ok | B9: [MON]
A10: ok | B10: [OUTCOME]
A12: ok | B12: [SAVE_DC]
A13: ok | B13: [ABILITY]
A15: ok | B15: [TGT_EFFECT]

Sheet tags
A1: Feature/Ability Tags | B1: Add-On Tags | C1: Outcome Tags | D1: Action Tags | E1: Attack Effect Tags | F1: Condition Effect Tags | G1: Damage Effect Tags | H1: Save Effect Tags | I1: Secondary Effect Tags | J1: Target Effect Tags | K1: Bonus Action Tags | L1: Reaction Tags
A2: {=_xlfn._xlws.SORT(_xlfn.UNIQUE(TRIM(_xlfn.TOCOL(_xlfn.TEXTSPLIT('features-abilities'!$C$2:$C$2000,",",,TRUE),3))))} -> Ability Score Damage | B2: {=_xlfn._xlws.SORT(_xlfn.UNIQUE(TRIM(_xlfn.TOCOL(_xlfn.TEXTSPLIT('add-ons'!$C$2:$C$2000,",",,TRUE),3))))} -> Ability Score Damage | C2: {=_xlfn._xlws.SORT(_xlfn.UNIQUE(TRIM(_xlfn.TOCOL(_xlfn.TEXTSPLIT(outcomes!$C$2:$C$1999,",",,TRUE),3))))} -> Ability Score Damage | D2: {=_xlfn._xlws.SORT(_xlfn.UNIQUE(TRIM(_xlfn.TOCOL(_xlfn.TEXTSPLIT(actions!$C$2:$C$2000,",",,TRUE),3))))} -> Ability Score Damage | E2: {=_xlfn._xlws.SORT(_xlfn.UNIQUE(TRIM(_xlfn.TOCOL(_xlfn.TEXTSPLIT('attack effects'!$C$2:$C$2000,",",,TRUE),3))))} -> Advantage | F2: {=_xlfn._xlws.SORT(_xlfn.UNIQUE(TRIM(_xlfn.TOCOL(_xlfn.TEXTSPLIT('condition effects'!$C$2:$C$2000,",",,TRUE),3))))} -> Ability Score Damage | G2: {=_xlfn._xlws.SORT(_xlfn.UNIQUE(TRIM(_xlfn.TOCOL(_xlfn.TEXTSPLIT('damage effects'!$C$2:$C$2000,",",,TRUE),3))))} -> Ability Score Damage | H2: {=_xlfn._xlws.SORT(_xlfn.UNIQUE(TRIM(_xlfn.TOCOL(_xlfn.TEXTSPLIT('save effects'!$C$2:$C$2000,",",,TRUE),3))))} -> Advantage | I2: {=_xlfn._xlws.SORT(_xlfn.UNIQUE(TRIM(_xlfn.TOCOL(_xlfn.TEXTSPLIT('secondary effects'!$C$2:$C$2000,",",,TRUE),3))))} -> AC Change | J2: {=_xlfn._xlws.SORT(_xlfn.UNIQUE(TRIM(_xlfn.TOCOL(_xlfn.TEXTSPLIT('target effects'!$C$2:$C$2000,",",,TRUE),3))))} -> Ability Score Damage | K2: {=_xlfn._xlws.SORT(_xlfn.UNIQUE(TRIM(_xlfn.TOCOL(_xlfn.TEXTSPLIT('bonus actions'!$C$2:$C$2000,",",,TRUE),3))))} -> Ability Score Damage | L2: {=_xlfn._xlws.SORT(_xlfn.UNIQUE(TRIM(_xlfn.TOCOL(_xlfn.TEXTSPLIT(reactions!$C$2:$C$2000,",",,TRUE),3))))} -> AC Change
A3: AC Change | B3: AC Change | C3: AC Change | D3: AC Change | E3: Area | F3: Advantage | G3: Advantage | H3: Charm Effect | I3: Bonus Action Attack | J3: AC Change | K3: AC Change | L3: Advantage
A4: Advantage | B4: Advantage | C4: Advantage | D4: Advantage | E4: Attachment Effect | F4: Approaching | G4: Aging | H4: Charming | I4: Charm Effect | J4: Advantage | K4: Advantage | L4: Area
A5: Aging | B5: Aging | C5: Aging | D5: Approaching | E5: Bonus Action Attack | F5: Attachment Effect | G5: Area | H5: Confusion | I5: Consumption Ending | J5: Area | K5: Approaching | L5: Aura
A6: Approaching | B6: Approaching | C6: Approaching | D6: Area | E6: Concentration | F6: Attachment Ending | G6: Bonus Action Attack | H6: Curse Effect | I6: Curse Effect | J6: Attaching | K6: Area | L6: Betraying
A7: Area | B7: Area | C7: Area | D7: Attaching | E7: Consuming | F7: Aura | G7: Disadvantage | H7: Disadvantage | I7: Disengaging | J7: Bonus Action Attack | K7: Aura | L7: Blinding
A8: Attaching | B8: Attachment Effect | C8: Betraying | D8: Aura | E8: Cursing | F8: Betraying | G8: Disarming | H8: Discharging | I8: Extra Damage | J8: Coating | K8: Betraying | L8: Charm Effect
A9: Aura | B9: Attachment Ending | C9: Blinding | D9: Betraying | E9: Disadvantage | F9: Blinding | G9: Equipment Damage | H9: Fear Effect | I9: Fear Effect | J9: Consuming | K9: Blinding | L9: Charming
A10: Blinding | B10: Aura | C10: Bonus Action Attack | D10: Blinding | E10: Discharging | F10: Blindness Ending | G10: Exhausting | H10: Limitation | I10: Grapple Effect | J10: Disadvantage | K10: Bonus Action Attack | L10: Consumption Effect
A11: Blindness Effect | B11: Betraying | C11: Charming | D11: Bonus Action Attack | E11: Disengaging | F11: Can't Attack Other Targets | G11: Extra Damage | I11: HP Max Reducing | J11: Disengaging | K11: Charming | L11: Cursing
A12: Bonus Action Attack | B12: Blinding | C12: Coating | D12: Charm Effect | E12: Equipment Damage | F12: Charm Effect | G12: Grapple Effect | I12: Incapacitation Effect | J12: Equipment Damage | K12: Communication | L12: Damage Reduction
A13: Charming | B13: Blindness Ending | C13: Confusing | D13: Charming | E13: Expanded Crit Range | F13: Charm Ending | G13: Healing | I13: Infecting | J13: Extra Damage | K13: Consumption Effect | L13: Difficult Terrain
A14: Coating | B14: Bonus Action Attack | C14: Consuming | D14: Coating | E14: Extra Damage | F14: Charming | G14: HP Max Reducing | I14: Limitation | J14: HP Max Reducing | K14: Cursing | L14: Disadvantage
A15: Communication | B15: Can't Attack Other Targets | C15: Cursing | D15: Communication | E15: Grapple Effect | F15: Confusing | G15: Knockout | I15: Magic Disrupting | J15: Magic Disrupting | K15: Damage Reduction | L15: Disarming
A16: Concentration | B16: Charm Effect | C16: Damage Reduction | D16: Concentration | E16: Grappling | F16: Confusion | G16: Lethal | I16: Movement | J16: Nonreactive | K16: Difficult Terrain | L16: Disengaging
A17: Confusing | B17: Charm Ending | C17: Deafening | D17: Confusing | E17: HP Max Reducing | F17: Confusion Ending | G17: Limitation | I17: Obscuring | J17: Ongoing Damage | K17: Disadvantage | L17: Drop to 0
A18: Consuming | B18: Charming | C18: Disadvantage | D18: Consuming | E18: Incapacitating | F18: Consumption Effect | G18: Nonlethal | I18: Poison Effect | J18: Paralyzing | K18: Discharging | L18: Extra Damage
A19: Curse Effect | B19: Communication | C19: Disarming | D19: Curse Effect | E19: Infecting | F19: Consumption Ending | G19: Self Healing | I19: Prone Effect | J19: Pushing | K19: Disengaging | L19: Frightening
A20: Cursing | B20: Concentration | C20: Drop to 0 | D20: Cursing | E20: Injury | F20: Curse Effect | G20: Shapechanging | I20: Pushing | J20: Shapechanging | K20: Equipment Damage | L20: Gaze
A21: Damage Reduction | B21: Confusing | C21: Effect Ending | D21: Damage Reduction | E21: Lethal | F21: Curse Ending | G21: Spawning | I21: Restraining | J21: Speed Change | K21: Exhausting | L21: Grappling
A22: Deafening | B22: Confusion | C22: Exhausting | D22: Deafening | E22: Light | F22: Cursing | G22: Temporary Self Healing | I22: Restraint Effect | J22: Suffocating | K22: Expanded Crit Range | L22: Healing
A23: Difficult Terrain | B23: Confusion Ending | C23: Extra Damage | D23: Difficult Terrain | E23: Limitation | F23: Damage Reduction | I23: Self Healing | J23: Summoning | K23: Extra Damage | L23: Incapacitating
A24: Disadvantage | B24: Consuming | C24: Frightening | D24: Disadvantage | E24: Magic Disrupting | F24: Deafness Ending | I24: Stun Effect | J24: Teleportation | K24: Grapple Effect | L24: Invisible
A25: Disarming | B25: Consumption Effect | C25: Grappling | D25: Disarming | E25: Mount | F25: Disadvantage | I25: Temporary Self Healing | J25: Zero Speed | K25: Grappling | L25: Light
A26: Discharging | B26: Consumption Ending | C26: Healing | D26: Discharging | E26: Movement | F26: Disease | I26: Throwing | K26: Incapacitating | L26: Magic Disrupting
A27: Disengaging | B27: Curse Effect | C27: HP Max Reducing | D27: Disengaging | E27: Ongoing Damage | F27: Effect Ending | I27: Toppling | K27: Infecting | L27: Mount
A28: Drop to 0 | B28: Curse Ending | C28: Incapacitating | D28: Drop to 0 | E28: Poisoning | F28: Exhausting | I28: Unconsciousness Effect | K28: Invisible | L28: Movement
A29: Effect Ending | B29: Cursing | C29: Infecting | D29: Equipment Damage | E29: Rattling | F29: Exhaustion Effect | I29: Weakness | K29: Lethal | L29: Nonreactive
A30: Equipment Damage | B30: Damage Reduction | C30: Knockout | D30: Exhausting | E30: Recharging | F30: Exhaustion Ending | K30: Light | L30: Obscuring
A31: Exhausting | B31: Deafening | C31: Lethal | D31: Frightening | E31: Self Healing | F31: Extra Damage | K31: Magic Disrupting | L31: Ongoing Damage
A32: Expanded Crit Range | B32: Deafness Ending | C32: Madness | D32: Grapple Effect | E32: Shapechanging | F32: Fear Effect | K32: Mount | L32: Poisoning
A33: Extra Damage | B33: Difficult Terrain | C33: Magic Disrupting | D33: Grapple Ending | E33: Spawning | F33: Fear Ending | K33: Movement | L33: Prone Effect
A34: Frightening | B34: Disadvantage | C34: Marking | D34: Grappling | E34: Temporary Healing | F34: Fire Effect | K34: Obscuring | L34: Pushing
A35: Gaze | B35: Disarming | C35: Movement | D35: Healing | E35: Unhealable | F35: Grapple Effect | K35: Ongoing Damage | L35: Recharging
A36: Grapple Effect | B36: Discharging | C36: Nonreactive | D36: HP Max Reducing | E36: Weakness | F36: Grapple Ending | K36: Poisoning | L36: Self Healing
A37: Grappling | B37: Disease | C37: Ongoing Damage | D37: Incapacitating | F37: HP Max Reducing | K37: Possessing | L37: Shapechanging
A38: Healing | B38: Disengaging | C38: Paralyzing | D38: Incapacitation Effect | F38: Incapacitating | K38: Prone Effect | L38: Speed Change
A39: HP Max Reducing | B39: Effect Ending | C39: Petrifying | D39: Infecting | F39: Incapacitation Effect | K39: Pulling | L39: Stunning
A40: Incapacitating | B40: Equipment Damage | C40: Poisoning | D40: Invisible | F40: Incapacitation Ending | K40: Rampaging | L40: Summoning
A41: Incapacitation Effect | B41: Exhausting | C41: Possessing | D41: Knockout | F41: Infecting | K41: Recharging | L41: Teleportation
A42: Infected | B42: Exhaustion Effect | C42: Pulling | D42: Lair | F42: Infection Effect | K42: Restraining | L42: Temporary Healing
A43: Infecting | B43: Exhaustion Ending | C43: Pushing | D43: Lethal | F43: Infection Ending | K43: Self Healing | L43: Temporary Self Healing
A44: Invisible | B44: Expanded Crit Range | C44: Random Effects | D44: Light | F44: Invisible | K44: Sense | L44: Toppling
A45: Knockout | B45: Extra Damage | C45: Restoring | D45: Madness | F45: Knockout | K45: Shapechanging | L45: Variable Damage Type
A46: Lair | B46: Fear Effect | C46: Restraining | D46: Magic Disrupting | F46: Limbs | K46: Spawning
A47: Lethal | B47: Fear Ending | C47: Self Healing | D47: Marking | F47: Movement | K47: Speed Change
A48: Light | B48: Fire Effect | C48: Sense | D48: Mount | F48: Nonreactive | K48: Stunning
A49: Limbs | B49: Grapple Effect | C49: Shapechanging | D49: Movement | F49: Ongoing Damage | K49: Suffocating
A50: Magic Disrupting | B50: Grapple Ending | C50: Silencing | D50: Obscuring | F50: Paralysis Ending | K50: Summoning
A51: Mount | B51: Grappling | C51: Speed Change | D51: Ongoing Damage | F51: Paralyzing | K51: Teleportation
A52: Movement | B52: Healing | C52: Stunning | D52: Petrifying | F52: Petrifying | K52: Temporary Self Healing
A53: Nonreactive | B53: HP Max Reducing | C53: Suffocating | D53: Poisoning | F53: Poison Effect | K53: Throwing
A54: Obscuring | B54: Incapacitating | C54: Teleportation | D54: Possessing | F54: Poison Ending | K54: Toppling
A55: Ongoing Damage | B55: Incapacitation Effect | C55: Temporary Healing | D55: Prone Effect | F55: Poisoning | K55: Variable Damage Type
A56: Paralyzing | B56: Incapacitation Ending | C56: Throwing | D56: Pulling | F56: Restraint Effect | K56: Zero Speed
A57: Petrifying | B57: Infecting | C57: Toppling | D57: Pushing | F57: Restraint Ending
A58: Poisoning | B58: Infection Effect | C58: Unhealable | D58: Rattling | F58: Stun Effect
A59: Pushing | B59: Infection Ending | C59: Variable Damage Type | D59: Recharging | F59: Stun Ending
A60: Rampaging | B60: Injury | C60: Zero Speed | D60: Restoring (Self) | F60: Unconsciousness Ending
A61: Random Effects | B61: Invisible | D61: Restraining
A62: Rattling | B62: Knockout | D62: Restraint Effect
A63: Recharging | B63: Lethal | D63: Self Healing
A64: Restoring | B64: Light | D64: Sense
A65: Restoring (Self) | B65: Limbs | D65: Shapechanging
A66: Restraining | B66: Limitation | D66: Spawning
A67: Resurrection | B67: Magic Disrupting | D67: Speed Change
A68: Self Healing | B68: Mount | D68: Stunning
A69: Sense | B69: Movement | D69: Suffocating
A70: Shapechanging | B70: Nonlethal | D70: Summoning
A71: Silencing | B71: Nonreactive | D71: Target
A72: Spawning | B72: Obscuring | D72: Teleportation
... A76: Teleportation | B76: Petrifying | D76: Weakness
A77: Temporary Self Healing | B77: Poison Effect
A78: Toppling | B78: Poison Ending
A79: Variable Damage Type | B79: Poisoning
A80: Weakness | B80: Prone Effect
A81: Zero Speed | B81: Pushing
B82: Rattling
B83: Recharging
B84: Restoring
B85: Restraining
B86: Restraint Effect
B87: Restraint Ending
B88: Resurrection
B89: Self Healing
B90: Shapechanging
B91: Spawning
B92: Speed Change
B93: Stun Effect
... B105: Weakness

Sheet standard weapons
A1: Type | B1: Weapon | C1: Ability | D1: Reach/Range | E1: Damage Die | F1: Damage Type | G1: Properties | H1: Mastery (2024 only) | I1: Special Text | J1: Template | K1: With Mastery | L1: With Properties | P1: Split | U1: Split 2 | W1: 2 | Y1: 3 | AA1: 4 | AC1: 5
A2: Melee Weapon Attack | B2: Club (2014 edition) | C2: Strength | D2: reach 5 ft | E2: 1d4 | F2: bludgeoning | G2: Light | J2: =A2&": [ATK_MOD] to hit, "&D2&", one target. Hit: [DAMAGE] "&F2&" damage. "&I2 -> Melee Weapon Attack: [ATK_MOD] to hit, reach 5 ft, one target. Hit: [DAMAGE] bludgeoning damage. | L2: =IF(NOT(G2=""),IF(COUNTA(P2:T2)>1,"Properties: ","Property: ")&U2&" ("&V2&")"&IF(NOT(W2=""),", "&W2&" ("&X2&")"&IF(NOT(Y2=""),", "&Y2&" ("&Z2&")"&IF(NOT(AA2=""),", "&AB2&" ("&AC2&")",""),""),""),"") -> Property: Light (A light weapon is small and easy to handle, making it ideal for use when fighting with two weapons.) | P2: {=IFERROR(_xlfn.TEXTSPLIT(G2,", ",,TRUE),"")} -> Light | U2: {=IFERROR(INDEX(_xlfn.TEXTSPLIT(P2," "),,1),"")} -> Light | V2: =IF(NOT(U2=""),_xlfn.XLOOKUP(U2,'weapon masteries'!$A$10:$A$19,'weapon masteries'!$B$10:$B$19,"",0),"") -> A light weapon is small and easy to handle, making it ideal for use when fighting with two weapons. | W2: {=IFERROR(INDEX(_xlfn.TEXTSPLIT(Q2," "),,1),"")} | X2: =IF(NOT(W2=""),_xlfn.XLOOKUP(W2,'weapon masteries'!$A$10:$A$19,'weapon masteries'!$B$10:$B$19,"",0),"") | Y2: {=IFERROR(INDEX(_xlfn.TEXTSPLIT(R2," "),,1),"")} | Z2: =IF(NOT(Y2=""),_xlfn.XLOOKUP(Y2,'weapon masteries'!$A$10:$A$19,'weapon masteries'!$B$10:$B$19,"",0),"") | AA2: {=IFERROR(INDEX(_xlfn.TEXTSPLIT(S2," "),,1),"")} | AB2: =IF(NOT(AA2=""),_xlfn.XLOOKUP(AA2,'weapon masteries'!$A$10:$A$19,'weapon masteries'!$B$10:$B$19,"",0),"") | AC2: {=IFERROR(INDEX(_xlfn.TEXTSPLIT(T2," "),,1),"")} | AD2: =IF(NOT(AC2=""),_xlfn.XLOOKUP(AC2,'weapon masteries'!$A$10:$A$20,'weapon masteries'!$B$10:$B$20,"",0),"")
A3: Melee or Ranged Weapon Attack | B3: Dagger (2014 edition) | C3: Max of Strength or Dexterity | D3: reach 5 ft or range 20/60 ft | E3: 1d4 | F3: piercing | G3: Finesse, Light, Thrown (20/60) | J3: =A3&": [ATK_MOD] to hit, "&D3&", one target. Hit: [DAMAGE] "&F3&" damage. "&I3 -> Melee or Ranged Weapon Attack: [ATK_MOD] to hit, reach 5 ft or range 20/60 ft, one target. Hit: [DAMAGE] piercing damage. | L3: =IF(NOT(G3=""),IF(COUNTA(P3:T3)>1,"Properties: ","Property: ")&U3&" ("&V3&")"&IF(NOT(W3=""),", "&W3&" ("&X3&")"&IF(NOT(Y3=""),", "&Y3&" ("&Z3&")"&IF(NOT(AA3=""),", "&AB3&" ("&AC3&")",""),""),""),"") -> Properties: Finesse (When making an attack with a finesse weapon, you use your choice of your Strength or Dexterity modifier for the attack and damage rolls. You must use the same modifier for both rolls.), Light (A light weapon is small and easy to handle, making it ideal for use when fighting with two weapons.), Thrown (If a weapon has the thrown property, you can throw the weapon to make a ranged attack. If the weapon is a melee weapon, you use the same ability modifier for that attack roll and damage roll that you would use for a melee attack with the weapon. For example, if you throw a handaxe, you use your Strength, but if you throw a dagger, you can use either your Strength or your Dexterity, since the dagger has the finesse property.) | P3: {=IFERROR(_xlfn.TEXTSPLIT(G3,", ",,TRUE),"")} -> Finesse | Q3: Light | R3: Thrown (20/60) | U3: {=IFERROR(INDEX(_xlfn.TEXTSPLIT(P3," "),,1),"")} -> Finesse | V3: =IF(NOT(U3=""),_xlfn.XLOOKUP(U3,'weapon masteries'!$A$10:$A$19,'weapon masteries'!$B$10:$B$19,"",0),"") -> When making an attack with a finesse weapon, you use your choice of your Strength or Dexterity modifier for the attack and damage rolls. You must use the same modifier for both rolls. | W3: {=IFERROR(INDEX(_xlfn.TEXTSPLIT(Q3," "),,1),"")} -> Light | X3: =IF(NOT(W3=""),_xlfn.XLOOKUP(W3,'weapon masteries'!$A$10:$A$19,'weapon masteries'!$B$10:$B$19,"",0),"") -> A light weapon is small and easy to handle, making it ideal for use when fighting with two weapons. | Y3: {=IFERROR(INDEX(_xlfn.TEXTSPLIT(R3," "),,1),"")} -> Thrown | Z3: =IF(NOT(Y3=""),_xlfn.XLOOKUP(Y3,'weapon masteries'!$A$10:$A$19,'weapon masteries'!$B$10:$B$19,"",0),"") -> If a weapon has the thrown property, you can throw the weapon to make a ranged attack. If the weapon is a melee weapon, you use the same ability modifier for that attack roll and damage roll that you would use for a melee attack with the weapon. For example, if you throw a handaxe, you use your Strength, but if you throw a dagger, you can use either your Strength or your Dexterity, since the dagger has the finesse property. | AA3: {=IFERROR(INDEX(_xlfn.TEXTSPLIT(S3," "),,1),"")} | AB3: =IF(NOT(AA3=""),_xlfn.XLOOKUP(AA3,'weapon masteries'!$A$10:$A$19,'weapon masteries'!$B$10:$B$19,"",0),"") | AC3: {=IFERROR(INDEX(_xlfn.TEXTSPLIT(T3," "),,1),"")} | AD3: =IF(NOT(AC3=""),_xlfn.XLOOKUP(AC3,'weapon masteries'!$A$10:$A$20,'weapon masteries'!$B$10:$B$20,"",0),"")
A4: Melee Weapon Attack | B4: Greatclub (2014 edition) | C4: Strength | D4: reach 5 ft target | E4: 1d8 | F4: bludgeoning | G4: Two-Handed | J4: =A4&": [ATK_MOD] to hit, "&D4&", one target. Hit: [DAMAGE] "&F4&" damage. "&I4 -> Melee Weapon Attack: [ATK_MOD] to hit, reach 5 ft target, one target. Hit: [DAMAGE] bludgeoning damage. | L4: =IF(NOT(G4=""),IF(COUNTA(P4:T4)>1,"Properties: ","Property: ")&U4&" ("&V4&")"&IF(NOT(W4=""),", "&W4&" ("&X4&")"&IF(NOT(Y4=""),", "&Y4&" ("&Z4&")"&IF(NOT(AA4=""),", "&AB4&" ("&AC4&")",""),""),""),"") -> Property: Two-Handed (This weapon requires two hands to use. This property is relevant only when you attack with the weapon, not when you simply hold it.) | P4: {=IFERROR(_xlfn.TEXTSPLIT(G4,", ",,TRUE),"")} -> Two-Handed | U4: {=IFERROR(INDEX(_xlfn.TEXTSPLIT(P4," "),,1),"")} -> Two-Handed | V4: =IF(NOT(U4=""),_xlfn.XLOOKUP(U4,'weapon masteries'!$A$10:$A$19,'weapon masteries'!$B$10:$B$19,"",0),"") -> This weapon requires two hands to use. This property is relevant only when you attack with the weapon, not when you simply hold it. | W4: {=IFERROR(INDEX(_xlfn.TEXTSPLIT(Q4," "),,1),"")} | X4: =IF(NOT(W4=""),_xlfn.XLOOKUP(W4,'weapon masteries'!$A$10:$A$19,'weapon masteries'!$B$10:$B$19,"",0),"") | Y4: {=IFERROR(INDEX(_xlfn.TEXTSPLIT(R4," "),,1),"")} | Z4: =IF(NOT(Y4=""),_xlfn.XLOOKUP(Y4,'weapon masteries'!$A$10:$A$19,'weapon masteries'!$B$10:$B$19,"",0),"") | AA4: {=IFERROR(INDEX(_xlfn.TEXTSPLIT(S4," "),,1),"")} | AB4: =IF(NOT(AA4=""),_xlfn.XLOOKUP(AA4,'weapon masteries'!$A$10:$A$19,'weapon masteries'!$B$10:$B$19,"",0),"") | AC4: {=IFERROR(INDEX(_xlfn.TEXTSPLIT(T4," "),,1),"")} | AD4: =IF(NOT(AC4=""),_xlfn.XLOOKUP(AC4,'weapon masteries'!$A$10:$A$20,'weapon masteries'!$B$10:$B$20,"",0),"")
A5: Melee or Ranged Weapon Attack | B5: Handaxe (2014 edition) | C5: Max of Strength or Dexterity | D5: reach 5 ft or range 20/60 ft | E5: 1d6 | F5: slashing | G5: Light, Thrown (20/60) | J5: =A5&": [ATK_MOD] to hit, "&D5&", one target. Hit: [DAMAGE] "&F5&" damage. "&I5 -> Melee or Ranged Weapon Attack: [ATK_MOD] to hit, reach 5 ft or range 20/60 ft, one target. Hit: [DAMAGE] slashing damage. | L5: =IF(NOT(G5=""),IF(COUNTA(P5:T5)>1,"Properties: ","Property: ")&U5&" ("&V5&")"&IF(NOT(W5=""),", "&W5&" ("&X5&")"&IF(NOT(Y5=""),", "&Y5&" ("&Z5&")"&IF(NOT(AA5=""),", "&AB5&" ("&AC5&")",""),""),""),"") -> Properties: Light (A light weapon is small and easy to handle, making it ideal for use when fighting with two weapons.), Thrown (If a weapon has the thrown property, you can throw the weapon to make a ranged attack. If the weapon is a melee weapon, you use the same ability modifier for that attack roll and damage roll that you would use for a melee attack with the weapon. For example, if you throw a handaxe, you use your Strength, but if you throw a dagger, you can use either your Strength or your Dexterity, since the dagger has the finesse property.) | P5: {=IFERROR(_xlfn.TEXTSPLIT(G5,", ",,TRUE),"")} -> Light | Q5: Thrown (20/60) | U5: {=IFERROR(INDEX(_xlfn.TEXTSPLIT(P5," "),,1),"")} -> Light | V5: =IF(NOT(U5=""),_xlfn.XLOOKUP(U5,'weapon masteries'!$A$10:$A$19,'weapon masteries'!$B$10:$B$19,"",0),"") -> A light weapon is small and easy to handle, making it ideal for use when fighting with two weapons. | W5: {=IFERROR(INDEX(_xlfn.TEXTSPLIT(Q5," "),,1),"")} -> Thrown | X5: =IF(NOT(W5=""),_xlfn.XLOOKUP(W5,'weapon masteries'!$A$10:$A$19,'weapon masteries'!$B$10:$B$19,"",0),"") -> If a weapon has the thrown property, you can throw the weapon to make a ranged attack. If the weapon is a melee weapon, you use the same ability modifier for that attack roll and damage roll that you would use for a melee attack with the weapon. For example, if you throw a handaxe, you use your Strength, but if you throw a dagger, you can use either your Strength or your Dexterity, since the dagger has the finesse property. | Y5: {=IFERROR(INDEX(_xlfn.TEXTSPLIT(R5," "),,1),"")} | Z5: =IF(NOT(Y5=""),_xlfn.XLOOKUP(Y5,'weapon masteries'!$A$10:$A$19,'weapon masteries'!$B$10:$B$19,"",0),"") | AA5: {=IFERROR(INDEX(_xlfn.TEXTSPLIT(S5," "),,1),"")} | AB5: =IF(NOT(AA5=""),_xlfn.XLOOKUP(AA5,'weapon masteries'!$A$10:$A$19,'weapon masteries'!$B$10:$B$19,"",0),"") | AC5: {=IFERROR(INDEX(_xlfn.TEXTSPLIT(T5," "),,1),"")} | AD5: =IF(NOT(AC5=""),_xlfn.XLOOKUP(AC5,'weapon masteries'!$A$10:$A$20,'weapon masteries'!$B$10:$B$20,"",0),"")
A6: Melee or Ranged Weapon Attack | B6: Javelin (2014 edition) | C6: Strength | D6: reach 5 ft or range 30/120 ft | E6: 1d6 | F6: piercing | G6: Thrown (30/120) | J6: =A6&": [ATK_MOD] to hit, "&D6&", one target. Hit: [DAMAGE] "&F6&" damage. "&I6 -> Melee or Ranged Weapon Attack: [ATK_MOD] to hit, reach 5 ft or range 30/120 ft, one target. Hit: [DAMAGE] piercing damage. | L6: =IF(NOT(G6=""),IF(COUNTA(P6:T6)>1,"Properties: ","Property: ")&U6&" ("&V6&")"&IF(NOT(W6=""),", "&W6&" ("&X6&")"&IF(NOT(Y6=""),", "&Y6&" ("&Z6&")"&IF(NOT(AA6=""),", "&AB6&" ("&AC6&")",""),""),""),"") -> Property: Thrown (If a weapon has the thrown property, you can throw the weapon to make a ranged attack. If the weapon is a melee weapon, you use the same ability modifier for that attack roll and damage roll that you would use for a melee attack with the weapon. For example, if you throw a handaxe, you use your Strength, but if you throw a dagger, you can use either your Strength or your Dexterity, since the dagger has the finesse property.) | P6: {=IFERROR(_xlfn.TEXTSPLIT(G6,", ",,TRUE),"")} -> Thrown (30/120) | U6: {=IFERROR(INDEX(_xlfn.TEXTSPLIT(P6," "),,1),"")} -> Thrown | V6: =IF(NOT(U6=""),_xlfn.XLOOKUP(U6,'weapon masteries'!$A$10:$A$19,'weapon masteries'!$B$10:$B$19,"",0),"") -> If a weapon has the thrown property, you can throw the weapon to make a ranged attack. If the weapon is a melee weapon, you use the same ability modifier for that attack roll and damage roll that you would use for a melee attack with the weapon. For example, if you throw a handaxe, you use your Strength, but if you throw a dagger, you can use either your Strength or your Dexterity, since the dagger has the finesse property. | W6: {=IFERROR(INDEX(_xlfn.TEXTSPLIT(Q6," "),,1),"")} | X6: =IF(NOT(W6=""),_xlfn.XLOOKUP(W6,'weapon masteries'!$A$10:$A$19,'weapon masteries'!$B$10:$B$19,"",0),"") | Y6: {=IFERROR(INDEX(_xlfn.TEXTSPLIT(R6," "),,1),"")} | Z6: =IF(NOT(Y6=""),_xlfn.XLOOKUP(Y6,'weapon masteries'!$A$10:$A$19,'weapon masteries'!$B$10:$B$19,"",0),"") | AA6: {=IFERROR(INDEX(_xlfn.TEXTSPLIT(S6," "),,1),"")} | AB6: =IF(NOT(AA6=""),_xlfn.XLOOKUP(AA6,'weapon masteries'!$A$10:$A$19,'weapon masteries'!$B$10:$B$19,"",0),"") | AC6: {=IFERROR(INDEX(_xlfn.TEXTSPLIT(T6," "),,1),"")} | AD6: =IF(NOT(AC6=""),_xlfn.XLOOKUP(AC6,'weapon masteries'!$A$10:$A$20,'weapon masteries'!$B$10:$B$20,"",0),"")
A7: Melee or Ranged Weapon Attack | B7: Light Hammer (2014 edition) | C7: Max of Strength or Dexterity | D7: reach 5 ft or range 20/60 ft | E7: 1d4 | F7: bludgeoning | G7: Light, Thrown (20/60) | J7: =A7&": [ATK_MOD] to hit, "&D7&", one target. Hit: [DAMAGE] "&F7&" damage. "&I7 -> Melee or Ranged Weapon Attack: [ATK_MOD] to hit, reach 5 ft or range 20/60 ft, one target. Hit: [DAMAGE] bludgeoning damage. | L7: =IF(NOT(G7=""),IF(COUNTA(P7:T7)>1,"Properties: ","Property: ")&U7&" ("&V7&")"&IF(NOT(W7=""),", "&W7&" ("&X7&")"&IF(NOT(Y7=""),", "&Y7&" ("&Z7&")"&IF(NOT(AA7=""),", "&AB7&" ("&AC7&")",""),""),""),"") -> Properties: Light (A light weapon is small and easy to handle, making it ideal for use when fighting with two weapons.), Thrown (If a weapon has the thrown property, you can throw the weapon to make a ranged attack. If the weapon is a melee weapon, you use the same ability modifier for that attack roll and damage roll that you would use for a melee attack with the weapon. For example, if you throw a handaxe, you use your Strength, but if you throw a dagger, you can use either your Strength or your Dexterity, since the dagger has the finesse property.) | P7: {=IFERROR(_xlfn.TEXTSPLIT(G7,", ",,TRUE),"")} -> Light | Q7: Thrown (20/60) | U7: {=IFERROR(INDEX(_xlfn.TEXTSPLIT(P7," "),,1),"")} -> Light | V7: =IF(NOT(U7=""),_xlfn.XLOOKUP(U7,'weapon masteries'!$A$10:$A$19,'weapon masteries'!$B$10:$B$19,"",0),"") -> A light weapon is small and easy to handle, making it ideal for use when fighting with two weapons. | W7: {=IFERROR(INDEX(_xlfn.TEXTSPLIT(Q7," "),,1),"")} -> Thrown | X7: =IF(NOT(W7=""),_xlfn.XLOOKUP(W7,'weapon masteries'!$A$10:$A$19,'weapon masteries'!$B$10:$B$19,"",0),"") -> If a weapon has the thrown property, you can throw the weapon to make a ranged attack. If the weapon is a melee weapon, you use the same ability modifier for that attack roll and damage roll that you would use for a melee attack with the weapon. For example, if you throw a handaxe, you use your Strength, but if you throw a dagger, you can use either your Strength or your Dexterity, since the dagger has the finesse property. | Y7: {=IFERROR(INDEX(_xlfn.TEXTSPLIT(R7," "),,1),"")} | Z7: =IF(NOT(Y7=""),_xlfn.XLOOKUP(Y7,'weapon masteries'!$A$10:$A$19,'weapon masteries'!$B$10:$B$19,"",0),"") | AA7: {=IFERROR(INDEX(_xlfn.TEXTSPLIT(S7," "),,1),"")} | AB7: =IF(NOT(AA7=""),_xlfn.XLOOKUP(AA7,'weapon masteries'!$A$10:$A$19,'weapon masteries'!$B$10:$B$19,"",0),"") | AC7: {=IFERROR(INDEX(_xlfn.TEXTSPLIT(T7," "),,1),"")} | AD7: =IF(NOT(AC7=""),_xlfn.XLOOKUP(AC7,'weapon masteries'!$A$10:$A$20,'weapon masteries'!$B$10:$B$20,"",0),"")
A8: Melee Weapon Attack | B8: Mace (2014 edition) | C8: Strength | D8: reach 5 ft | E8: 1d6 | F8: bludgeoning | J8: =A8&": [ATK_MOD] to hit, "&D8&", one target. Hit: [DAMAGE] "&F8&" damage. "&I8 -> Melee Weapon Attack: [ATK_MOD] to hit, reach 5 ft, one target. Hit: [DAMAGE] bludgeoning damage. | L8: =IF(NOT(G8=""),IF(COUNTA(P8:T8)>1,"Properties: ","Property: ")&U8&" ("&V8&")"&IF(NOT(W8=""),", "&W8&" ("&X8&")"&IF(NOT(Y8=""),", "&Y8&" ("&Z8&")"&IF(NOT(AA8=""),", "&AB8&" ("&AC8&")",""),""),""),"") | P8: {=IFERROR(_xlfn.TEXTSPLIT(G8,", ",,TRUE),"")} | U8: {=IFERROR(INDEX(_xlfn.TEXTSPLIT(P8," "),,1),"")} | V8: =IF(NOT(U8=""),_xlfn.XLOOKUP(U8,'weapon masteries'!$A$10:$A$19,'weapon masteries'!$B$10:$B$19,"",0),"") | W8: {=IFERROR(INDEX(_xlfn.TEXTSPLIT(Q8," "),,1),"")} | X8: =IF(NOT(W8=""),_xlfn.XLOOKUP(W8,'weapon masteries'!$A$10:$A$19,'weapon masteries'!$B$10:$B$19,"",0),"") | Y8: {=IFERROR(INDEX(_xlfn.TEXTSPLIT(R8," "),,1),"")} | Z8: =IF(NOT(Y8=""),_xlfn.XLOOKUP(Y8,'weapon masteries'!$A$10:$A$19,'weapon masteries'!$B$10:$B$19,"",0),"") | AA8: {=IFERROR(INDEX(_xlfn.TEXTSPLIT(S8," "),,1),"")} | AB8: =IF(NOT(AA8=""),_xlfn.XLOOKUP(AA8,'weapon masteries'!$A$10:$A$19,'weapon masteries'!$B$10:$B$19,"",0),"") | AC8: {=IFERROR(INDEX(_xlfn.TEXTSPLIT(T8," "),,1),"")} | AD8: =IF(NOT(AC8=""),_xlfn.XLOOKUP(AC8,'weapon masteries'!$A$10:$A$20,'weapon masteries'!$B$10:$B$20,"",0),"")
A9: Melee Weapon Attack | B9: Quarterstaff (2014 edition) | C9: Strength | D9: reach 5 ft | E9: 1d6 | F9: bludgeoning | G9: Versatile (1d8) | J9: =A9&": [ATK_MOD] to hit, "&D9&", one target. Hit: [DAMAGE] "&F9&" damage. "&I9 -> Melee Weapon Attack: [ATK_MOD] to hit, reach 5 ft, one target. Hit: [DAMAGE] bludgeoning damage. | L9: =IF(NOT(G9=""),IF(COUNTA(P9:T9)>1,"Properties: ","Property: ")&U9&" ("&V9&")"&IF(NOT(W9=""),", "&W9&" ("&X9&")"&IF(NOT(Y9=""),", "&Y9&" ("&Z9&")"&IF(NOT(AA9=""),", "&AB9&" ("&AC9&")",""),""),""),"") -> Property: Versatile (This weapon can be used with one or two hands. A damage value in parentheses appears with the property—the damage when the weapon is used with two hands to make a melee attack.) | P9: {=IFERROR(_xlfn.TEXTSPLIT(G9,", ",,TRUE),"")} -> Versatile (1d8) | U9: {=IFERROR(INDEX(_xlfn.TEXTSPLIT(P9," "),,1),"")} -> Versatile | V9: =IF(NOT(U9=""),_xlfn.XLOOKUP(U9,'weapon masteries'!$A$10:$A$19,'weapon masteries'!$B$10:$B$19,"",0),"") -> This weapon can be used with one or two hands. A damage value in parentheses appears with the property—the damage when the weapon is used with two hands to make a melee attack. | W9: {=IFERROR(INDEX(_xlfn.TEXTSPLIT(Q9," "),,1),"")} | X9: =IF(NOT(W9=""),_xlfn.XLOOKUP(W9,'weapon masteries'!$A$10:$A$19,'weapon masteries'!$B$10:$B$19,"",0),"") | Y9: {=IFERROR(INDEX(_xlfn.TEXTSPLIT(R9," "),,1),"")} | Z9: =IF(NOT(Y9=""),_xlfn.XLOOKUP(Y9,'weapon masteries'!$A$10:$A$19,'weapon masteries'!$B$10:$B$19,"",0),"") | AA9: {=IFERROR(INDEX(_xlfn.TEXTSPLIT(S9," "),,1),"")} | AB9: =IF(NOT(AA9=""),_xlfn.XLOOKUP(AA9,'weapon masteries'!$A$10:$A$19,'weapon masteries'!$B$10:$B$19,"",0),"") | AC9: {=IFERROR(INDEX(_xlfn.TEXTSPLIT(T9," "),,1),"")} | AD9: =IF(NOT(AC9=""),_xlfn.XLOOKUP(AC9,'weapon masteries'!$A$10:$A$20,'weapon masteries'!$B$10:$B$20,"",0),"")
A10: Melee Weapon Attack | B10: Sickle (2014 edition) | C10: Max of Strength or Dexterity | D10: reach 5 ft | E10: 1d4 | F10: slashing | G10: Light | J10: =A10&": [ATK_MOD] to hit, "&D10&", one target. Hit: [DAMAGE] "&F10&" damage. "&I10 -> Melee Weapon Attack: [ATK_MOD] to hit, reach 5 ft, one target. Hit: [DAMAGE] slashing damage. | L10: =IF(NOT(G10=""),IF(COUNTA(P10:T10)>1,"Properties: ","Property: ")&U10&" ("&V10&")"&IF(NOT(W10=""),", "&W10&" ("&X10&")"&IF(NOT(Y10=""),", "&Y10&" ("&Z10&")"&IF(NOT(AA10=""),", "&AB10&" ("&AC10&")",""),""),""),"") -> Property: Light (A light weapon is small and easy to handle, making it ideal for use when fighting with two weapons.) | P10: {=IFERROR(_xlfn.TEXTSPLIT(G10,", ",,TRUE),"")} -> Light | U10: {=IFERROR(INDEX(_xlfn.TEXTSPLIT(P10," "),,1),"")} -> Light | V10: =IF(NOT(U10=""),_xlfn.XLOOKUP(U10,'weapon masteries'!$A$10:$A$19,'weapon masteries'!$B$10:$B$19,"",0),"") -> A light weapon is small and easy to handle, making it ideal for use when fighting with two weapons. | W10: {=IFERROR(INDEX(_xlfn.TEXTSPLIT(Q10," "),,1),"")} | X10: =IF(NOT(W10=""),_xlfn.XLOOKUP(W10,'weapon masteries'!$A$10:$A$19,'weapon masteries'!$B$10:$B$19,"",0),"") | Y10: {=IFERROR(INDEX(_xlfn.TEXTSPLIT(R10," "),,1),"")} | Z10: =IF(NOT(Y10=""),_xlfn.XLOOKUP(Y10,'weapon masteries'!$A$10:$A$19,'weapon masteries'!$B$10:$B$19,"",0),"") | AA10: {=IFERROR(INDEX(_xlfn.TEXTSPLIT(S10," "),,1),"")} | AB10: =IF(NOT(AA10=""),_xlfn.XLOOKUP(AA10,'weapon masteries'!$A$10:$A$19,'weapon masteries'!$B$10:$B$19,"",0),"") | AC10: {=IFERROR(INDEX(_xlfn.TEXTSPLIT(T10," "),,1),"")} | AD10: =IF(NOT(AC10=""),_xlfn.XLOOKUP(AC10,'weapon masteries'!$A$10:$A$20,'weapon masteries'!$B$10:$B$20,"",0),"")
A11: Melee or Ranged Weapon Attack | B11: Spear (2014 edition) | C11: Strength | D11: reach 5 ft or range 20/60 ft | E11: 1d6 | F11: piercing | G11: Thrown (20/60), Versatile (1d8) | J11: =A11&": [ATK_MOD] to hit, "&D11&", one target. Hit: [DAMAGE] "&F11&" damage. "&I11 -> Melee or Ranged Weapon Attack: [ATK_MOD] to hit, reach 5 ft or range 20/60 ft, one target. Hit: [DAMAGE] piercing damage. | L11: =IF(NOT(G11=""),IF(COUNTA(P11:T11)>1,"Properties: ","Property: ")&U11&" ("&V11&")"&IF(NOT(W11=""),", "&W11&" ("&X11&")"&IF(NOT(Y11=""),", "&Y11&" ("&Z11&")"&IF(NOT(AA11=""),", "&AB11&" ("&AC11&")",""),""),""),"") -> Properties: Thrown (If a weapon has the thrown property, you can throw the weapon to make a ranged attack. If the weapon is a melee weapon, you use the same ability modifier for that attack roll and damage roll that you would use for a melee attack with the weapon. For example, if you throw a handaxe, you use your Strength, but if you throw a dagger, you can use either your Strength or your Dexterity, since the dagger has the finesse property.), Versatile (This weapon can be used with one or two hands. A damage value in parentheses appears with the property—the damage when the weapon is used with two hands to make a melee attack.) | P11: {=IFERROR(_xlfn.TEXTSPLIT(G11,", ",,TRUE),"")} -> Thrown (20/60) | Q11: Versatile (1d8) | U11: {=IFERROR(INDEX(_xlfn.TEXTSPLIT(P11," "),,1),"")} -> Thrown | V11: =IF(NOT(U11=""),_xlfn.XLOOKUP(U11,'weapon masteries'!$A$10:$A$19,'weapon masteries'!$B$10:$B$19,"",0),"") -> If a weapon has the thrown property, you can throw the weapon to make a ranged attack. If the weapon is a melee weapon, you use the same ability modifier for that attack roll and damage roll that you would use for a melee attack with the weapon. For example, if you throw a handaxe, you use your Strength, but if you throw a dagger, you can use either your Strength or your Dexterity, since the dagger has the finesse property. | W11: {=IFERROR(INDEX(_xlfn.TEXTSPLIT(Q11," "),,1),"")} -> Versatile | X11: =IF(NOT(W11=""),_xlfn.XLOOKUP(W11,'weapon masteries'!$A$10:$A$19,'weapon masteries'!$B$10:$B$19,"",0),"") -> This weapon can be used with one or two hands. A damage value in parentheses appears with the property—the damage when the weapon is used with two hands to make a melee attack. | Y11: {=IFERROR(INDEX(_xlfn.TEXTSPLIT(R11," "),,1),"")} | Z11: =IF(NOT(Y11=""),_xlfn.XLOOKUP(Y11,'weapon masteries'!$A$10:$A$19,'weapon masteries'!$B$10:$B$19,"",0),"") | AA11: {=IFERROR(INDEX(_xlfn.TEXTSPLIT(S11," "),,1),"")} | AB11: =IF(NOT(AA11=""),_xlfn.XLOOKUP(AA11,'weapon masteries'!$A$10:$A$19,'weapon masteries'!$B$10:$B$19,"",0),"") | AC11: {=IFERROR(INDEX(_xlfn.TEXTSPLIT(T11," "),,1),"")} | AD11: =IF(NOT(AC11=""),_xlfn.XLOOKUP(AC11,'weapon masteries'!$A$10:$A$20,'weapon masteries'!$B$10:$B$20,"",0),"")
A12: Ranged Weapon Attack | B12: Light Crossbow (2014 edition) | C12: Dexterity | D12: range 80/320 ft | E12: 1d8 | F12: piercing | G12: Ammunition, Range (80/320), Loading, Two-Handed | J12: =A12&": [ATK_MOD] to hit, "&D12&", one target. Hit: [DAMAGE] "&F12&" damage. "&I12 -> Ranged Weapon Attack: [ATK_MOD] to hit, range 80/320 ft, one target. Hit: [DAMAGE] piercing damage. | L12: =IF(NOT(G12=""),IF(COUNTA(P12:T12)>1,"Properties: ","Property: ")&U12&" ("&V12&")"&IF(NOT(W12=""),", "&W12&" ("&X12&")"&IF(NOT(Y12=""),", "&Y12&" ("&Z12&")"&IF(NOT(AA12=""),", "&AB12&" ("&AC12&")",""),""),""),"") -> Properties: Ammunition (You can use a weapon that has the ammunition property to make a ranged attack only if you have ammunition to fire from the weapon. Each time you attack with the weapon, you expend one piece of ammunition. Drawing the ammunition from a quiver, case, or other container is part of the attack. Loading a one-handed weapon requires a free hand. At the end of the battle, you can recover half your expended ammunition by taking a minute to search the battlefield. If you use a weapon that has the ammunition property to make a melee attack, you treat the weapon as an improvised weapon. A sling must be loaded to deal any damage when used in this way.), Range (A weapon that can be used to make a ranged attack has a range shown in parentheses after the ammunition or thrown property. The range lists two numbers. The first is the weapon’s normal range in feet, and the second indicates the weapon’s maximum range. When attacking a target beyond normal range, you have disadvantage on the attack roll. You can’t attack a target beyond the weapon’s long range.), Loading (Because of the time required to load this weapon, you can fire only one piece of ammunition from it when you use an action, bonus action, or reaction to fire it, regardless of the number of attacks you can normally make.), This weapon requires two hands to use. This property is relevant only when you attack with the weapon, not when you simply hold it. () | P12: {=IFERROR(_xlfn.TEXTSPLIT(G12,", ",,TRUE),"")} -> Ammunition | Q12: Range (80/320) | R12: Loading | S12: Two-Handed | U12: {=IFERROR(INDEX(_xlfn.TEXTSPLIT(P12," "),,1),"")} -> Ammunition | V12: =IF(NOT(U12=""),_xlfn.XLOOKUP(U12,'weapon masteries'!$A$10:$A$19,'weapon masteries'!$B$10:$B$19,"",0),"") -> You can use a weapon that has the ammunition property to make a ranged attack only if you have ammunition to fire from the weapon. Each time you attack with the weapon, you expend one piece of ammunition. Drawing the ammunition from a quiver, case, or other container is part of the attack. Loading a one-handed weapon requires a free hand. At the end of the battle, you can recover half your expended ammunition by taking a minute to search the battlefield. If you use a weapon that has the ammunition property to make a melee attack, you treat the weapon as an improvised weapon. A sling must be loaded to deal any damage when used in this way. | W12: {=IFERROR(INDEX(_xlfn.TEXTSPLIT(Q12," "),,1),"")} -> Range | X12: =IF(NOT(W12=""),_xlfn.XLOOKUP(W12,'weapon masteries'!$A$10:$A$19,'weapon masteries'!$B$10:$B$19,"",0),"") -> A weapon that can be used to make a ranged attack has a range shown in parentheses after the ammunition or thrown property. The range lists two numbers. The first is the weapon’s normal range in feet, and the second indicates the weapon’s maximum range. When attacking a target beyond normal range, you have disadvantage on the attack roll. You can’t attack a target beyond the weapon’s long range. | Y12: {=IFERROR(INDEX(_xlfn.TEXTSPLIT(R12," "),,1),"")} -> Loading | Z12: =IF(NOT(Y12=""),_xlfn.XLOOKUP(Y12,'weapon masteries'!$A$10:$A$19,'weapon masteries'!$B$10:$B$19,"",0),"") -> Because of the time required to load this weapon, you can fire only one piece of ammunition from it when you use an action, bonus action, or reaction to fire it, regardless of the number of attacks you can normally make. | AA12: {=IFERROR(INDEX(_xlfn.TEXTSPLIT(S12," "),,1),"")} -> Two-Handed | AB12: =IF(NOT(AA12=""),_xlfn.XLOOKUP(AA12,'weapon masteries'!$A$10:$A$19,'weapon masteries'!$B$10:$B$19,"",0),"") -> This weapon requires two hands to use. This property is relevant only when you attack with the weapon, not when you simply hold it. | AC12: {=IFERROR(INDEX(_xlfn.TEXTSPLIT(T12," "),,1),"")} | AD12: =IF(NOT(AC12=""),_xlfn.XLOOKUP(AC12,'weapon masteries'!$A$10:$A$20,'weapon masteries'!$B$10:$B$20,"",0),"")
A13: Ranged Weapon Attack | B13: Dart (2014 edition) | C13: Dexterity | D13: range 20/60 ft | E13: 1d4 | F13: piercing | G13: Finesse, Thrown (20/60) | J13: =A13&": [ATK_MOD] to hit, "&D13&", one target. Hit: [DAMAGE] "&F13&" damage. "&I13 -> Ranged Weapon Attack: [ATK_MOD] to hit, range 20/60 ft, one target. Hit: [DAMAGE] piercing damage. | L13: =IF(NOT(G13=""),IF(COUNTA(P13:T13)>1,"Properties: ","Property: ")&U13&" ("&V13&")"&IF(NOT(W13=""),", "&W13&" ("&X13&")"&IF(NOT(Y13=""),", "&Y13&" ("&Z13&")"&IF(NOT(AA13=""),", "&AB13&" ("&AC13&")",""),""),""),"") -> Properties: Finesse (When making an attack with a finesse weapon, you use your choice of your Strength or Dexterity modifier for the attack and damage rolls. You must use the same modifier for both rolls.), Thrown (If a weapon has the thrown property, you can throw the weapon to make a ranged attack. If the weapon is a melee weapon, you use the same ability modifier for that attack roll and damage roll that you would use for a melee attack with the weapon. For example, if you throw a handaxe, you use your Strength, but if you throw a dagger, you can use either your Strength or your Dexterity, since the dagger has the finesse property.) | P13: {=IFERROR(_xlfn.TEXTSPLIT(G13,", ",,TRUE),"")} -> Finesse | Q13: Thrown (20/60) | U13: {=IFERROR(INDEX(_xlfn.TEXTSPLIT(P13," "),,1),"")} -> Finesse | V13: =IF(NOT(U13=""),_xlfn.XLOOKUP(U13,'weapon masteries'!$A$10:$A$19,'weapon masteries'!$B$10:$B$19,"",0),"") -> When making an attack with a finesse weapon, you use your choice of your Strength or Dexterity modifier for the attack and damage rolls. You must use the same modifier for both rolls. | W13: {=IFERROR(INDEX(_xlfn.TEXTSPLIT(Q13," "),,1),"")} -> Thrown | X13: =IF(NOT(W13=""),_xlfn.XLOOKUP(W13,'weapon masteries'!$A$10:$A$19,'weapon masteries'!$B$10:$B$19,"",0),"") -> If a weapon has the thrown property, you can throw the weapon to make a ranged attack. If the weapon is a melee weapon, you use the same ability modifier for that attack roll and damage roll that you would use for a melee attack with the weapon. For example, if you throw a handaxe, you use your Strength, but if you throw a dagger, you can use either your Strength or your Dexterity, since the dagger has the finesse property. | Y13: {=IFERROR(INDEX(_xlfn.TEXTSPLIT(R13," "),,1),"")} | Z13: =IF(NOT(Y13=""),_xlfn.XLOOKUP(Y13,'weapon masteries'!$A$10:$A$19,'weapon masteries'!$B$10:$B$19,"",0),"") | AA13: {=IFERROR(INDEX(_xlfn.TEXTSPLIT(S13," "),,1),"")} | AB13: =IF(NOT(AA13=""),_xlfn.XLOOKUP(AA13,'weapon masteries'!$A$10:$A$19,'weapon masteries'!$B$10:$B$19,"",0),"") | AC13: {=IFERROR(INDEX(_xlfn.TEXTSPLIT(T13," "),,1),"")} | AD13: =IF(NOT(AC13=""),_xlfn.XLOOKUP(AC13,'weapon masteries'!$A$10:$A$20,'weapon masteries'!$B$10:$B$20,"",0),"")
A14: Ranged Weapon Attack | B14: Shortbow (2014 edition) | C14: Dexterity | D14: range 80/320 ft | E14: 1d6 | F14: piercing | G14: Ammunition, Range (80/320), Two-Handed | J14: =A14&": [ATK_MOD] to hit, "&D14&", one target. Hit: [DAMAGE] "&F14&" damage. "&I14 -> Ranged Weapon Attack: [ATK_MOD] to hit, range 80/320 ft, one target. Hit: [DAMAGE] piercing damage. | L14: =IF(NOT(G14=""),IF(COUNTA(P14:T14)>1,"Properties: ","Property: ")&U14&" ("&V14&")"&IF(NOT(W14=""),", "&W14&" ("&X14&")"&IF(NOT(Y14=""),", "&Y14&" ("&Z14&")"&IF(NOT(AA14=""),", "&AB14&" ("&AC14&")",""),""),""),"") -> Properties: Ammunition (You can use a weapon that has the ammunition property to make a ranged attack only if you have ammunition to fire from the weapon. Each time you attack with the weapon, you expend one piece of ammunition. Drawing the ammunition from a quiver, case, or other container is part of the attack. Loading a one-handed weapon requires a free hand. At the end of the battle, you can recover half your expended ammunition by taking a minute to search the battlefield. If you use a weapon that has the ammunition property to make a melee attack, you treat the weapon as an improvised weapon. A sling must be loaded to deal any damage when used in this way.), Range (A weapon that can be used to make a ranged attack has a range shown in parentheses after the ammunition or thrown property. The range lists two numbers. The first is the weapon’s normal range in feet, and the second indicates the weapon’s maximum range. When attacking a target beyond normal range, you have disadvantage on the attack roll. You can’t attack a target beyond the weapon’s long range.), Two-Handed (This weapon requires two hands to use. This property is relevant only when you attack with the weapon, not when you simply hold it.) | P14: {=IFERROR(_xlfn.TEXTSPLIT(G14,", ",,TRUE),"")} -> Ammunition | Q14: Range (80/320) | R14: Two-Handed | U14: {=IFERROR(INDEX(_xlfn.TEXTSPLIT(P14," "),,1),"")} -> Ammunition | V14: =IF(NOT(U14=""),_xlfn.XLOOKUP(U14,'weapon masteries'!$A$10:$A$19,'weapon masteries'!$B$10:$B$19,"",0),"") -> You can use a weapon that has the ammunition property to make a ranged attack only if you have ammunition to fire from the weapon. Each time you attack with the weapon, you expend one piece of ammunition. Drawing the ammunition from a quiver, case, or other container is part of the attack. Loading a one-handed weapon requires a free hand. At the end of the battle, you can recover half your expended ammunition by taking a minute to search the battlefield. If you use a weapon that has the ammunition property to make a melee attack, you treat the weapon as an improvised weapon. A sling must be loaded to deal any damage when used in this way. | W14: {=IFERROR(INDEX(_xlfn.TEXTSPLIT(Q14," "),,1),"")} -> Range | X14: =IF(NOT(W14=""),_xlfn.XLOOKUP(W14,'weapon masteries'!$A$10:$A$19,'weapon masteries'!$B$10:$B$19,"",0),"") -> A weapon that can be used to make a ranged attack has a range shown in parentheses after the ammunition or thrown property. The range lists two numbers. The first is the weapon’s normal range in feet, and the second indicates the weapon’s maximum range. When attacking a target beyond normal range, you have disadvantage on the attack roll. You can’t attack a target beyond the weapon’s long range. | Y14: {=IFERROR(INDEX(_xlfn.TEXTSPLIT(R14," "),,1),"")} -> Two-Handed | Z14: =IF(NOT(Y14=""),_xlfn.XLOOKUP(Y14,'weapon masteries'!$A$10:$A$19,'weapon masteries'!$B$10:$B$19,"",0),"") -> This weapon requires two hands to use. This property is relevant only when you attack with the weapon, not when you simply hold it. | AA14: {=IFERROR(INDEX(_xlfn.TEXTSPLIT(S14," "),,1),"")} | AB14: =IF(NOT(AA14=""),_xlfn.XLOOKUP(AA14,'weapon masteries'!$A$10:$A$19,'weapon masteries'!$B$10:$B$19,"",0),"") | AC14: {=IFERROR(INDEX(_xlfn.TEXTSPLIT(T14," "),,1),"")} | AD14: =IF(NOT(AC14=""),_xlfn.XLOOKUP(AC14,'weapon masteries'!$A$10:$A$20,'weapon masteries'!$B$10:$B$20,"",0),"")
A15: Ranged Weapon Attack | B15: Sling (2014 edition) | C15: Dexterity | D15: range 30/120 ft | E15: 1d4 | F15: bludgeoning | G15: Ammunition, Range (30/120) | J15: =A15&": [ATK_MOD] to hit, "&D15&", one target. Hit: [DAMAGE] "&F15&" damage. "&I15 -> Ranged Weapon Attack: [ATK_MOD] to hit, range 30/120 ft, one target. Hit: [DAMAGE] bludgeoning damage. | L15: =IF(NOT(G15=""),IF(COUNTA(P15:T15)>1,"Properties: ","Property: ")&U15&" ("&V15&")"&IF(NOT(W15=""),", "&W15&" ("&X15&")"&IF(NOT(Y15=""),", "&Y15&" ("&Z15&")"&IF(NOT(AA15=""),", "&AB15&" ("&AC15&")",""),""),""),"") -> Properties: Ammunition (You can use a weapon that has the ammunition property to make a ranged attack only if you have ammunition to fire from the weapon. Each time you attack with the weapon, you expend one piece of ammunition. Drawing the ammunition from a quiver, case, or other container is part of the attack. Loading a one-handed weapon requires a free hand. At the end of the battle, you can recover half your expended ammunition by taking a minute to search the battlefield. If you use a weapon that has the ammunition property to make a melee attack, you treat the weapon as an improvised weapon. A sling must be loaded to deal any damage when used in this way.), Range (A weapon that can be used to make a ranged attack has a range shown in parentheses after the ammunition or thrown property. The range lists two numbers. The first is the weapon’s normal range in feet, and the second indicates the weapon’s maximum range. When attacking a target beyond normal range, you have disadvantage on the attack roll. You can’t attack a target beyond the weapon’s long range.) | P15: {=IFERROR(_xlfn.TEXTSPLIT(G15,", ",,TRUE),"")} -> Ammunition | Q15: Range (30/120) | U15: {=IFERROR(INDEX(_xlfn.TEXTSPLIT(P15," "),,1),"")} -> Ammunition | V15: =IF(NOT(U15=""),_xlfn.XLOOKUP(U15,'weapon masteries'!$A$10:$A$19,'weapon masteries'!$B$10:$B$19,"",0),"") -> You can use a weapon that has the ammunition property to make a ranged attack only if you have ammunition to fire from the weapon. Each time you attack with the weapon, you expend one piece of ammunition. Drawing the ammunition from a quiver, case, or other container is part of the attack. Loading a one-handed weapon requires a free hand. At the end of the battle, you can recover half your expended ammunition by taking a minute to search the battlefield. If you use a weapon that has the ammunition property to make a melee attack, you treat the weapon as an improvised weapon. A sling must be loaded to deal any damage when used in this way. | W15: {=IFERROR(INDEX(_xlfn.TEXTSPLIT(Q15," "),,1),"")} -> Range | X15: =IF(NOT(W15=""),_xlfn.XLOOKUP(W15,'weapon masteries'!$A$10:$A$19,'weapon masteries'!$B$10:$B$19,"",0),"") -> A weapon that can be used to make a ranged attack has a range shown in parentheses after the ammunition or thrown property. The range lists two numbers. The first is the weapon’s normal range in feet, and the second indicates the weapon’s maximum range. When attacking a target beyond normal range, you have disadvantage on the attack roll. You can’t attack a target beyond the weapon’s long range. | Y15: {=IFERROR(INDEX(_xlfn.TEXTSPLIT(R15," "),,1),"")} | Z15: =IF(NOT(Y15=""),_xlfn.XLOOKUP(Y15,'weapon masteries'!$A$10:$A$19,'weapon masteries'!$B$10:$B$19,"",0),"") | AA15: {=IFERROR(INDEX(_xlfn.TEXTSPLIT(S15," "),,1),"")} | AB15: =IF(NOT(AA15=""),_xlfn.XLOOKUP(AA15,'weapon masteries'!$A$10:$A$19,'weapon masteries'!$B$10:$B$19,"",0),"") | AC15: {=IFERROR(INDEX(_xlfn.TEXTSPLIT(T15," "),,1),"")} | AD15: =IF(NOT(AC15=""),_xlfn.XLOOKUP(AC15,'weapon masteries'!$A$10:$A$20,'weapon masteries'!$B$10:$B$20,"",0),"")
A16: Melee Weapon Attack | B16: Battleaxe (2014 edition) | C16: Strength | D16: reach 5 ft | E16: 1d8 | F16: slashing | G16: Versatile (1d10) | J16: =A16&": [ATK_MOD] to hit, "&D16&", one target. Hit: [DAMAGE] "&F16&" damage. "&I16 -> Melee Weapon Attack: [ATK_MOD] to hit, reach 5 ft, one target. Hit: [DAMAGE] slashing damage. | L16: =IF(NOT(G16=""),IF(COUNTA(P16:T16)>1,"Properties: ","Property: ")&U16&" ("&V16&")"&IF(NOT(W16=""),", "&W16&" ("&X16&")"&IF(NOT(Y16=""),", "&Y16&" ("&Z16&")"&IF(NOT(AA16=""),", "&AB16&" ("&AC16&")",""),""),""),"") -> Property: Versatile (This weapon can be used with one or two hands. A damage value in parentheses appears with the property—the damage when the weapon is used with two hands to make a melee attack.) | P16: {=IFERROR(_xlfn.TEXTSPLIT(G16,", ",,TRUE),"")} -> Versatile (1d10) | U16: {=IFERROR(INDEX(_xlfn.TEXTSPLIT(P16," "),,1),"")} -> Versatile | V16: =IF(NOT(U16=""),_xlfn.XLOOKUP(U16,'weapon masteries'!$A$10:$A$19,'weapon masteries'!$B$10:$B$19,"",0),"") -> This weapon can be used with one or two hands. A damage value in parentheses appears with the property—the damage when the weapon is used with two hands to make a melee attack. | W16: {=IFERROR(INDEX(_xlfn.TEXTSPLIT(Q16," "),,1),"")} | X16: =IF(NOT(W16=""),_xlfn.XLOOKUP(W16,'weapon masteries'!$A$10:$A$19,'weapon masteries'!$B$10:$B$19,"",0),"") | Y16: {=IFERROR(INDEX(_xlfn.TEXTSPLIT(R16," "),,1),"")} | Z16: =IF(NOT(Y16=""),_xlfn.XLOOKUP(Y16,'weapon masteries'!$A$10:$A$19,'weapon masteries'!$B$10:$B$19,"",0),"") | AA16: {=IFERROR(INDEX(_xlfn.TEXTSPLIT(S16," "),,1),"")} | AB16: =IF(NOT(AA16=""),_xlfn.XLOOKUP(AA16,'weapon masteries'!$A$10:$A$19,'weapon masteries'!$B$10:$B$19,"",0),"") | AC16: {=IFERROR(INDEX(_xlfn.TEXTSPLIT(T16," "),,1),"")} | AD16: =IF(NOT(AC16=""),_xlfn.XLOOKUP(AC16,'weapon masteries'!$A$10:$A$20,'weapon masteries'!$B$10:$B$20,"",0),"")
A17: Melee Weapon Attack | B17: Flail (2014 edition) | C17: Strength | D17: reach 5 ft | E17: 1d8 | F17: bludgeoning | J17: =A17&": [ATK_MOD] to hit, "&D17&", one target. Hit: [DAMAGE] "&F17&" damage. "&I17 -> Melee Weapon Attack: [ATK_MOD] to hit, reach 5 ft, one target. Hit: [DAMAGE] bludgeoning damage. | L17: =IF(NOT(G17=""),IF(COUNTA(P17:T17)>1,"Properties: ","Property: ")&U17&" ("&V17&")"&IF(NOT(W17=""),", "&W17&" ("&X17&")"&IF(NOT(Y17=""),", "&Y17&" ("&Z17&")"&IF(NOT(AA17=""),", "&AB17&" ("&AC17&")",""),""),""),"") | P17: {=IFERROR(_xlfn.TEXTSPLIT(G17,", ",,TRUE),"")} | U17: {=IFERROR(INDEX(_xlfn.TEXTSPLIT(P17," "),,1),"")} | V17: =IF(NOT(U17=""),_xlfn.XLOOKUP(U17,'weapon masteries'!$A$10:$A$19,'weapon masteries'!$B$10:$B$19,"",0),"") | W17: {=IFERROR(INDEX(_xlfn.TEXTSPLIT(Q17," "),,1),"")} | X17: =IF(NOT(W17=""),_xlfn.XLOOKUP(W17,'weapon masteries'!$A$10:$A$19,'weapon masteries'!$B$10:$B$19,"",0),"") | Y17: {=IFERROR(INDEX(_xlfn.TEXTSPLIT(R17," "),,1),"")} | Z17: =IF(NOT(Y17=""),_xlfn.XLOOKUP(Y17,'weapon masteries'!$A$10:$A$19,'weapon masteries'!$B$10:$B$19,"",0),"") | AA17: {=IFERROR(INDEX(_xlfn.TEXTSPLIT(S17," "),,1),"")} | AB17: =IF(NOT(AA17=""),_xlfn.XLOOKUP(AA17,'weapon masteries'!$A$10:$A$19,'weapon masteries'!$B$10:$B$19,"",0),"") | AC17: {=IFERROR(INDEX(_xlfn.TEXTSPLIT(T17," "),,1),"")} | AD17: =IF(NOT(AC17=""),_xlfn.XLOOKUP(AC17,'weapon masteries'!$A$10:$A$20,'weapon masteries'!$B$10:$B$20,"",0),"")
A18: Melee Weapon Attack | B18: Glaive (2014 edition) | C18: Strength | D18: reach 10 ft | E18: 1d10 | F18: slashing | G18: Heavy, Reach, Two-Handed | J18: =A18&": [ATK_MOD] to hit, "&D18&", one target. Hit: [DAMAGE] "&F18&" damage. "&I18 -> Melee Weapon Attack: [ATK_MOD] to hit, reach 10 ft, one target. Hit: [DAMAGE] slashing damage. | L18: =IF(NOT(G18=""),IF(COUNTA(P18:T18)>1,"Properties: ","Property: ")&U18&" ("&V18&")"&IF(NOT(W18=""),", "&W18&" ("&X18&")"&IF(NOT(Y18=""),", "&Y18&" ("&Z18&")"&IF(NOT(AA18=""),", "&AB18&" ("&AC18&")",""),""),""),"") -> Properties: Heavy (Creatures that are Small or Tiny have disadvantage on attack rolls with heavy weapons. A heavy weapon's size and bulk make it too large for a Small or Tiny creature to use effectively.), Reach (This weapon adds 5 feet to your reach when you attack with it. This property also determines your reach for opportunity attacks with a reach weapon.), Two-Handed (This weapon requires two hands to use. This property is relevant only when you attack with the weapon, not when you simply hold it.) | P18: {=IFERROR(_xlfn.TEXTSPLIT(G18,", ",,TRUE),"")} -> Heavy | Q18: Reach | R18: Two-Handed | U18: {=IFERROR(INDEX(_xlfn.TEXTSPLIT(P18," "),,1),"")} -> Heavy | V18: =IF(NOT(U18=""),_xlfn.XLOOKUP(U18,'weapon masteries'!$A$10:$A$19,'weapon masteries'!$B$10:$B$19,"",0),"") -> Creatures that are Small or Tiny have disadvantage on attack rolls with heavy weapons. A heavy weapon's size and bulk make it too large for a Small or Tiny creature to use effectively. | W18: {=IFERROR(INDEX(_xlfn.TEXTSPLIT(Q18," "),,1),"")} -> Reach | X18: =IF(NOT(W18=""),_xlfn.XLOOKUP(W18,'weapon masteries'!$A$10:$A$19,'weapon masteries'!$B$10:$B$19,"",0),"") -> This weapon adds 5 feet to your reach when you attack with it. This property also determines your reach for opportunity attacks with a reach weapon. | Y18: {=IFERROR(INDEX(_xlfn.TEXTSPLIT(R18," "),,1),"")} -> Two-Handed | Z18: =IF(NOT(Y18=""),_xlfn.XLOOKUP(Y18,'weapon masteries'!$A$10:$A$19,'weapon masteries'!$B$10:$B$19,"",0),"") -> This weapon requires two hands to use. This property is relevant only when you attack with the weapon, not when you simply hold it. | AA18: {=IFERROR(INDEX(_xlfn.TEXTSPLIT(S18," "),,1),"")} | AB18: =IF(NOT(AA18=""),_xlfn.XLOOKUP(AA18,'weapon masteries'!$A$10:$A$19,'weapon masteries'!$B$10:$B$19,"",0),"") | AC18: {=IFERROR(INDEX(_xlfn.TEXTSPLIT(T18," "),,1),"")} | AD18: =IF(NOT(AC18=""),_xlfn.XLOOKUP(AC18,'weapon masteries'!$A$10:$A$20,'weapon masteries'!$B$10:$B$20,"",0),"")
A19: Melee Weapon Attack | B19: Greataxe (2014 edition) | C19: Strength | D19: reach 5 ft | E19: 1d12 | F19: slashing | G19: Heavy, Two-Handed | J19: =A19&": [ATK_MOD] to hit, "&D19&", one target. Hit: [DAMAGE] "&F19&" damage. "&I19 -> Melee Weapon Attack: [ATK_MOD] to hit, reach 5 ft, one target. Hit: [DAMAGE] slashing damage. | L19: =IF(NOT(G19=""),IF(COUNTA(P19:T19)>1,"Properties: ","Property: ")&U19&" ("&V19&")"&IF(NOT(W19=""),", "&W19&" ("&X19&")"&IF(NOT(Y19=""),", "&Y19&" ("&Z19&")"&IF(NOT(AA19=""),", "&AB19&" ("&AC19&")",""),""),""),"") -> Properties: Heavy (Creatures that are Small or Tiny have disadvantage on attack rolls with heavy weapons. A heavy weapon's size and bulk make it too large for a Small or Tiny creature to use effectively.), Two-Handed (This weapon requires two hands to use. This property is relevant only when you attack with the weapon, not when you simply hold it.) | P19: {=IFERROR(_xlfn.TEXTSPLIT(G19,", ",,TRUE),"")} -> Heavy | Q19: Two-Handed | U19: {=IFERROR(INDEX(_xlfn.TEXTSPLIT(P19," "),,1),"")} -> Heavy | V19: =IF(NOT(U19=""),_xlfn.XLOOKUP(U19,'weapon masteries'!$A$10:$A$19,'weapon masteries'!$B$10:$B$19,"",0),"") -> Creatures that are Small or Tiny have disadvantage on attack rolls with heavy weapons. A heavy weapon's size and bulk make it too large for a Small or Tiny creature to use effectively. | W19: {=IFERROR(INDEX(_xlfn.TEXTSPLIT(Q19," "),,1),"")} -> Two-Handed | X19: =IF(NOT(W19=""),_xlfn.XLOOKUP(W19,'weapon masteries'!$A$10:$A$19,'weapon masteries'!$B$10:$B$19,"",0),"") -> This weapon requires two hands to use. This property is relevant only when you attack with the weapon, not when you simply hold it. | Y19: {=IFERROR(INDEX(_xlfn.TEXTSPLIT(R19," "),,1),"")} | Z19: =IF(NOT(Y19=""),_xlfn.XLOOKUP(Y19,'weapon masteries'!$A$10:$A$19,'weapon masteries'!$B$10:$B$19,"",0),"") | AA19: {=IFERROR(INDEX(_xlfn.TEXTSPLIT(S19," "),,1),"")} | AB19: =IF(NOT(AA19=""),_xlfn.XLOOKUP(AA19,'weapon masteries'!$A$10:$A$19,'weapon masteries'!$B$10:$B$19,"",0),"") | AC19: {=IFERROR(INDEX(_xlfn.TEXTSPLIT(T19," "),,1),"")} | AD19: =IF(NOT(AC19=""),_xlfn.XLOOKUP(AC19,'weapon masteries'!$A$10:$A$20,'weapon masteries'!$B$10:$B$20,"",0),"")
A20: Melee Weapon Attack | B20: Greatsword (2014 edition) | C20: Strength | D20: reach 5 ft | E20: 2d6 | F20: slashing | G20: Heavy, Two-Handed | J20: =A20&": [ATK_MOD] to hit, "&D20&", one target. Hit: [DAMAGE] "&F20&" damage. "&I20 -> Melee Weapon Attack: [ATK_MOD] to hit, reach 5 ft, one target. Hit: [DAMAGE] slashing damage. | L20: =IF(NOT(G20=""),IF(COUNTA(P20:T20)>1,"Properties: ","Property: ")&U20&" ("&V20&")"&IF(NOT(W20=""),", "&W20&" ("&X20&")"&IF(NOT(Y20=""),", "&Y20&" ("&Z20&")"&IF(NOT(AA20=""),", "&AB20&" ("&AC20&")",""),""),""),"") -> Properties: Heavy (Creatures that are Small or Tiny have disadvantage on attack rolls with heavy weapons. A heavy weapon's size and bulk make it too large for a Small or Tiny creature to use effectively.), Two-Handed (This weapon requires two hands to use. This property is relevant only when you attack with the weapon, not when you simply hold it.) | P20: {=IFERROR(_xlfn.TEXTSPLIT(G20,", ",,TRUE),"")} -> Heavy | Q20: Two-Handed | U20: {=IFERROR(INDEX(_xlfn.TEXTSPLIT(P20," "),,1),"")} -> Heavy | V20: =IF(NOT(U20=""),_xlfn.XLOOKUP(U20,'weapon masteries'!$A$10:$A$19,'weapon masteries'!$B$10:$B$19,"",0),"") -> Creatures that are Small or Tiny have disadvantage on attack rolls with heavy weapons. A heavy weapon's size and bulk make it too large for a Small or Tiny creature to use effectively. | W20: {=IFERROR(INDEX(_xlfn.TEXTSPLIT(Q20," "),,1),"")} -> Two-Handed | X20: =IF(NOT(W20=""),_xlfn.XLOOKUP(W20,'weapon masteries'!$A$10:$A$19,'weapon masteries'!$B$10:$B$19,"",0),"") -> This weapon requires two hands to use. This property is relevant only when you attack with the weapon, not when you simply hold it. | Y20: {=IFERROR(INDEX(_xlfn.TEXTSPLIT(R20," "),,1),"")} | Z20: =IF(NOT(Y20=""),_xlfn.XLOOKUP(Y20,'weapon masteries'!$A$10:$A$19,'weapon masteries'!$B$10:$B$19,"",0),"") | AA20: {=IFERROR(INDEX(_xlfn.TEXTSPLIT(S20," "),,1),"")} | AB20: =IF(NOT(AA20=""),_xlfn.XLOOKUP(AA20,'weapon masteries'!$A$10:$A$19,'weapon masteries'!$B$10:$B$19,"",0),"") | AC20: {=IFERROR(INDEX(_xlfn.TEXTSPLIT(T20," "),,1),"")} | AD20: =IF(NOT(AC20=""),_xlfn.XLOOKUP(AC20,'weapon masteries'!$A$10:$A$20,'weapon masteries'!$B$10:$B$20,"",0),"")
A21: Melee Weapon Attack | B21: Halberd (2014 edition) | C21: Strength | D21: reach 10 ft | E21: 1d10 | F21: slashing | G21: Heavy, Reach, Two-Handed | J21: =A21&": [ATK_MOD] to hit, "&D21&", one target. Hit: [DAMAGE] "&F21&" damage. "&I21 -> Melee Weapon Attack: [ATK_MOD] to hit, reach 10 ft, one target. Hit: [DAMAGE] slashing damage. | L21: =IF(NOT(G21=""),IF(COUNTA(P21:T21)>1,"Properties: ","Property: ")&U21&" ("&V21&")"&IF(NOT(W21=""),", "&W21&" ("&X21&")"&IF(NOT(Y21=""),", "&Y21&" ("&Z21&")"&IF(NOT(AA21=""),", "&AB21&" ("&AC21&")",""),""),""),"") -> Properties: Heavy (Creatures that are Small or Tiny have disadvantage on attack rolls with heavy weapons. A heavy weapon's size and bulk make it too large for a Small or Tiny creature to use effectively.), Reach (This weapon adds 5 feet to your reach when you attack with it. This property also determines your reach for opportunity attacks with a reach weapon.), Two-Handed (This weapon requires two hands to use. This property is relevant only when you attack with the weapon, not when you simply hold it.) | P21: {=IFERROR(_xlfn.TEXTSPLIT(G21,", ",,TRUE),"")} -> Heavy | Q21: Reach | R21: Two-Handed | U21: {=IFERROR(INDEX(_xlfn.TEXTSPLIT(P21," "),,1),"")} -> Heavy | V21: =IF(NOT(U21=""),_xlfn.XLOOKUP(U21,'weapon masteries'!$A$10:$A$19,'weapon masteries'!$B$10:$B$19,"",0),"") -> Creatures that are Small or Tiny have disadvantage on attack rolls with heavy weapons. A heavy weapon's size and bulk make it too large for a Small or Tiny creature to use effectively. | W21: {=IFERROR(INDEX(_xlfn.TEXTSPLIT(Q21," "),,1),"")} -> Reach | X21: =IF(NOT(W21=""),_xlfn.XLOOKUP(W21,'weapon masteries'!$A$10:$A$19,'weapon masteries'!$B$10:$B$19,"",0),"") -> This weapon adds 5 feet to your reach when you attack with it. This property also determines your reach for opportunity attacks with a reach weapon. | Y21: {=IFERROR(INDEX(_xlfn.TEXTSPLIT(R21," "),,1),"")} -> Two-Handed | Z21: =IF(NOT(Y21=""),_xlfn.XLOOKUP(Y21,'weapon masteries'!$A$10:$A$19,'weapon masteries'!$B$10:$B$19,"",0),"") -> This weapon requires two hands to use. This property is relevant only when you attack with the weapon, not when you simply hold it. | AA21: {=IFERROR(INDEX(_xlfn.TEXTSPLIT(S21," "),,1),"")} | AB21: =IF(NOT(AA21=""),_xlfn.XLOOKUP(AA21,'weapon masteries'!$A$10:$A$19,'weapon masteries'!$B$10:$B$19,"",0),"") | AC21: {=IFERROR(INDEX(_xlfn.TEXTSPLIT(T21," "),,1),"")} | AD21: =IF(NOT(AC21=""),_xlfn.XLOOKUP(AC21,'weapon masteries'!$A$10:$A$20,'weapon masteries'!$B$10:$B$20,"",0),"")
A22: Melee Weapon Attack | B22: Lance (2014 edition) | C22: Strength | D22: reach 10 ft | E22: 1d12 | F22: piercing | G22: Reach | I22: The [MON] has disadvantage when it uses a lance to attack a target within 5 feet of itself. Also, a lance requires two hands to wield when not mounted. | J22: =A22&": [ATK_MOD] to hit, "&D22&", one target. Hit: [DAMAGE] "&F22&" damage. "&I22 -> Melee Weapon Attack: [ATK_MOD] to hit, reach 10 ft, one target. Hit: [DAMAGE] piercing damage. The [MON] has disadvantage when it uses a lance to attack a target within 5 feet of itself. Also, a lance requires two hands to wield when not mounted. | L22: =IF(NOT(G22=""),IF(COUNTA(P22:T22)>1,"Properties: ","Property: ")&U22&" ("&V22&")"&IF(NOT(W22=""),", "&W22&" ("&X22&")"&IF(NOT(Y22=""),", "&Y22&" ("&Z22&")"&IF(NOT(AA22=""),", "&AB22&" ("&AC22&")",""),""),""),"") -> Property: Reach (This weapon adds 5 feet to your reach when you attack with it. This property also determines your reach for opportunity attacks with a reach weapon.) | P22: {=IFERROR(_xlfn.TEXTSPLIT(G22,", ",,TRUE),"")} -> Reach | U22: {=IFERROR(INDEX(_xlfn.TEXTSPLIT(P22," "),,1),"")} -> Reach | V22: =IF(NOT(U22=""),_xlfn.XLOOKUP(U22,'weapon masteries'!$A$10:$A$19,'weapon masteries'!$B$10:$B$19,"",0),"") -> This weapon adds 5 feet to your reach when you attack with it. This property also determines your reach for opportunity attacks with a reach weapon. | W22: {=IFERROR(INDEX(_xlfn.TEXTSPLIT(Q22," "),,1),"")} | X22: =IF(NOT(W22=""),_xlfn.XLOOKUP(W22,'weapon masteries'!$A$10:$A$19,'weapon masteries'!$B$10:$B$19,"",0),"") | Y22: {=IFERROR(INDEX(_xlfn.TEXTSPLIT(R22," "),,1),"")} | Z22: =IF(NOT(Y22=""),_xlfn.XLOOKUP(Y22,'weapon masteries'!$A$10:$A$19,'weapon masteries'!$B$10:$B$19,"",0),"") | AA22: {=IFERROR(INDEX(_xlfn.TEXTSPLIT(S22," "),,1),"")} | AB22: =IF(NOT(AA22=""),_xlfn.XLOOKUP(AA22,'weapon masteries'!$A$10:$A$19,'weapon masteries'!$B$10:$B$19,"",0),"") | AC22: {=IFERROR(INDEX(_xlfn.TEXTSPLIT(T22," "),,1),"")} | AD22: =IF(NOT(AC22=""),_xlfn.XLOOKUP(AC22,'weapon masteries'!$A$10:$A$20,'weapon masteries'!$B$10:$B$20,"",0),"")
A23: Melee Weapon Attack | B23: Longsword (2014 edition) | C23: Strength | D23: reach 5 ft | E23: 1d8 | F23: slashing | G23: Versatile (1d10) | J23: =A23&": [ATK_MOD] to hit, "&D23&", one target. Hit: [DAMAGE] "&F23&" damage. "&I23 -> Melee Weapon Attack: [ATK_MOD] to hit, reach 5 ft, one target. Hit: [DAMAGE] slashing damage. | L23: =IF(NOT(G23=""),IF(COUNTA(P23:T23)>1,"Properties: ","Property: ")&U23&" ("&V23&")"&IF(NOT(W23=""),", "&W23&" ("&X23&")"&IF(NOT(Y23=""),", "&Y23&" ("&Z23&")"&IF(NOT(AA23=""),", "&AB23&" ("&AC23&")",""),""),""),"") -> Property: Versatile (This weapon can be used with one or two hands. A damage value in parentheses appears with the property—the damage when the weapon is used with two hands to make a melee attack.) | P23: {=IFERROR(_xlfn.TEXTSPLIT(G23,", ",,TRUE),"")} -> Versatile (1d10) | U23: {=IFERROR(INDEX(_xlfn.TEXTSPLIT(P23," "),,1),"")} -> Versatile | V23: =IF(NOT(U23=""),_xlfn.XLOOKUP(U23,'weapon masteries'!$A$10:$A$19,'weapon masteries'!$B$10:$B$19,"",0),"") -> This weapon can be used with one or two hands. A damage value in parentheses appears with the property—the damage when the weapon is used with two hands to make a melee attack. | W23: {=IFERROR(INDEX(_xlfn.TEXTSPLIT(Q23," "),,1),"")} | X23: =IF(NOT(W23=""),_xlfn.XLOOKUP(W23,'weapon masteries'!$A$10:$A$19,'weapon masteries'!$B$10:$B$19,"",0),"") | Y23: {=IFERROR(INDEX(_xlfn.TEXTSPLIT(R23," "),,1),"")} | Z23: =IF(NOT(Y23=""),_xlfn.XLOOKUP(Y23,'weapon masteries'!$A$10:$A$19,'weapon masteries'!$B$10:$B$19,"",0),"") | AA23: {=IFERROR(INDEX(_xlfn.TEXTSPLIT(S23," "),,1),"")} | AB23: =IF(NOT(AA23=""),_xlfn.XLOOKUP(AA23,'weapon masteries'!$A$10:$A$19,'weapon masteries'!$B$10:$B$19,"",0),"") | AC23: {=IFERROR(INDEX(_xlfn.TEXTSPLIT(T23," "),,1),"")} | AD23: =IF(NOT(AC23=""),_xlfn.XLOOKUP(AC23,'weapon masteries'!$A$10:$A$20,'weapon masteries'!$B$10:$B$20,"",0),"")
A24: Melee Weapon Attack | B24: Maul (2014 edition) | C24: Strength | D24: reach 5 ft | E24: 2d6 | F24: bludgeoning | G24: Heavy, Two-Handed | J24: =A24&": [ATK_MOD] to hit, "&D24&", one target. Hit: [DAMAGE] "&F24&" damage. "&I24 -> Melee Weapon Attack: [ATK_MOD] to hit, reach 5 ft, one target. Hit: [DAMAGE] bludgeoning damage. | L24: =IF(NOT(G24=""),IF(COUNTA(P24:T24)>1,"Properties: ","Property: ")&U24&" ("&V24&")"&IF(NOT(W24=""),", "&W24&" ("&X24&")"&IF(NOT(Y24=""),", "&Y24&" ("&Z24&")"&IF(NOT(AA24=""),", "&AB24&" ("&AC24&")",""),""),""),"") -> Properties: Heavy (Creatures that are Small or Tiny have disadvantage on attack rolls with heavy weapons. A heavy weapon's size and bulk make it too large for a Small or Tiny creature to use effectively.), Two-Handed (This weapon requires two hands to use. This property is relevant only when you attack with the weapon, not when you simply hold it.) | P24: {=IFERROR(_xlfn.TEXTSPLIT(G24,", ",,TRUE),"")} -> Heavy | Q24: Two-Handed | U24: {=IFERROR(INDEX(_xlfn.TEXTSPLIT(P24," "),,1),"")} -> Heavy | V24: =IF(NOT(U24=""),_xlfn.XLOOKUP(U24,'weapon masteries'!$A$10:$A$19,'weapon masteries'!$B$10:$B$19,"",0),"") -> Creatures that are Small or Tiny have disadvantage on attack rolls with heavy weapons. A heavy weapon's size and bulk make it too large for a Small or Tiny creature to use effectively. | W24: {=IFERROR(INDEX(_xlfn.TEXTSPLIT(Q24," "),,1),"")} -> Two-Handed | X24: =IF(NOT(W24=""),_xlfn.XLOOKUP(W24,'weapon masteries'!$A$10:$A$19,'weapon masteries'!$B$10:$B$19,"",0),"") -> This weapon requires two hands to use. This property is relevant only when you attack with the weapon, not when you simply hold it. | Y24: {=IFERROR(INDEX(_xlfn.TEXTSPLIT(R24," "),,1),"")} | Z24: =IF(NOT(Y24=""),_xlfn.XLOOKUP(Y24,'weapon masteries'!$A$10:$A$19,'weapon masteries'!$B$10:$B$19,"",0),"") | AA24: {=IFERROR(INDEX(_xlfn.TEXTSPLIT(S24," "),,1),"")} | AB24: =IF(NOT(AA24=""),_xlfn.XLOOKUP(AA24,'weapon masteries'!$A$10:$A$19,'weapon masteries'!$B$10:$B$19,"",0),"") | AC24: {=IFERROR(INDEX(_xlfn.TEXTSPLIT(T24," "),,1),"")} | AD24: =IF(NOT(AC24=""),_xlfn.XLOOKUP(AC24,'weapon masteries'!$A$10:$A$20,'weapon masteries'!$B$10:$B$20,"",0),"")
A25: Melee Weapon Attack | B25: Morningstar (2014 edition) | C25: Strength | D25: reach 5 ft | E25: 1d8 | F25: piercing | J25: =A25&": [ATK_MOD] to hit, "&D25&", one target. Hit: [DAMAGE] "&F25&" damage. "&I25 -> Melee Weapon Attack: [ATK_MOD] to hit, reach 5 ft, one target. Hit: [DAMAGE] piercing damage. | L25: =IF(NOT(G25=""),IF(COUNTA(P25:T25)>1,"Properties: ","Property: ")&U25&" ("&V25&")"&IF(NOT(W25=""),", "&W25&" ("&X25&")"&IF(NOT(Y25=""),", "&Y25&" ("&Z25&")"&IF(NOT(AA25=""),", "&AB25&" ("&AC25&")",""),""),""),"") | P25: {=IFERROR(_xlfn.TEXTSPLIT(G25,", ",,TRUE),"")} | U25: {=IFERROR(INDEX(_xlfn.TEXTSPLIT(P25," "),,1),"")} | V25: =IF(NOT(U25=""),_xlfn.XLOOKUP(U25,'weapon masteries'!$A$10:$A$19,'weapon masteries'!$B$10:$B$19,"",0),"") | W25: {=IFERROR(INDEX(_xlfn.TEXTSPLIT(Q25," "),,1),"")} | X25: =IF(NOT(W25=""),_xlfn.XLOOKUP(W25,'weapon masteries'!$A$10:$A$19,'weapon masteries'!$B$10:$B$19,"",0),"") | Y25: {=IFERROR(INDEX(_xlfn.TEXTSPLIT(R25," "),,1),"")} | Z25: =IF(NOT(Y25=""),_xlfn.XLOOKUP(Y25,'weapon masteries'!$A$10:$A$19,'weapon masteries'!$B$10:$B$19,"",0),"") | AA25: {=IFERROR(INDEX(_xlfn.TEXTSPLIT(S25," "),,1),"")} | AB25: =IF(NOT(AA25=""),_xlfn.XLOOKUP(AA25,'weapon masteries'!$A$10:$A$19,'weapon masteries'!$B$10:$B$19,"",0),"") | AC25: {=IFERROR(INDEX(_xlfn.TEXTSPLIT(T25," "),,1),"")} | AD25: =IF(NOT(AC25=""),_xlfn.XLOOKUP(AC25,'weapon masteries'!$A$10:$A$20,'weapon masteries'!$B$10:$B$20,"",0),"")
A26: Melee Weapon Attack | B26: Pike (2014 edition) | C26: Strength | D26: reach 10 ft | E26: 1d10 | F26: piercing | G26: Heavy, Reach, Two-Handed | J26: =A26&": [ATK_MOD] to hit, "&D26&", one target. Hit: [DAMAGE] "&F26&" damage. "&I26 -> Melee Weapon Attack: [ATK_MOD] to hit, reach 10 ft, one target. Hit: [DAMAGE] piercing damage. | L26: =IF(NOT(G26=""),IF(COUNTA(P26:T26)>1,"Properties: ","Property: ")&U26&" ("&V26&")"&IF(NOT(W26=""),", "&W26&" ("&X26&")"&IF(NOT(Y26=""),", "&Y26&" ("&Z26&")"&IF(NOT(AA26=""),", "&AB26&" ("&AC26&")",""),""),""),"") -> Properties: Heavy (Creatures that are Small or Tiny have disadvantage on attack rolls with heavy weapons. A heavy weapon's size and bulk make it too large for a Small or Tiny creature to use effectively.), Reach (This weapon adds 5 feet to your reach when you attack with it. This property also determines your reach for opportunity attacks with a reach weapon.), Two-Handed (This weapon requires two hands to use. This property is relevant only when you attack with the weapon, not when you simply hold it.) | P26: {=IFERROR(_xlfn.TEXTSPLIT(G26,", ",,TRUE),"")} -> Heavy | Q26: Reach | R26: Two-Handed | U26: {=IFERROR(INDEX(_xlfn.TEXTSPLIT(P26," "),,1),"")} -> Heavy | V26: =IF(NOT(U26=""),_xlfn.XLOOKUP(U26,'weapon masteries'!$A$10:$A$19,'weapon masteries'!$B$10:$B$19,"",0),"") -> Creatures that are Small or Tiny have disadvantage on attack rolls with heavy weapons. A heavy weapon's size and bulk make it too large for a Small or Tiny creature to use effectively. | W26: {=IFERROR(INDEX(_xlfn.TEXTSPLIT(Q26," "),,1),"")} -> Reach | X26: =IF(NOT(W26=""),_xlfn.XLOOKUP(W26,'weapon masteries'!$A$10:$A$19,'weapon masteries'!$B$10:$B$19,"",0),"") -> This weapon adds 5 feet to your reach when you attack with it. This property also determines your reach for opportunity attacks with a reach weapon. | Y26: {=IFERROR(INDEX(_xlfn.TEXTSPLIT(R26," "),,1),"")} -> Two-Handed | Z26: =IF(NOT(Y26=""),_xlfn.XLOOKUP(Y26,'weapon masteries'!$A$10:$A$19,'weapon masteries'!$B$10:$B$19,"",0),"") -> This weapon requires two hands to use. This property is relevant only when you attack with the weapon, not when you simply hold it. | AA26: {=IFERROR(INDEX(_xlfn.TEXTSPLIT(S26," "),,1),"")} | AB26: =IF(NOT(AA26=""),_xlfn.XLOOKUP(AA26,'weapon masteries'!$A$10:$A$19,'weapon masteries'!$B$10:$B$19,"",0),"") | AC26: {=IFERROR(INDEX(_xlfn.TEXTSPLIT(T26," "),,1),"")} | AD26: =IF(NOT(AC26=""),_xlfn.XLOOKUP(AC26,'weapon masteries'!$A$10:$A$20,'weapon masteries'!$B$10:$B$20,"",0),"")
A27: Melee Weapon Attack | B27: Rapier (2014 edition) | C27: Max of Strength or Dexterity | D27: reach 5 ft | E27: 1d8 | F27: piercing | G27: Finesse | J27: =A27&": [ATK_MOD] to hit, "&D27&", one target. Hit: [DAMAGE] "&F27&" damage. "&I27 -> Melee Weapon Attack: [ATK_MOD] to hit, reach 5 ft, one target. Hit: [DAMAGE] piercing damage. | L27: =IF(NOT(G27=""),IF(COUNTA(P27:T27)>1,"Properties: ","Property: ")&U27&" ("&V27&")"&IF(NOT(W27=""),", "&W27&" ("&X27&")"&IF(NOT(Y27=""),", "&Y27&" ("&Z27&")"&IF(NOT(AA27=""),", "&AB27&" ("&AC27&")",""),""),""),"") -> Property: Finesse (When making an attack with a finesse weapon, you use your choice of your Strength or Dexterity modifier for the attack and damage rolls. You must use the same modifier for both rolls.) | P27: {=IFERROR(_xlfn.TEXTSPLIT(G27,", ",,TRUE),"")} -> Finesse | U27: {=IFERROR(INDEX(_xlfn.TEXTSPLIT(P27," "),,1),"")} -> Finesse | V27: =IF(NOT(U27=""),_xlfn.XLOOKUP(U27,'weapon masteries'!$A$10:$A$19,'weapon masteries'!$B$10:$B$19,"",0),"") -> When making an attack with a finesse weapon, you use your choice of your Strength or Dexterity modifier for the attack and damage rolls. You must use the same modifier for both rolls. | W27: {=IFERROR(INDEX(_xlfn.TEXTSPLIT(Q27," "),,1),"")} | X27: =IF(NOT(W27=""),_xlfn.XLOOKUP(W27,'weapon masteries'!$A$10:$A$19,'weapon masteries'!$B$10:$B$19,"",0),"") | Y27: {=IFERROR(INDEX(_xlfn.TEXTSPLIT(R27," "),,1),"")} | Z27: =IF(NOT(Y27=""),_xlfn.XLOOKUP(Y27,'weapon masteries'!$A$10:$A$19,'weapon masteries'!$B$10:$B$19,"",0),"") | AA27: {=IFERROR(INDEX(_xlfn.TEXTSPLIT(S27," "),,1),"")} | AB27: =IF(NOT(AA27=""),_xlfn.XLOOKUP(AA27,'weapon masteries'!$A$10:$A$19,'weapon masteries'!$B$10:$B$19,"",0),"") | AC27: {=IFERROR(INDEX(_xlfn.TEXTSPLIT(T27," "),,1),"")} | AD27: =IF(NOT(AC27=""),_xlfn.XLOOKUP(AC27,'weapon masteries'!$A$10:$A$20,'weapon masteries'!$B$10:$B$20,"",0),"")
A28: Melee Weapon Attack | B28: Scimitar (2014 edition) | C28: Max of Strength or Dexterity | D28: reach 5 ft | E28: 1d6 | F28: slashing | G28: Finesse, Light | J28: =A28&": [ATK_MOD] to hit, "&D28&", one target. Hit: [DAMAGE] "&F28&" damage. "&I28 -> Melee Weapon Attack: [ATK_MOD] to hit, reach 5 ft, one target. Hit: [DAMAGE] slashing damage. | L28: =IF(NOT(G28=""),IF(COUNTA(P28:T28)>1,"Properties: ","Property: ")&U28&" ("&V28&")"&IF(NOT(W28=""),", "&W28&" ("&X28&")"&IF(NOT(Y28=""),", "&Y28&" ("&Z28&")"&IF(NOT(AA28=""),", "&AB28&" ("&AC28&")",""),""),""),"") -> Properties: Finesse (When making an attack with a finesse weapon, you use your choice of your Strength or Dexterity modifier for the attack and damage rolls. You must use the same modifier for both rolls.), Light (A light weapon is small and easy to handle, making it ideal for use when fighting with two weapons.) | P28: {=IFERROR(_xlfn.TEXTSPLIT(G28,", ",,TRUE),"")} -> Finesse | Q28: Light | U28: {=IFERROR(INDEX(_xlfn.TEXTSPLIT(P28," "),,1),"")} -> Finesse | V28: =IF(NOT(U28=""),_xlfn.XLOOKUP(U28,'weapon masteries'!$A$10:$A$19,'weapon masteries'!$B$10:$B$19,"",0),"") -> When making an attack with a finesse weapon, you use your choice of your Strength or Dexterity modifier for the attack and damage rolls. You must use the same modifier for both rolls. | W28: {=IFERROR(INDEX(_xlfn.TEXTSPLIT(Q28," "),,1),"")} -> Light | X28: =IF(NOT(W28=""),_xlfn.XLOOKUP(W28,'weapon masteries'!$A$10:$A$19,'weapon masteries'!$B$10:$B$19,"",0),"") -> A light weapon is small and easy to handle, making it ideal for use when fighting with two weapons. | Y28: {=IFERROR(INDEX(_xlfn.TEXTSPLIT(R28," "),,1),"")} | Z28: =IF(NOT(Y28=""),_xlfn.XLOOKUP(Y28,'weapon masteries'!$A$10:$A$19,'weapon masteries'!$B$10:$B$19,"",0),"") | AA28: {=IFERROR(INDEX(_xlfn.TEXTSPLIT(S28," "),,1),"")} | AB28: =IF(NOT(AA28=""),_xlfn.XLOOKUP(AA28,'weapon masteries'!$A$10:$A$19,'weapon masteries'!$B$10:$B$19,"",0),"") | AC28: {=IFERROR(INDEX(_xlfn.TEXTSPLIT(T28," "),,1),"")} | AD28: =IF(NOT(AC28=""),_xlfn.XLOOKUP(AC28,'weapon masteries'!$A$10:$A$20,'weapon masteries'!$B$10:$B$20,"",0),"")
A29: Melee Weapon Attack | B29: Shortsword (2014 edition) | C29: Max of Strength or Dexterity | D29: reach 5 ft | E29: 1d6 | F29: piercing | G29: Finesse, Light | J29: =A29&": [ATK_MOD] to hit, "&D29&", one target. Hit: [DAMAGE] "&F29&" damage. "&I29 -> Melee Weapon Attack: [ATK_MOD] to hit, reach 5 ft, one target. Hit: [DAMAGE] piercing damage. | L29: =IF(NOT(G29=""),IF(COUNTA(P29:T29)>1,"Properties: ","Property: ")&U29&" ("&V29&")"&IF(NOT(W29=""),", "&W29&" ("&X29&")"&IF(NOT(Y29=""),", "&Y29&" ("&Z29&")"&IF(NOT(AA29=""),", "&AB29&" ("&AC29&")",""),""),""),"") -> Properties: Finesse (When making an attack with a finesse weapon, you use your choice of your Strength or Dexterity modifier for the attack and damage rolls. You must use the same modifier for both rolls.), Light (A light weapon is small and easy to handle, making it ideal for use when fighting with two weapons.) | P29: {=IFERROR(_xlfn.TEXTSPLIT(G29,", ",,TRUE),"")} -> Finesse | Q29: Light | U29: {=IFERROR(INDEX(_xlfn.TEXTSPLIT(P29," "),,1),"")} -> Finesse | V29: =IF(NOT(U29=""),_xlfn.XLOOKUP(U29,'weapon masteries'!$A$10:$A$19,'weapon masteries'!$B$10:$B$19,"",0),"") -> When making an attack with a finesse weapon, you use your choice of your Strength or Dexterity modifier for the attack and damage rolls. You must use the same modifier for both rolls. | W29: {=IFERROR(INDEX(_xlfn.TEXTSPLIT(Q29," "),,1),"")} -> Light | X29: =IF(NOT(W29=""),_xlfn.XLOOKUP(W29,'weapon masteries'!$A$10:$A$19,'weapon masteries'!$B$10:$B$19,"",0),"") -> A light weapon is small and easy to handle, making it ideal for use when fighting with two weapons. | Y29: {=IFERROR(INDEX(_xlfn.TEXTSPLIT(R29," "),,1),"")} | Z29: =IF(NOT(Y29=""),_xlfn.XLOOKUP(Y29,'weapon masteries'!$A$10:$A$19,'weapon masteries'!$B$10:$B$19,"",0),"") | AA29: {=IFERROR(INDEX(_xlfn.TEXTSPLIT(S29," "),,1),"")} | AB29: =IF(NOT(AA29=""),_xlfn.XLOOKUP(AA29,'weapon masteries'!$A$10:$A$19,'weapon masteries'!$B$10:$B$19,"",0),"") | AC29: {=IFERROR(INDEX(_xlfn.TEXTSPLIT(T29," "),,1),"")} | AD29: =IF(NOT(AC29=""),_xlfn.XLOOKUP(AC29,'weapon masteries'!$A$10:$A$20,'weapon masteries'!$B$10:$B$20,"",0),"")
A30: Melee or Ranged Weapon Attack | B30: Trident (2014 edition) | C30: Strength | D30: reach 5 ft or range 20/60 ft | E30: 1d6 | F30: piercing | G30: Thrown (20/60), Versatile (1d8) | J30: =A30&": [ATK_MOD] to hit, "&D30&", one target. Hit: [DAMAGE] "&F30&" damage. "&I30 -> Melee or Ranged Weapon Attack: [ATK_MOD] to hit, reach 5 ft or range 20/60 ft, one target. Hit: [DAMAGE] piercing damage. | L30: =IF(NOT(G30=""),IF(COUNTA(P30:T30)>1,"Properties: ","Property: ")&U30&" ("&V30&")"&IF(NOT(W30=""),", "&W30&" ("&X30&")"&IF(NOT(Y30=""),", "&Y30&" ("&Z30&")"&IF(NOT(AA30=""),", "&AB30&" ("&AC30&")",""),""),""),"") -> Properties: Thrown (If a weapon has the thrown property, you can throw the weapon to make a ranged attack. If the weapon is a melee weapon, you use the same ability modifier for that attack roll and damage roll that you would use for a melee attack with the weapon. For example, if you throw a handaxe, you use your Strength, but if you throw a dagger, you can use either your Strength or your Dexterity, since the dagger has the finesse property.), Versatile (This weapon can be used with one or two hands. A damage value in parentheses appears with the property—the damage when the weapon is used with two hands to make a melee attack.) | P30: {=IFERROR(_xlfn.TEXTSPLIT(G30,", ",,TRUE),"")} -> Thrown (20/60) | Q30: Versatile (1d8) | U30: {=IFERROR(INDEX(_xlfn.TEXTSPLIT(P30," "),,1),"")} -> Thrown | V30: =IF(NOT(U30=""),_xlfn.XLOOKUP(U30,'weapon masteries'!$A$10:$A$19,'weapon masteries'!$B$10:$B$19,"",0),"") -> If a weapon has the thrown property, you can throw the weapon to make a ranged attack. If the weapon is a melee weapon, you use the same ability modifier for that attack roll and damage roll that you would use for a melee attack with the weapon. For example, if you throw a handaxe, you use your Strength, but if you throw a dagger, you can use either your Strength or your Dexterity, since the dagger has the finesse property. | W30: {=IFERROR(INDEX(_xlfn.TEXTSPLIT(Q30," "),,1),"")} -> Versatile | X30: =IF(NOT(W30=""),_xlfn.XLOOKUP(W30,'weapon masteries'!$A$10:$A$19,'weapon masteries'!$B$10:$B$19,"",0),"") -> This weapon can be used with one or two hands. A damage value in parentheses appears with the property—the damage when the weapon is used with two hands to make a melee attack. | Y30: {=IFERROR(INDEX(_xlfn.TEXTSPLIT(R30," "),,1),"")} | Z30: =IF(NOT(Y30=""),_xlfn.XLOOKUP(Y30,'weapon masteries'!$A$10:$A$19,'weapon masteries'!$B$10:$B$19,"",0),"") | AA30: {=IFERROR(INDEX(_xlfn.TEXTSPLIT(S30," "),,1),"")} | AB30: =IF(NOT(AA30=""),_xlfn.XLOOKUP(AA30,'weapon masteries'!$A$10:$A$19,'weapon masteries'!$B$10:$B$19,"",0),"") | AC30: {=IFERROR(INDEX(_xlfn.TEXTSPLIT(T30," "),,1),"")} | AD30: =IF(NOT(AC30=""),_xlfn.XLOOKUP(AC30,'weapon masteries'!$A$10:$A$20,'weapon masteries'!$B$10:$B$20,"",0),"")
A31: Melee Weapon Attack | B31: War Pick (2014 edition) | C31: Strength | D31: reach 5 ft | E31: 1d8 | F31: piercing | J31: =A31&": [ATK_MOD] to hit, "&D31&", one target. Hit: [DAMAGE] "&F31&" damage. "&I31 -> Melee Weapon Attack: [ATK_MOD] to hit, reach 5 ft, one target. Hit: [DAMAGE] piercing damage. | L31: =IF(NOT(G31=""),IF(COUNTA(P31:T31)>1,"Properties: ","Property: ")&U31&" ("&V31&")"&IF(NOT(W31=""),", "&W31&" ("&X31&")"&IF(NOT(Y31=""),", "&Y31&" ("&Z31&")"&IF(NOT(AA31=""),", "&AB31&" ("&AC31&")",""),""),""),"") | P31: {=IFERROR(_xlfn.TEXTSPLIT(G31,", ",,TRUE),"")} | U31: {=IFERROR(INDEX(_xlfn.TEXTSPLIT(P31," "),,1),"")} | V31: =IF(NOT(U31=""),_xlfn.XLOOKUP(U31,'weapon masteries'!$A$10:$A$19,'weapon masteries'!$B$10:$B$19,"",0),"") | W31: {=IFERROR(INDEX(_xlfn.TEXTSPLIT(Q31," "),,1),"")} | X31: =IF(NOT(W31=""),_xlfn.XLOOKUP(W31,'weapon masteries'!$A$10:$A$19,'weapon masteries'!$B$10:$B$19,"",0),"") | Y31: {=IFERROR(INDEX(_xlfn.TEXTSPLIT(R31," "),,1),"")} | Z31: =IF(NOT(Y31=""),_xlfn.XLOOKUP(Y31,'weapon masteries'!$A$10:$A$19,'weapon masteries'!$B$10:$B$19,"",0),"") | AA31: {=IFERROR(INDEX(_xlfn.TEXTSPLIT(S31," "),,1),"")} | AB31: =IF(NOT(AA31=""),_xlfn.XLOOKUP(AA31,'weapon masteries'!$A$10:$A$19,'weapon masteries'!$B$10:$B$19,"",0),"") | AC31: {=IFERROR(INDEX(_xlfn.TEXTSPLIT(T31," "),,1),"")} | AD31: =IF(NOT(AC31=""),_xlfn.XLOOKUP(AC31,'weapon masteries'!$A$10:$A$20,'weapon masteries'!$B$10:$B$20,"",0),"")
A32: Melee Weapon Attack | B32: Warhammer (2014 edition) | C32: Strength | D32: reach 5 ft | E32: 1d8 | F32: bludgeoning | G32: Versatile (1d10) | J32: =A32&": [ATK_MOD] to hit, "&D32&", one target. Hit: [DAMAGE] "&F32&" damage. "&I32 -> Melee Weapon Attack: [ATK_MOD] to hit, reach 5 ft, one target. Hit: [DAMAGE] bludgeoning damage. | L32: =IF(NOT(G32=""),IF(COUNTA(P32:T32)>1,"Properties: ","Property: ")&U32&" ("&V32&")"&IF(NOT(W32=""),", "&W32&" ("&X32&")"&IF(NOT(Y32=""),", "&Y32&" ("&Z32&")"&IF(NOT(AA32=""),", "&AB32&" ("&AC32&")",""),""),""),"") -> Property: Versatile (This weapon can be used with one or two hands. A damage value in parentheses appears with the property—the damage when the weapon is used with two hands to make a melee attack.) | P32: {=IFERROR(_xlfn.TEXTSPLIT(G32,", ",,TRUE),"")} -> Versatile (1d10) | U32: {=IFERROR(INDEX(_xlfn.TEXTSPLIT(P32," "),,1),"")} -> Versatile | V32: =IF(NOT(U32=""),_xlfn.XLOOKUP(U32,'weapon masteries'!$A$10:$A$19,'weapon masteries'!$B$10:$B$19,"",0),"") -> This weapon can be used with one or two hands. A damage value in parentheses appears with the property—the damage when the weapon is used with two hands to make a melee attack. | W32: {=IFERROR(INDEX(_xlfn.TEXTSPLIT(Q32," "),,1),"")} | X32: =IF(NOT(W32=""),_xlfn.XLOOKUP(W32,'weapon masteries'!$A$10:$A$19,'weapon masteries'!$B$10:$B$19,"",0),"") | Y32: {=IFERROR(INDEX(_xlfn.TEXTSPLIT(R32," "),,1),"")} | Z32: =IF(NOT(Y32=""),_xlfn.XLOOKUP(Y32,'weapon masteries'!$A$10:$A$19,'weapon masteries'!$B$10:$B$19,"",0),"") | AA32: {=IFERROR(INDEX(_xlfn.TEXTSPLIT(S32," "),,1),"")} | AB32: =IF(NOT(AA32=""),_xlfn.XLOOKUP(AA32,'weapon masteries'!$A$10:$A$19,'weapon masteries'!$B$10:$B$19,"",0),"") | AC32: {=IFERROR(INDEX(_xlfn.TEXTSPLIT(T32," "),,1),"")} | AD32: =IF(NOT(AC32=""),_xlfn.XLOOKUP(AC32,'weapon masteries'!$A$10:$A$20,'weapon masteries'!$B$10:$B$20,"",0),"")
A33: Melee Weapon Attack | B33: Whip (2014 edition) | C33: Max of Strength or Dexterity | D33: reach 5 ft | E33: 1d4 | F33: slashing | G33: Finesse, Reach | J33: =A33&": [ATK_MOD] to hit, "&D33&", one target. Hit: [DAMAGE] "&F33&" damage. "&I33 -> Melee Weapon Attack: [ATK_MOD] to hit, reach 5 ft, one target. Hit: [DAMAGE] slashing damage. | L33: =IF(NOT(G33=""),IF(COUNTA(P33:T33)>1,"Properties: ","Property: ")&U33&" ("&V33&")"&IF(NOT(W33=""),", "&W33&" ("&X33&")"&IF(NOT(Y33=""),", "&Y33&" ("&Z33&")"&IF(NOT(AA33=""),", "&AB33&" ("&AC33&")",""),""),""),"") -> Properties: Finesse (When making an attack with a finesse weapon, you use your choice of your Strength or Dexterity modifier for the attack and damage rolls. You must use the same modifier for both rolls.), Reach (This weapon adds 5 feet to your reach when you attack with it. This property also determines your reach for opportunity attacks with a reach weapon.) | P33: {=IFERROR(_xlfn.TEXTSPLIT(G33,", ",,TRUE),"")} -> Finesse | Q33: Reach | U33: {=IFERROR(INDEX(_xlfn.TEXTSPLIT(P33," "),,1),"")} -> Finesse | V33: =IF(NOT(U33=""),_xlfn.XLOOKUP(U33,'weapon masteries'!$A$10:$A$19,'weapon masteries'!$B$10:$B$19,"",0),"") -> When making an attack with a finesse weapon, you use your choice of your Strength or Dexterity modifier for the attack and damage rolls. You must use the same modifier for both rolls. | W33: {=IFERROR(INDEX(_xlfn.TEXTSPLIT(Q33," "),,1),"")} -> Reach | X33: =IF(NOT(W33=""),_xlfn.XLOOKUP(W33,'weapon masteries'!$A$10:$A$19,'weapon masteries'!$B$10:$B$19,"",0),"") -> This weapon adds 5 feet to your reach when you attack with it. This property also determines your reach for opportunity attacks with a reach weapon. | Y33: {=IFERROR(INDEX(_xlfn.TEXTSPLIT(R33," "),,1),"")} | Z33: =IF(NOT(Y33=""),_xlfn.XLOOKUP(Y33,'weapon masteries'!$A$10:$A$19,'weapon masteries'!$B$10:$B$19,"",0),"") | AA33: {=IFERROR(INDEX(_xlfn.TEXTSPLIT(S33," "),,1),"")} | AB33: =IF(NOT(AA33=""),_xlfn.XLOOKUP(AA33,'weapon masteries'!$A$10:$A$19,'weapon masteries'!$B$10:$B$19,"",0),"") | AC33: {=IFERROR(INDEX(_xlfn.TEXTSPLIT(T33," "),,1),"")} | AD33: =IF(NOT(AC33=""),_xlfn.XLOOKUP(AC33,'weapon masteries'!$A$10:$A$20,'weapon masteries'!$B$10:$B$20,"",0),"")
A34: Ranged Weapon Attack | B34: Blowgun (2014 edition) | C34: Dexterity | D34: range 25/100 ft | E34: 1 | F34: piercing | G34: Ammunition, Range (25/100), Loading | J34: =A34&": [ATK_MOD] to hit, "&D34&", one target. Hit: [DAMAGE] "&F34&" damage. "&I34 -> Ranged Weapon Attack: [ATK_MOD] to hit, range 25/100 ft, one target. Hit: [DAMAGE] piercing damage. | L34: =IF(NOT(G34=""),IF(COUNTA(P34:T34)>1,"Properties: ","Property: ")&U34&" ("&V34&")"&IF(NOT(W34=""),", "&W34&" ("&X34&")"&IF(NOT(Y34=""),", "&Y34&" ("&Z34&")"&IF(NOT(AA34=""),", "&AB34&" ("&AC34&")",""),""),""),"") -> Properties: Ammunition (You can use a weapon that has the ammunition property to make a ranged attack only if you have ammunition to fire from the weapon. Each time you attack with the weapon, you expend one piece of ammunition. Drawing the ammunition from a quiver, case, or other container is part of the attack. Loading a one-handed weapon requires a free hand. At the end of the battle, you can recover half your expended ammunition by taking a minute to search the battlefield. If you use a weapon that has the ammunition property to make a melee attack, you treat the weapon as an improvised weapon. A sling must be loaded to deal any damage when used in this way.), Range (A weapon that can be used to make a ranged attack has a range shown in parentheses after the ammunition or thrown property. The range lists two numbers. The first is the weapon’s normal range in feet, and the second indicates the weapon’s maximum range. When attacking a target beyond normal range, you have disadvantage on the attack roll. You can’t attack a target beyond the weapon’s long range.), Loading (Because of the time required to load this weapon, you can fire only one piece of ammunition from it when you use an action, bonus action, or reaction to fire it, regardless of the number of attacks you can normally make.) | P34: {=IFERROR(_xlfn.TEXTSPLIT(G34,", ",,TRUE),"")} -> Ammunition | Q34: Range (25/100) | R34: Loading | U34: {=IFERROR(INDEX(_xlfn.TEXTSPLIT(P34," "),,1),"")} -> Ammunition | V34: =IF(NOT(U34=""),_xlfn.XLOOKUP(U34,'weapon masteries'!$A$10:$A$19,'weapon masteries'!$B$10:$B$19,"",0),"") -> You can use a weapon that has the ammunition property to make a ranged attack only if you have ammunition to fire from the weapon. Each time you attack with the weapon, you expend one piece of ammunition. Drawing the ammunition from a quiver, case, or other container is part of the attack. Loading a one-handed weapon requires a free hand. At the end of the battle, you can recover half your expended ammunition by taking a minute to search the battlefield. If you use a weapon that has the ammunition property to make a melee attack, you treat the weapon as an improvised weapon. A sling must be loaded to deal any damage when used in this way. | W34: {=IFERROR(INDEX(_xlfn.TEXTSPLIT(Q34," "),,1),"")} -> Range | X34: =IF(NOT(W34=""),_xlfn.XLOOKUP(W34,'weapon masteries'!$A$10:$A$19,'weapon masteries'!$B$10:$B$19,"",0),"") -> A weapon that can be used to make a ranged attack has a range shown in parentheses after the ammunition or thrown property. The range lists two numbers. The first is the weapon’s normal range in feet, and the second indicates the weapon’s maximum range. When attacking a target beyond normal range, you have disadvantage on the attack roll. You can’t attack a target beyond the weapon’s long range. | Y34: {=IFERROR(INDEX(_xlfn.TEXTSPLIT(R34," "),,1),"")} -> Loading | Z34: =IF(NOT(Y34=""),_xlfn.XLOOKUP(Y34,'weapon masteries'!$A$10:$A$19,'weapon masteries'!$B$10:$B$19,"",0),"") -> Because of the time required to load this weapon, you can fire only one piece of ammunition from it when you use an action, bonus action, or reaction to fire it, regardless of the number of attacks you can normally make. | AA34: {=IFERROR(INDEX(_xlfn.TEXTSPLIT(S34," "),,1),"")} | AB34: =IF(NOT(AA34=""),_xlfn.XLOOKUP(AA34,'weapon masteries'!$A$10:$A$19,'weapon masteries'!$B$10:$B$19,"",0),"") | AC34: {=IFERROR(INDEX(_xlfn.TEXTSPLIT(T34," "),,1),"")} | AD34: =IF(NOT(AC34=""),_xlfn.XLOOKUP(AC34,'weapon masteries'!$A$10:$A$20,'weapon masteries'!$B$10:$B$20,"",0),"")
A35: Ranged Weapon Attack | B35: Hand Crossbow (2014 edition) | C35: Dexterity | D35: range 30/120 ft | E35: 1d6 | F35: piercing | G35: Ammunition, Range (30/120), Light, Loading | J35: =A35&": [ATK_MOD] to hit, "&D35&", one target. Hit: [DAMAGE] "&F35&" damage. "&I35 -> Ranged Weapon Attack: [ATK_MOD] to hit, range 30/120 ft, one target. Hit: [DAMAGE] piercing damage. | L35: =IF(NOT(G35=""),IF(COUNTA(P35:T35)>1,"Properties: ","Property: ")&U35&" ("&V35&")"&IF(NOT(W35=""),", "&W35&" ("&X35&")"&IF(NOT(Y35=""),", "&Y35&" ("&Z35&")"&IF(NOT(AA35=""),", "&AB35&" ("&AC35&")",""),""),""),"") -> Properties: Ammunition (You can use a weapon that has the ammunition property to make a ranged attack only if you have ammunition to fire from the weapon. Each time you attack with the weapon, you expend one piece of ammunition. Drawing the ammunition from a quiver, case, or other container is part of the attack. Loading a one-handed weapon requires a free hand. At the end of the battle, you can recover half your expended ammunition by taking a minute to search the battlefield. If you use a weapon that has the ammunition property to make a melee attack, you treat the weapon as an improvised weapon. A sling must be loaded to deal any damage when used in this way.), Range (A weapon that can be used to make a ranged attack has a range shown in parentheses after the ammunition or thrown property. The range lists two numbers. The first is the weapon’s normal range in feet, and the second indicates the weapon’s maximum range. When attacking a target beyond normal range, you have disadvantage on the attack roll. You can’t attack a target beyond the weapon’s long range.), Light (A light weapon is small and easy to handle, making it ideal for use when fighting with two weapons.), Because of the time required to load this weapon, you can fire only one piece of ammunition from it when you use an action, bonus action, or reaction to fire it, regardless of the number of attacks you can normally make. () | P35: {=IFERROR(_xlfn.TEXTSPLIT(G35,", ",,TRUE),"")} -> Ammunition | Q35: Range (30/120) | R35: Light | S35: Loading | U35: {=IFERROR(INDEX(_xlfn.TEXTSPLIT(P35," "),,1),"")} -> Ammunition | V35: =IF(NOT(U35=""),_xlfn.XLOOKUP(U35,'weapon masteries'!$A$10:$A$19,'weapon masteries'!$B$10:$B$19,"",0),"") -> You can use a weapon that has the ammunition property to make a ranged attack only if you have ammunition to fire from the weapon. Each time you attack with the weapon, you expend one piece of ammunition. Drawing the ammunition from a quiver, case, or other container is part of the attack. Loading a one-handed weapon requires a free hand. At the end of the battle, you can recover half your expended ammunition by taking a minute to search the battlefield. If you use a weapon that has the ammunition property to make a melee attack, you treat the weapon as an improvised weapon. A sling must be loaded to deal any damage when used in this way. | W35: {=IFERROR(INDEX(_xlfn.TEXTSPLIT(Q35," "),,1),"")} -> Range | X35: =IF(NOT(W35=""),_xlfn.XLOOKUP(W35,'weapon masteries'!$A$10:$A$19,'weapon masteries'!$B$10:$B$19,"",0),"") -> A weapon that can be used to make a ranged attack has a range shown in parentheses after the ammunition or thrown property. The range lists two numbers. The first is the weapon’s normal range in feet, and the second indicates the weapon’s maximum range. When attacking a target beyond normal range, you have disadvantage on the attack roll. You can’t attack a target beyond the weapon’s long range. | Y35: {=IFERROR(INDEX(_xlfn.TEXTSPLIT(R35," "),,1),"")} -> Light | Z35: =IF(NOT(Y35=""),_xlfn.XLOOKUP(Y35,'weapon masteries'!$A$10:$A$19,'weapon masteries'!$B$10:$B$19,"",0),"") -> A light weapon is small and easy to handle, making it ideal for use when fighting with two weapons. | AA35: {=IFERROR(INDEX(_xlfn.TEXTSPLIT(S35," "),,1),"")} -> Loading | AB35: =IF(NOT(AA35=""),_xlfn.XLOOKUP(AA35,'weapon masteries'!$A$10:$A$19,'weapon masteries'!$B$10:$B$19,"",0),"") -> Because of the time required to load this weapon, you can fire only one piece of ammunition from it when you use an action, bonus action, or reaction to fire it, regardless of the number of attacks you can normally make. | AC35: {=IFERROR(INDEX(_xlfn.TEXTSPLIT(T35," "),,1),"")} | AD35: =IF(NOT(AC35=""),_xlfn.XLOOKUP(AC35,'weapon masteries'!$A$10:$A$20,'weapon masteries'!$B$10:$B$20,"",0),"")
A36: Ranged Weapon Attack | B36: Heavy Crossbow (2014 edition) | C36: Dexterity | D36: range 100/400 ft | E36: 1d10 | F36: piercing | G36: Ammunition, Range (100/400), Heavy, Loading, Two-Handed | J36: =A36&": [ATK_MOD] to hit, "&D36&", one target. Hit: [DAMAGE] "&F36&" damage. "&I36 -> Ranged Weapon Attack: [ATK_MOD] to hit, range 100/400 ft, one target. Hit: [DAMAGE] piercing damage. | L36: =IF(NOT(G36=""),IF(COUNTA(P36:T36)>1,"Properties: ","Property: ")&U36&" ("&V36&")"&IF(NOT(W36=""),", "&W36&" ("&X36&")"&IF(NOT(Y36=""),", "&Y36&" ("&Z36&")"&IF(NOT(AA36=""),", "&AB36&" ("&AC36&")",""),""),""),"") -> Properties: Ammunition (You can use a weapon that has the ammunition property to make a ranged attack only if you have ammunition to fire from the weapon. Each time you attack with the weapon, you expend one piece of ammunition. Drawing the ammunition from a quiver, case, or other container is part of the attack. Loading a one-handed weapon requires a free hand. At the end of the battle, you can recover half your expended ammunition by taking a minute to search the battlefield. If you use a weapon that has the ammunition property to make a melee attack, you treat the weapon as an improvised weapon. A sling must be loaded to deal any damage when used in this way.), Range (A weapon that can be used to make a ranged attack has a range shown in parentheses after the ammunition or thrown property. The range lists two numbers. The first is the weapon’s normal range in feet, and the second indicates the weapon’s maximum range. When attacking a target beyond normal range, you have disadvantage on the attack roll. You can’t attack a target beyond the weapon’s long range.), Heavy (Creatures that are Small or Tiny have disadvantage on attack rolls with heavy weapons. A heavy weapon's size and bulk make it too large for a Small or Tiny creature to use effectively.), Because of the time required to load this weapon, you can fire only one piece of ammunition from it when you use an action, bonus action, or reaction to fire it, regardless of the number of attacks you can normally make. (Two-Handed) | P36: {=IFERROR(_xlfn.TEXTSPLIT(G36,", ",,TRUE),"")} -> Ammunition | Q36: Range (100/400) | R36: Heavy | S36: Loading | T36: Two-Handed | U36: {=IFERROR(INDEX(_xlfn.TEXTSPLIT(P36," "),,1),"")} -> Ammunition | V36: =IF(NOT(U36=""),_xlfn.XLOOKUP(U36,'weapon masteries'!$A$10:$A$19,'weapon masteries'!$B$10:$B$19,"",0),"") -> You can use a weapon that has the ammunition property to make a ranged attack only if you have ammunition to fire from the weapon. Each time you attack with the weapon, you expend one piece of ammunition. Drawing the ammunition from a quiver, case, or other container is part of the attack. Loading a one-handed weapon requires a free hand. At the end of the battle, you can recover half your expended ammunition by taking a minute to search the battlefield. If you use a weapon that has the ammunition property to make a melee attack, you treat the weapon as an improvised weapon. A sling must be loaded to deal any damage when used in this way. | W36: {=IFERROR(INDEX(_xlfn.TEXTSPLIT(Q36," "),,1),"")} -> Range | X36: =IF(NOT(W36=""),_xlfn.XLOOKUP(W36,'weapon masteries'!$A$10:$A$19,'weapon masteries'!$B$10:$B$19,"",0),"") -> A weapon that can be used to make a ranged attack has a range shown in parentheses after the ammunition or thrown property. The range lists two numbers. The first is the weapon’s normal range in feet, and the second indicates the weapon’s maximum range. When attacking a target beyond normal range, you have disadvantage on the attack roll. You can’t attack a target beyond the weapon’s long range. | Y36: {=IFERROR(INDEX(_xlfn.TEXTSPLIT(R36," "),,1),"")} -> Heavy | Z36: =IF(NOT(Y36=""),_xlfn.XLOOKUP(Y36,'weapon masteries'!$A$10:$A$19,'weapon masteries'!$B$10:$B$19,"",0),"") -> Creatures that are Small or Tiny have disadvantage on attack rolls with heavy weapons. A heavy weapon's size and bulk make it too large for a Small or Tiny creature to use effectively. | AA36: {=IFERROR(INDEX(_xlfn.TEXTSPLIT(S36," "),,1),"")} -> Loading | AB36: =IF(NOT(AA36=""),_xlfn.XLOOKUP(AA36,'weapon masteries'!$A$10:$A$19,'weapon masteries'!$B$10:$B$19,"",0),"") -> Because of the time required to load this weapon, you can fire only one piece of ammunition from it when you use an action, bonus action, or reaction to fire it, regardless of the number of attacks you can normally make. | AC36: {=IFERROR(INDEX(_xlfn.TEXTSPLIT(T36," "),,1),"")} -> Two-Handed | AD36: =IF(NOT(AC36=""),_xlfn.XLOOKUP(AC36,'weapon masteries'!$A$10:$A$20,'weapon masteries'!$B$10:$B$20,"",0),"") -> This weapon requires two hands to use. This property is relevant only when you attack with the weapon, not when you simply hold it.
A37: Ranged Weapon Attack | B37: Longbow (2014 edition) | C37: Dexterity | D37: range 150/600 ft | E37: 1d8 | F37: piercing | G37: Ammunition, Range (150/600), Heavy, Two-Handed | J37: =A37&": [ATK_MOD] to hit, "&D37&", one target. Hit: [DAMAGE] "&F37&" damage. "&I37 -> Ranged Weapon Attack: [ATK_MOD] to hit, range 150/600 ft, one target. Hit: [DAMAGE] piercing damage. | L37: =IF(NOT(G37=""),IF(COUNTA(P37:T37)>1,"Properties: ","Property: ")&U37&" ("&V37&")"&IF(NOT(W37=""),", "&W37&" ("&X37&")"&IF(NOT(Y37=""),", "&Y37&" ("&Z37&")"&IF(NOT(AA37=""),", "&AB37&" ("&AC37&")",""),""),""),"") -> Properties: Ammunition (You can use a weapon that has the ammunition property to make a ranged attack only if you have ammunition to fire from the weapon. Each time you attack with the weapon, you expend one piece of ammunition. Drawing the ammunition from a quiver, case, or other container is part of the attack. Loading a one-handed weapon requires a free hand. At the end of the battle, you can recover half your expended ammunition by taking a minute to search the battlefield. If you use a weapon that has the ammunition property to make a melee attack, you treat the weapon as an improvised weapon. A sling must be loaded to deal any damage when used in this way.), Range (A weapon that can be used to make a ranged attack has a range shown in parentheses after the ammunition or thrown property. The range lists two numbers. The first is the weapon’s normal range in feet, and the second indicates the weapon’s maximum range. When attacking a target beyond normal range, you have disadvantage on the attack roll. You can’t attack a target beyond the weapon’s long range.), Heavy (Creatures that are Small or Tiny have disadvantage on attack rolls with heavy weapons. A heavy weapon's size and bulk make it too large for a Small or Tiny creature to use effectively.), This weapon requires two hands to use. This property is relevant only when you attack with the weapon, not when you simply hold it. () | P37: {=IFERROR(_xlfn.TEXTSPLIT(G37,", ",,TRUE),"")} -> Ammunition | Q37: Range (150/600) | R37: Heavy | S37: Two-Handed | U37: {=IFERROR(INDEX(_xlfn.TEXTSPLIT(P37," "),,1),"")} -> Ammunition | V37: =IF(NOT(U37=""),_xlfn.XLOOKUP(U37,'weapon masteries'!$A$10:$A$19,'weapon masteries'!$B$10:$B$19,"",0),"") -> You can use a weapon that has the ammunition property to make a ranged attack only if you have ammunition to fire from the weapon. Each time you attack with the weapon, you expend one piece of ammunition. Drawing the ammunition from a quiver, case, or other container is part of the attack. Loading a one-handed weapon requires a free hand. At the end of the battle, you can recover half your expended ammunition by taking a minute to search the battlefield. If you use a weapon that has the ammunition property to make a melee attack, you treat the weapon as an improvised weapon. A sling must be loaded to deal any damage when used in this way. | W37: {=IFERROR(INDEX(_xlfn.TEXTSPLIT(Q37," "),,1),"")} -> Range | X37: =IF(NOT(W37=""),_xlfn.XLOOKUP(W37,'weapon masteries'!$A$10:$A$19,'weapon masteries'!$B$10:$B$19,"",0),"") -> A weapon that can be used to make a ranged attack has a range shown in parentheses after the ammunition or thrown property. The range lists two numbers. The first is the weapon’s normal range in feet, and the second indicates the weapon’s maximum range. When attacking a target beyond normal range, you have disadvantage on the attack roll. You can’t attack a target beyond the weapon’s long range. | Y37: {=IFERROR(INDEX(_xlfn.TEXTSPLIT(R37," "),,1),"")} -> Heavy | Z37: =IF(NOT(Y37=""),_xlfn.XLOOKUP(Y37,'weapon masteries'!$A$10:$A$19,'weapon masteries'!$B$10:$B$19,"",0),"") -> Creatures that are Small or Tiny have disadvantage on attack rolls with heavy weapons. A heavy weapon's size and bulk make it too large for a Small or Tiny creature to use effectively. | AA37: {=IFERROR(INDEX(_xlfn.TEXTSPLIT(S37," "),,1),"")} -> Two-Handed | AB37: =IF(NOT(AA37=""),_xlfn.XLOOKUP(AA37,'weapon masteries'!$A$10:$A$19,'weapon masteries'!$B$10:$B$19,"",0),"") -> This weapon requires two hands to use. This property is relevant only when you attack with the weapon, not when you simply hold it. | AC37: {=IFERROR(INDEX(_xlfn.TEXTSPLIT(T37," "),,1),"")} | AD37: =IF(NOT(AC37=""),_xlfn.XLOOKUP(AC37,'weapon masteries'!$A$10:$A$20,'weapon masteries'!$B$10:$B$20,"",0),"")
A38: Ranged Weapon Attack | B38: Net (2014 edition) | C38: Dexterity | D38: range 5/15 ft | G38: Thrown (5/15) | I38: A Large or smaller creature hit by a net is restrained until it is freed. A net has no effect on creatures that are formless, or creatures that are Huge or larger. A creature can use its action to make a DC 10 Strength check, freeing itself or another creature within its reach on a success. Dealing 5 slashing damage to the net (AC 10) also frees the creature without harming it, ending the effect and destroying the net. When the [MON] uses an action, bonus action, or reaction to attack with a net, it can make only one attack regardless of the number of attacks it can normally make. | J38: =A38&": [ATK_MOD] to hit, "&D38&", one target. Hit: [DAMAGE] "&F38&" damage. "&I38 -> Ranged Weapon Attack: [ATK_MOD] to hit, range 5/15 ft, one target. Hit: [DAMAGE] damage. A Large or smaller creature hit by a net is restrained until it is freed. A net has no effect on creatures that are formless, or creatures that are Huge or larger. A creature can use its action to make a DC 10 Strength check, freeing itself or another creature within its reach on a success. Dealing 5 slashing damage to the net (AC 10) also frees the creature without harming it, ending the effect and destroying the net. When the [MON] uses an action, bonus action, or reaction to attack with a net, it can make only one attack regardless of the number of attacks it can normally make. | L38: =IF(NOT(G38=""),IF(COUNTA(P38:T38)>1,"Properties: ","Property: ")&U38&" ("&V38&")"&IF(NOT(W38=""),", "&W38&" ("&X38&")"&IF(NOT(Y38=""),", "&Y38&" ("&Z38&")"&IF(NOT(AA38=""),", "&AB38&" ("&AC38&")",""),""),""),"") -> Property: Thrown (If a weapon has the thrown property, you can throw the weapon to make a ranged attack. If the weapon is a melee weapon, you use the same ability modifier for that attack roll and damage roll that you would use for a melee attack with the weapon. For example, if you throw a handaxe, you use your Strength, but if you throw a dagger, you can use either your Strength or your Dexterity, since the dagger has the finesse property.) | P38: {=IFERROR(_xlfn.TEXTSPLIT(G38,", ",,TRUE),"")} -> Thrown (5/15) | U38: {=IFERROR(INDEX(_xlfn.TEXTSPLIT(P38," "),,1),"")} -> Thrown | V38: =IF(NOT(U38=""),_xlfn.XLOOKUP(U38,'weapon masteries'!$A$10:$A$19,'weapon masteries'!$B$10:$B$19,"",0),"") -> If a weapon has the thrown property, you can throw the weapon to make a ranged attack. If the weapon is a melee weapon, you use the same ability modifier for that attack roll and damage roll that you would use for a melee attack with the weapon. For example, if you throw a handaxe, you use your Strength, but if you throw a dagger, you can use either your Strength or your Dexterity, since the dagger has the finesse property. | W38: {=IFERROR(INDEX(_xlfn.TEXTSPLIT(Q38," "),,1),"")} | X38: =IF(NOT(W38=""),_xlfn.XLOOKUP(W38,'weapon masteries'!$A$10:$A$19,'weapon masteries'!$B$10:$B$19,"",0),"") | Y38: {=IFERROR(INDEX(_xlfn.TEXTSPLIT(R38," "),,1),"")} | Z38: =IF(NOT(Y38=""),_xlfn.XLOOKUP(Y38,'weapon masteries'!$A$10:$A$19,'weapon masteries'!$B$10:$B$19,"",0),"") | AA38: {=IFERROR(INDEX(_xlfn.TEXTSPLIT(S38," "),,1),"")} | AB38: =IF(NOT(AA38=""),_xlfn.XLOOKUP(AA38,'weapon masteries'!$A$10:$A$19,'weapon masteries'!$B$10:$B$19,"",0),"") | AC38: {=IFERROR(INDEX(_xlfn.TEXTSPLIT(T38," "),,1),"")} | AD38: =IF(NOT(AC38=""),_xlfn.XLOOKUP(AC38,'weapon masteries'!$A$10:$A$20,'weapon masteries'!$B$10:$B$20,"",0),"")
A39: Melee Weapon Attack | B39: Club (2024 edition) | C39: Strength | D39: reach 5 ft | E39: 1d4 | F39: bludgeoning | G39: Light | H39: Slow | J39: =A39&": [ATK_MOD] to hit, "&D39&", one target. Hit: [DAMAGE] "&F39&" damage. "&I39 -> Melee Weapon Attack: [ATK_MOD] to hit, reach 5 ft, one target. Hit: [DAMAGE] bludgeoning damage. | K39: ="Mastery: "&H39&". "&_xlfn.XLOOKUP(H39,'weapon masteries'!A$2:A$9,'weapon masteries'!B$2:B$9,"",0) -> Mastery: Slow. If the [MON] hits a creature with this weapon and deals damage to it, it can reduce the target's speed by 10 feet until the start of the [MON]'s next turn. If the creature is hit more than once by weapons that have this property, the speed reduction doesn’t exceed 10 feet. | L39: =IF(NOT(G39=""),IF(COUNTA(P39:T39)>1,"Properties: ","Property: ")&U39&" ("&V39&")"&IF(NOT(W39=""),", "&W39&" ("&X39&")"&IF(NOT(Y39=""),", "&Y39&" ("&Z39&")"&IF(NOT(AA39=""),", "&AB39&" ("&AC39&")",""),""),""),"") -> Property: Light (When you take the Attack action on your turn and attack with a Light weapon, you can make one extra attack as a Bonus Action later on the same turn. That extra attack must be made with a different Light weapon, and you don’t add your ability modifier to the extra attack’s damage unless that modifier is negative. For example, you can attack with a Shortsword in one hand and a Dagger in the other using the Attack action and a Bonus Action, but you don't add your Strength or Dexterity modifier to the damage roll of the Bonus Action unless that modifier is negative.) | P39: {=IFERROR(_xlfn.TEXTSPLIT(G39,", ",,TRUE),"")} -> Light | U39: {=IFERROR(INDEX(_xlfn.TEXTSPLIT(P39," "),,1),"")} -> Light | V39: =IF(NOT(U39=""),_xlfn.XLOOKUP(U39,'weapon masteries'!$A$20:$A$29,'weapon masteries'!$B$20:$B$29,"",0),"") -> When you take the Attack action on your turn and attack with a Light weapon, you can make one extra attack as a Bonus Action later on the same turn. That extra attack must be made with a different Light weapon, and you don’t add your ability modifier to the extra attack’s damage unless that modifier is negative. For example, you can attack with a Shortsword in one hand and a Dagger in the other using the Attack action and a Bonus Action, but you don't add your Strength or Dexterity modifier to the damage roll of the Bonus Action unless that modifier is negative. | W39: {=IFERROR(INDEX(_xlfn.TEXTSPLIT(Q39," "),,1),"")} | X39: =IF(NOT(W39=""),_xlfn.XLOOKUP(W39,'weapon masteries'!$A$20:$A$29,'weapon masteries'!$B$20:$B$29,"",0),"") | Y39: {=IFERROR(INDEX(_xlfn.TEXTSPLIT(R39," "),,1),"")} | Z39: =IF(NOT(Y39=""),_xlfn.XLOOKUP(Y39,'weapon masteries'!$A$20:$A$29,'weapon masteries'!$B$20:$B$29,"",0),"") | AA39: {=IFERROR(INDEX(_xlfn.TEXTSPLIT(S39," "),,1),"")} | AB39: =IF(NOT(AA39=""),_xlfn.XLOOKUP(AA39,'weapon masteries'!$A$20:$A$29,'weapon masteries'!$B$20:$B$29,"",0),"") | AC39: {=IFERROR(INDEX(_xlfn.TEXTSPLIT(T39," "),,1),"")} | AD39: =IF(NOT(AC39=""),_xlfn.XLOOKUP(AC39,'weapon masteries'!$A$20:$A$29,'weapon masteries'!$B$20:$B$29,"",0),"")
A40: Melee or Ranged Weapon Attack | B40: Dagger (2024 edition) | C40: Max of Strength or Dexterity | D40: reach 5 ft or range 20/60 ft | E40: 1d4 | F40: piercing | G40: Finesse, Light, Thrown (Range 20/60) | H40: Nick | J40: =A40&": [ATK_MOD] to hit, "&D40&", one target. Hit: [DAMAGE] "&F40&" damage. "&I40 -> Melee or Ranged Weapon Attack: [ATK_MOD] to hit, reach 5 ft or range 20/60 ft, one target. Hit: [DAMAGE] piercing damage. | K40: ="Mastery: "&H40&". "&_xlfn.XLOOKUP(H40,'weapon masteries'!A$2:A$9,'weapon masteries'!B$2:B$9,"",0) -> Mastery: Nick. When the [MON] makes the extra attack of the Light property, it can make it as part of the Attack action instead of as a Bonus Action. It can make this extra attack only once per turn. | L40: =IF(NOT(G40=""),IF(COUNTA(P40:T40)>1,"Properties: ","Property: ")&U40&" ("&V40&")"&IF(NOT(W40=""),", "&W40&" ("&X40&")"&IF(NOT(Y40=""),", "&Y40&" ("&Z40&")"&IF(NOT(AA40=""),", "&AB40&" ("&AC40&")",""),""),""),"") -> Properties: Finesse (When making an attack with a Finesse weapon, use your choice of your Strength or Dexterity modifier for the attack and damage rolls. You must use the same modifier for both rolls.), Light (When you take the Attack action on your turn and attack with a Light weapon, you can make one extra attack as a Bonus Action later on the same turn. That extra attack must be made with a different Light weapon, and you don’t add your ability modifier to the extra attack’s damage unless that modifier is negative. For example, you can attack with a Shortsword in one hand and a Dagger in the other using the Attack action and a Bonus Action, but you don't add your Strength or Dexterity modifier to the damage roll of the Bonus Action unless that modifier is negative.), Thrown (If a weapon has the Thrown property, you can throw the weapon to make a ranged attack, and you can draw that weapon as part of the attack. If the weapon is a Melee weapon, use the same ability modifier for the attack and damage rolls that you use for a melee attack with that weapon.) | P40: {=IFERROR(_xlfn.TEXTSPLIT(G40,", ",,TRUE),"")} -> Finesse | Q40: Light | R40: Thrown (Range 20/60) | U40: {=IFERROR(INDEX(_xlfn.TEXTSPLIT(P40," "),,1),"")} -> Finesse | V40: =IF(NOT(U40=""),_xlfn.XLOOKUP(U40,'weapon masteries'!$A$20:$A$29,'weapon masteries'!$B$20:$B$29,"",0),"") -> When making an attack with a Finesse weapon, use your choice of your Strength or Dexterity modifier for the attack and damage rolls. You must use the same modifier for both rolls. | W40: {=IFERROR(INDEX(_xlfn.TEXTSPLIT(Q40," "),,1),"")} -> Light | X40: =IF(NOT(W40=""),_xlfn.XLOOKUP(W40,'weapon masteries'!$A$20:$A$29,'weapon masteries'!$B$20:$B$29,"",0),"") -> When you take the Attack action on your turn and attack with a Light weapon, you can make one extra attack as a Bonus Action later on the same turn. That extra attack must be made with a different Light weapon, and you don’t add your ability modifier to the extra attack’s damage unless that modifier is negative. For example, you can attack with a Shortsword in one hand and a Dagger in the other using the Attack action and a Bonus Action, but you don't add your Strength or Dexterity modifier to the damage roll of the Bonus Action unless that modifier is negative. | Y40: {=IFERROR(INDEX(_xlfn.TEXTSPLIT(R40," "),,1),"")} -> Thrown | Z40: =IF(NOT(Y40=""),_xlfn.XLOOKUP(Y40,'weapon masteries'!$A$20:$A$29,'weapon masteries'!$B$20:$B$29,"",0),"") -> If a weapon has the Thrown property, you can throw the weapon to make a ranged attack, and you can draw that weapon as part of the attack. If the weapon is a Melee weapon, use the same ability modifier for the attack and damage rolls that you use for a melee attack with that weapon. | AA40: {=IFERROR(INDEX(_xlfn.TEXTSPLIT(S40," "),,1),"")} | AB40: =IF(NOT(AA40=""),_xlfn.XLOOKUP(AA40,'weapon masteries'!$A$20:$A$29,'weapon masteries'!$B$20:$B$29,"",0),"") | AC40: {=IFERROR(INDEX(_xlfn.TEXTSPLIT(T40," "),,1),"")} | AD40: =IF(NOT(AC40=""),_xlfn.XLOOKUP(AC40,'weapon masteries'!$A$20:$A$29,'weapon masteries'!$B$20:$B$29,"",0),"")
A41: Melee Weapon Attack | B41: Greatclub (2024 edition) | C41: Strength | D41: reach 5 ft target | E41: 1d8 | F41: bludgeoning | G41: Two-Handed | H41: Push | J41: =A41&": [ATK_MOD] to hit, "&D41&", one target. Hit: [DAMAGE] "&F41&" damage. "&I41 -> Melee Weapon Attack: [ATK_MOD] to hit, reach 5 ft target, one target. Hit: [DAMAGE] bludgeoning damage. | K41: ="Mastery: "&H41&". "&_xlfn.XLOOKUP(H41,'weapon masteries'!A$2:A$9,'weapon masteries'!B$2:B$9,"",0) -> Mastery: Push. If the [MON] hits a creature with this weapon, it can push the creature up to 10 feet straight away from itself if it is Large or smaller. | L41: =IF(NOT(G41=""),IF(COUNTA(P41:T41)>1,"Properties: ","Property: ")&U41&" ("&V41&")"&IF(NOT(W41=""),", "&W41&" ("&X41&")"&IF(NOT(Y41=""),", "&Y41&" ("&Z41&")"&IF(NOT(AA41=""),", "&AB41&" ("&AC41&")",""),""),""),"") -> Property: Two-Handed (A Two-Handed weapon requires two hands when you attack with it.) | P41: {=IFERROR(_xlfn.TEXTSPLIT(G41,", ",,TRUE),"")} -> Two-Handed | U41: {=IFERROR(INDEX(_xlfn.TEXTSPLIT(P41," "),,1),"")} -> Two-Handed | V41: =IF(NOT(U41=""),_xlfn.XLOOKUP(U41,'weapon masteries'!$A$20:$A$29,'weapon masteries'!$B$20:$B$29,"",0),"") -> A Two-Handed weapon requires two hands when you attack with it. | W41: {=IFERROR(INDEX(_xlfn.TEXTSPLIT(Q41," "),,1),"")} | X41: =IF(NOT(W41=""),_xlfn.XLOOKUP(W41,'weapon masteries'!$A$20:$A$29,'weapon masteries'!$B$20:$B$29,"",0),"") | Y41: {=IFERROR(INDEX(_xlfn.TEXTSPLIT(R41," "),,1),"")} | Z41: =IF(NOT(Y41=""),_xlfn.XLOOKUP(Y41,'weapon masteries'!$A$20:$A$29,'weapon masteries'!$B$20:$B$29,"",0),"") | AA41: {=IFERROR(INDEX(_xlfn.TEXTSPLIT(S41," "),,1),"")} | AB41: =IF(NOT(AA41=""),_xlfn.XLOOKUP(AA41,'weapon masteries'!$A$20:$A$29,'weapon masteries'!$B$20:$B$29,"",0),"") | AC41: {=IFERROR(INDEX(_xlfn.TEXTSPLIT(T41," "),,1),"")} | AD41: =IF(NOT(AC41=""),_xlfn.XLOOKUP(AC41,'weapon masteries'!$A$20:$A$29,'weapon masteries'!$B$20:$B$29,"",0),"")
A42: Melee or Ranged Weapon Attack | B42: Handaxe (2024 edition) | C42: Max of Strength or Dexterity | D42: reach 5 ft or range 20/60 ft | E42: 1d6 | F42: slashing | G42: Light, Thrown (Range 20/60) | H42: Vex | J42: =A42&": [ATK_MOD] to hit, "&D42&", one target. Hit: [DAMAGE] "&F42&" damage. "&I42 -> Melee or Ranged Weapon Attack: [ATK_MOD] to hit, reach 5 ft or range 20/60 ft, one target. Hit: [DAMAGE] slashing damage. | K42: ="Mastery: "&H42&". "&_xlfn.XLOOKUP(H42,'weapon masteries'!A$2:A$9,'weapon masteries'!B$2:B$9,"",0) -> Mastery: Vex. If the [MON] hits a creature with this weapon and deals damage to the creature, it has Advantage on its next attack roll against that creature before the end of its next turn. | L42: =IF(NOT(G42=""),IF(COUNTA(P42:T42)>1,"Properties: ","Property: ")&U42&" ("&V42&")"&IF(NOT(W42=""),", "&W42&" ("&X42&")"&IF(NOT(Y42=""),", "&Y42&" ("&Z42&")"&IF(NOT(AA42=""),", "&AB42&" ("&AC42&")",""),""),""),"") -> Properties: Light (When you take the Attack action on your turn and attack with a Light weapon, you can make one extra attack as a Bonus Action later on the same turn. That extra attack must be made with a different Light weapon, and you don’t add your ability modifier to the extra attack’s damage unless that modifier is negative. For example, you can attack with a Shortsword in one hand and a Dagger in the other using the Attack action and a Bonus Action, but you don't add your Strength or Dexterity modifier to the damage roll of the Bonus Action unless that modifier is negative.), Thrown (If a weapon has the Thrown property, you can throw the weapon to make a ranged attack, and you can draw that weapon as part of the attack. If the weapon is a Melee weapon, use the same ability modifier for the attack and damage rolls that you use for a melee attack with that weapon.) | P42: {=IFERROR(_xlfn.TEXTSPLIT(G42,", ",,TRUE),"")} -> Light | Q42: Thrown (Range 20/60) | U42: {=IFERROR(INDEX(_xlfn.TEXTSPLIT(P42," "),,1),"")} -> Light | V42: =IF(NOT(U42=""),_xlfn.XLOOKUP(U42,'weapon masteries'!$A$20:$A$29,'weapon masteries'!$B$20:$B$29,"",0),"") -> When you take the Attack action on your turn and attack with a Light weapon, you can make one extra attack as a Bonus Action later on the same turn. That extra attack must be made with a different Light weapon, and you don’t add your ability modifier to the extra attack’s damage unless that modifier is negative. For example, you can attack with a Shortsword in one hand and a Dagger in the other using the Attack action and a Bonus Action, but you don't add your Strength or Dexterity modifier to the damage roll of the Bonus Action unless that modifier is negative. | W42: {=IFERROR(INDEX(_xlfn.TEXTSPLIT(Q42," "),,1),"")} -> Thrown | X42: =IF(NOT(W42=""),_xlfn.XLOOKUP(W42,'weapon masteries'!$A$20:$A$29,'weapon masteries'!$B$20:$B$29,"",0),"") -> If a weapon has the Thrown property, you can throw the weapon to make a ranged attack, and you can draw that weapon as part of the attack. If the weapon is a Melee weapon, use the same ability modifier for the attack and damage rolls that you use for a melee attack with that weapon. | Y42: {=IFERROR(INDEX(_xlfn.TEXTSPLIT(R42," "),,1),"")} | Z42: =IF(NOT(Y42=""),_xlfn.XLOOKUP(Y42,'weapon masteries'!$A$20:$A$29,'weapon masteries'!$B$20:$B$29,"",0),"") | AA42: {=IFERROR(INDEX(_xlfn.TEXTSPLIT(S42," "),,1),"")} | AB42: =IF(NOT(AA42=""),_xlfn.XLOOKUP(AA42,'weapon masteries'!$A$20:$A$29,'weapon masteries'!$B$20:$B$29,"",0),"") | AC42: {=IFERROR(INDEX(_xlfn.TEXTSPLIT(T42," "),,1),"")} | AD42: =IF(NOT(AC42=""),_xlfn.XLOOKUP(AC42,'weapon masteries'!$A$20:$A$29,'weapon masteries'!$B$20:$B$29,"",0),"")
A43: Melee or Ranged Weapon Attack | B43: Javelin (2024 edition) | C43: Strength | D43: reach 5 ft or range 30/120 ft | E43: 1d6 | F43: piercing | G43: Thrown (Range 30/120) | H43: Slow | J43: =A43&": [ATK_MOD] to hit, "&D43&", one target. Hit: [DAMAGE] "&F43&" damage. "&I43 -> Melee or Ranged Weapon Attack: [ATK_MOD] to hit, reach 5 ft or range 30/120 ft, one target. Hit: [DAMAGE] piercing damage. | K43: ="Mastery: "&H43&". "&_xlfn.XLOOKUP(H43,'weapon masteries'!A$2:A$9,'weapon masteries'!B$2:B$9,"",0) -> Mastery: Slow. If the [MON] hits a creature with this weapon and deals damage to it, it can reduce the target's speed by 10 feet until the start of the [MON]'s next turn. If the creature is hit more than once by weapons that have this property, the speed reduction doesn’t exceed 10 feet. | L43: =IF(NOT(G43=""),IF(COUNTA(P43:T43)>1,"Properties: ","Property: ")&U43&" ("&V43&")"&IF(NOT(W43=""),", "&W43&" ("&X43&")"&IF(NOT(Y43=""),", "&Y43&" ("&Z43&")"&IF(NOT(AA43=""),", "&AB43&" ("&AC43&")",""),""),""),"") -> Property: Thrown (If a weapon has the Thrown property, you can throw the weapon to make a ranged attack, and you can draw that weapon as part of the attack. If the weapon is a Melee weapon, use the same ability modifier for the attack and damage rolls that you use for a melee attack with that weapon.) | P43: {=IFERROR(_xlfn.TEXTSPLIT(G43,", ",,TRUE),"")} -> Thrown (Range 30/120) | U43: {=IFERROR(INDEX(_xlfn.TEXTSPLIT(P43," "),,1),"")} -> Thrown | V43: =IF(NOT(U43=""),_xlfn.XLOOKUP(U43,'weapon masteries'!$A$20:$A$29,'weapon masteries'!$B$20:$B$29,"",0),"") -> If a weapon has the Thrown property, you can throw the weapon to make a ranged attack, and you can draw that weapon as part of the attack. If the weapon is a Melee weapon, use the same ability modifier for the attack and damage rolls that you use for a melee attack with that weapon. | W43: {=IFERROR(INDEX(_xlfn.TEXTSPLIT(Q43," "),,1),"")} | X43: =IF(NOT(W43=""),_xlfn.XLOOKUP(W43,'weapon masteries'!$A$20:$A$29,'weapon masteries'!$B$20:$B$29,"",0),"") | Y43: {=IFERROR(INDEX(_xlfn.TEXTSPLIT(R43," "),,1),"")} | Z43: =IF(NOT(Y43=""),_xlfn.XLOOKUP(Y43,'weapon masteries'!$A$20:$A$29,'weapon masteries'!$B$20:$B$29,"",0),"") | AA43: {=IFERROR(INDEX(_xlfn.TEXTSPLIT(S43," "),,1),"")} | AB43: =IF(NOT(AA43=""),_xlfn.XLOOKUP(AA43,'weapon masteries'!$A$20:$A$29,'weapon masteries'!$B$20:$B$29,"",0),"") | AC43: {=IFERROR(INDEX(_xlfn.TEXTSPLIT(T43," "),,1),"")} | AD43: =IF(NOT(AC43=""),_xlfn.XLOOKUP(AC43,'weapon masteries'!$A$20:$A$29,'weapon masteries'!$B$20:$B$29,"",0),"")
A44: Melee or Ranged Weapon Attack | B44: Light Hammer (2024 edition) | C44: Max of Strength or Dexterity | D44: reach 5 ft or range 20/60 ft | E44: 1d4 | F44: bludgeoning | G44: Light, Thrown (Range 20/60) | H44: Nick | J44: =A44&": [ATK_MOD] to hit, "&D44&", one target. Hit: [DAMAGE] "&F44&" damage. "&I44 -> Melee or Ranged Weapon Attack: [ATK_MOD] to hit, reach 5 ft or range 20/60 ft, one target. Hit: [DAMAGE] bludgeoning damage. | K44: ="Mastery: "&H44&". "&_xlfn.XLOOKUP(H44,'weapon masteries'!A$2:A$9,'weapon masteries'!B$2:B$9,"",0) -> Mastery: Nick. When the [MON] makes the extra attack of the Light property, it can make it as part of the Attack action instead of as a Bonus Action. It can make this extra attack only once per turn. | L44: =IF(NOT(G44=""),IF(COUNTA(P44:T44)>1,"Properties: ","Property: ")&U44&" ("&V44&")"&IF(NOT(W44=""),", "&W44&" ("&X44&")"&IF(NOT(Y44=""),", "&Y44&" ("&Z44&")"&IF(NOT(AA44=""),", "&AB44&" ("&AC44&")",""),""),""),"") -> Properties: Light (When you take the Attack action on your turn and attack with a Light weapon, you can make one extra attack as a Bonus Action later on the same turn. That extra attack must be made with a different Light weapon, and you don’t add your ability modifier to the extra attack’s damage unless that modifier is negative. For example, you can attack with a Shortsword in one hand and a Dagger in the other using the Attack action and a Bonus Action, but you don't add your Strength or Dexterity modifier to the damage roll of the Bonus Action unless that modifier is negative.), Thrown (If a weapon has the Thrown property, you can throw the weapon to make a ranged attack, and you can draw that weapon as part of the attack. If the weapon is a Melee weapon, use the same ability modifier for the attack and damage rolls that you use for a melee attack with that weapon.) | P44: {=IFERROR(_xlfn.TEXTSPLIT(G44,", ",,TRUE),"")} -> Light | Q44: Thrown (Range 20/60) | U44: {=IFERROR(INDEX(_xlfn.TEXTSPLIT(P44," "),,1),"")} -> Light | V44: =IF(NOT(U44=""),_xlfn.XLOOKUP(U44,'weapon masteries'!$A$20:$A$29,'weapon masteries'!$B$20:$B$29,"",0),"") -> When you take the Attack action on your turn and attack with a Light weapon, you can make one extra attack as a Bonus Action later on the same turn. That extra attack must be made with a different Light weapon, and you don’t add your ability modifier to the extra attack’s damage unless that modifier is negative. For example, you can attack with a Shortsword in one hand and a Dagger in the other using the Attack action and a Bonus Action, but you don't add your Strength or Dexterity modifier to the damage roll of the Bonus Action unless that modifier is negative. | W44: {=IFERROR(INDEX(_xlfn.TEXTSPLIT(Q44," "),,1),"")} -> Thrown | X44: =IF(NOT(W44=""),_xlfn.XLOOKUP(W44,'weapon masteries'!$A$20:$A$29,'weapon masteries'!$B$20:$B$29,"",0),"") -> If a weapon has the Thrown property, you can throw the weapon to make a ranged attack, and you can draw that weapon as part of the attack. If the weapon is a Melee weapon, use the same ability modifier for the attack and damage rolls that you use for a melee attack with that weapon. | Y44: {=IFERROR(INDEX(_xlfn.TEXTSPLIT(R44," "),,1),"")} | Z44: =IF(NOT(Y44=""),_xlfn.XLOOKUP(Y44,'weapon masteries'!$A$20:$A$29,'weapon masteries'!$B$20:$B$29,"",0),"") | AA44: {=IFERROR(INDEX(_xlfn.TEXTSPLIT(S44," "),,1),"")} | AB44: =IF(NOT(AA44=""),_xlfn.XLOOKUP(AA44,'weapon masteries'!$A$20:$A$29,'weapon masteries'!$B$20:$B$29,"",0),"") | AC44: {=IFERROR(INDEX(_xlfn.TEXTSPLIT(T44," "),,1),"")} | AD44: =IF(NOT(AC44=""),_xlfn.XLOOKUP(AC44,'weapon masteries'!$A$20:$A$29,'weapon masteries'!$B$20:$B$29,"",0),"")
A45: Melee Weapon Attack | B45: Mace (2024 edition) | C45: Strength | D45: reach 5 ft | E45: 1d6 | F45: bludgeoning | H45: Sap | J45: =A45&": [ATK_MOD] to hit, "&D45&", one target. Hit: [DAMAGE] "&F45&" damage. "&I45 -> Melee Weapon Attack: [ATK_MOD] to hit, reach 5 ft, one target. Hit: [DAMAGE] bludgeoning damage. | K45: ="Mastery: "&H45&". "&_xlfn.XLOOKUP(H45,'weapon masteries'!A$2:A$9,'weapon masteries'!B$2:B$9,"",0) -> Mastery: Sap. If the [MON] hits a creature with this weapon, that creature has disadvantage on its next attack roll before the start of the [MON]'s next turn. | L45: =IF(NOT(G45=""),IF(COUNTA(P45:T45)>1,"Properties: ","Property: ")&U45&" ("&V45&")"&IF(NOT(W45=""),", "&W45&" ("&X45&")"&IF(NOT(Y45=""),", "&Y45&" ("&Z45&")"&IF(NOT(AA45=""),", "&AB45&" ("&AC45&")",""),""),""),"") | P45: {=IFERROR(_xlfn.TEXTSPLIT(G45,", ",,TRUE),"")} | U45: {=IFERROR(INDEX(_xlfn.TEXTSPLIT(P45," "),,1),"")} | V45: =IF(NOT(U45=""),_xlfn.XLOOKUP(U45,'weapon masteries'!$A$20:$A$29,'weapon masteries'!$B$20:$B$29,"",0),"") | W45: {=IFERROR(INDEX(_xlfn.TEXTSPLIT(Q45," "),,1),"")} | X45: =IF(NOT(W45=""),_xlfn.XLOOKUP(W45,'weapon masteries'!$A$20:$A$29,'weapon masteries'!$B$20:$B$29,"",0),"") | Y45: {=IFERROR(INDEX(_xlfn.TEXTSPLIT(R45," "),,1),"")} | Z45: =IF(NOT(Y45=""),_xlfn.XLOOKUP(Y45,'weapon masteries'!$A$20:$A$29,'weapon masteries'!$B$20:$B$29,"",0),"") | AA45: {=IFERROR(INDEX(_xlfn.TEXTSPLIT(S45," "),,1),"")} | AB45: =IF(NOT(AA45=""),_xlfn.XLOOKUP(AA45,'weapon masteries'!$A$20:$A$29,'weapon masteries'!$B$20:$B$29,"",0),"") | AC45: {=IFERROR(INDEX(_xlfn.TEXTSPLIT(T45," "),,1),"")} | AD45: =IF(NOT(AC45=""),_xlfn.XLOOKUP(AC45,'weapon masteries'!$A$20:$A$29,'weapon masteries'!$B$20:$B$29,"",0),"")
A46: Melee Weapon Attack | B46: Quarterstaff (2024 edition) | C46: Strength | D46: reach 5 ft | E46: 1d6 | F46: bludgeoning | G46: Versatile (1d8) | H46: Topple | J46: =A46&": [ATK_MOD] to hit, "&D46&", one target. Hit: [DAMAGE] "&F46&" damage. "&I46 -> Melee Weapon Attack: [ATK_MOD] to hit, reach 5 ft, one target. Hit: [DAMAGE] bludgeoning damage. | K46: ="Mastery: "&H46&". "&_xlfn.XLOOKUP(H46,'weapon masteries'!A$2:A$9,'weapon masteries'!B$2:B$9,"",0) -> Mastery: Topple. If the [MON] hits a creature with this weapon, it can force the creature to make a Constitution saving throw (DC 8 plus the ability modifier used to make the attack roll and your Proficiency Bonus). On a failed save, the creature has the Prone condition. | L46: =IF(NOT(G46=""),IF(COUNTA(P46:T46)>1,"Properties: ","Property: ")&U46&" ("&V46&")"&IF(NOT(W46=""),", "&W46&" ("&X46&")"&IF(NOT(Y46=""),", "&Y46&" ("&Z46&")"&IF(NOT(AA46=""),", "&AB46&" ("&AC46&")",""),""),""),"") -> Property: Versatile (A Versatile weapon can be used with one or two hands. A damage value in parentheses appears with the property. The weapon deals that damage when used with two hands to make a melee attack.) | P46: {=IFERROR(_xlfn.TEXTSPLIT(G46,", ",,TRUE),"")} -> Versatile (1d8) | U46: {=IFERROR(INDEX(_xlfn.TEXTSPLIT(P46," "),,1),"")} -> Versatile | V46: =IF(NOT(U46=""),_xlfn.XLOOKUP(U46,'weapon masteries'!$A$20:$A$29,'weapon masteries'!$B$20:$B$29,"",0),"") -> A Versatile weapon can be used with one or two hands. A damage value in parentheses appears with the property. The weapon deals that damage when used with two hands to make a melee attack. | W46: {=IFERROR(INDEX(_xlfn.TEXTSPLIT(Q46," "),,1),"")} | X46: =IF(NOT(W46=""),_xlfn.XLOOKUP(W46,'weapon masteries'!$A$20:$A$29,'weapon masteries'!$B$20:$B$29,"",0),"") | Y46: {=IFERROR(INDEX(_xlfn.TEXTSPLIT(R46," "),,1),"")} | Z46: =IF(NOT(Y46=""),_xlfn.XLOOKUP(Y46,'weapon masteries'!$A$20:$A$29,'weapon masteries'!$B$20:$B$29,"",0),"") | AA46: {=IFERROR(INDEX(_xlfn.TEXTSPLIT(S46," "),,1),"")} | AB46: =IF(NOT(AA46=""),_xlfn.XLOOKUP(AA46,'weapon masteries'!$A$20:$A$29,'weapon masteries'!$B$20:$B$29,"",0),"") | AC46: {=IFERROR(INDEX(_xlfn.TEXTSPLIT(T46," "),,1),"")} | AD46: =IF(NOT(AC46=""),_xlfn.XLOOKUP(AC46,'weapon masteries'!$A$20:$A$29,'weapon masteries'!$B$20:$B$29,"",0),"")
A47: Melee Weapon Attack | B47: Sickle (2024 edition) | C47: Max of Strength or Dexterity | D47: reach 5 ft | E47: 1d4 | F47: slashing | G47: Light | H47: Nick | J47: =A47&": [ATK_MOD] to hit, "&D47&", one target. Hit: [DAMAGE] "&F47&" damage. "&I47 -> Melee Weapon Attack: [ATK_MOD] to hit, reach 5 ft, one target. Hit: [DAMAGE] slashing damage. | K47: ="Mastery: "&H47&". "&_xlfn.XLOOKUP(H47,'weapon masteries'!A$2:A$9,'weapon masteries'!B$2:B$9,"",0) -> Mastery: Nick. When the [MON] makes the extra attack of the Light property, it can make it as part of the Attack action instead of as a Bonus Action. It can make this extra attack only once per turn. | L47: =IF(NOT(G47=""),IF(COUNTA(P47:T47)>1,"Properties: ","Property: ")&U47&" ("&V47&")"&IF(NOT(W47=""),", "&W47&" ("&X47&")"&IF(NOT(Y47=""),", "&Y47&" ("&Z47&")"&IF(NOT(AA47=""),", "&AB47&" ("&AC47&")",""),""),""),"") -> Property: Light (When you take the Attack action on your turn and attack with a Light weapon, you can make one extra attack as a Bonus Action later on the same turn. That extra attack must be made with a different Light weapon, and you don’t add your ability modifier to the extra attack’s damage unless that modifier is negative. For example, you can attack with a Shortsword in one hand and a Dagger in the other using the Attack action and a Bonus Action, but you don't add your Strength or Dexterity modifier to the damage roll of the Bonus Action unless that modifier is negative.) | P47: {=IFERROR(_xlfn.TEXTSPLIT(G47,", ",,TRUE),"")} -> Light | U47: {=IFERROR(INDEX(_xlfn.TEXTSPLIT(P47," "),,1),"")} -> Light | V47: =IF(NOT(U47=""),_xlfn.XLOOKUP(U47,'weapon masteries'!$A$20:$A$29,'weapon masteries'!$B$20:$B$29,"",0),"") -> When you take the Attack action on your turn and attack with a Light weapon, you can make one extra attack as a Bonus Action later on the same turn. That extra attack must be made with a different Light weapon, and you don’t add your ability modifier to the extra attack’s damage unless that modifier is negative. For example, you can attack with a Shortsword in one hand and a Dagger in the other using the Attack action and a Bonus Action, but you don't add your Strength or Dexterity modifier to the damage roll of the Bonus Action unless that modifier is negative. | W47: {=IFERROR(INDEX(_xlfn.TEXTSPLIT(Q47," "),,1),"")} | X47: =IF(NOT(W47=""),_xlfn.XLOOKUP(W47,'weapon masteries'!$A$20:$A$29,'weapon masteries'!$B$20:$B$29,"",0),"") | Y47: {=IFERROR(INDEX(_xlfn.TEXTSPLIT(R47," "),,1),"")} | Z47: =IF(NOT(Y47=""),_xlfn.XLOOKUP(Y47,'weapon masteries'!$A$20:$A$29,'weapon masteries'!$B$20:$B$29,"",0),"") | AA47: {=IFERROR(INDEX(_xlfn.TEXTSPLIT(S47," "),,1),"")} | AB47: =IF(NOT(AA47=""),_xlfn.XLOOKUP(AA47,'weapon masteries'!$A$20:$A$29,'weapon masteries'!$B$20:$B$29,"",0),"") | AC47: {=IFERROR(INDEX(_xlfn.TEXTSPLIT(T47," "),,1),"")} | AD47: =IF(NOT(AC47=""),_xlfn.XLOOKUP(AC47,'weapon masteries'!$A$20:$A$29,'weapon masteries'!$B$20:$B$29,"",0),"")
A48: Melee or Ranged Weapon Attack | B48: Spear (2024 edition) | C48: Strength | D48: reach 5 ft or range 20/60 ft | E48: 1d6 | F48: piercing | G48: Thrown (Range 20/60), Versatile (1d8) | H48: Sap | J48: =A48&": [ATK_MOD] to hit, "&D48&", one target. Hit: [DAMAGE] "&F48&" damage. "&I48 -> Melee or Ranged Weapon Attack: [ATK_MOD] to hit, reach 5 ft or range 20/60 ft, one target. Hit: [DAMAGE] piercing damage. | K48: ="Mastery: "&H48&". "&_xlfn.XLOOKUP(H48,'weapon masteries'!A$2:A$9,'weapon masteries'!B$2:B$9,"",0) -> Mastery: Sap. If the [MON] hits a creature with this weapon, that creature has disadvantage on its next attack roll before the start of the [MON]'s next turn. | L48: =IF(NOT(G48=""),IF(COUNTA(P48:T48)>1,"Properties: ","Property: ")&U48&" ("&V48&")"&IF(NOT(W48=""),", "&W48&" ("&X48&")"&IF(NOT(Y48=""),", "&Y48&" ("&Z48&")"&IF(NOT(AA48=""),", "&AB48&" ("&AC48&")",""),""),""),"") -> Properties: Thrown (If a weapon has the Thrown property, you can throw the weapon to make a ranged attack, and you can draw that weapon as part of the attack. If the weapon is a Melee weapon, use the same ability modifier for the attack and damage rolls that you use for a melee attack with that weapon.), Versatile (A Versatile weapon can be used with one or two hands. A damage value in parentheses appears with the property. The weapon deals that damage when used with two hands to make a melee attack.) | P48: {=IFERROR(_xlfn.TEXTSPLIT(G48,", ",,TRUE),"")} -> Thrown (Range 20/60) | Q48: Versatile (1d8) | U48: {=IFERROR(INDEX(_xlfn.TEXTSPLIT(P48," "),,1),"")} -> Thrown | V48: =IF(NOT(U48=""),_xlfn.XLOOKUP(U48,'weapon masteries'!$A$20:$A$29,'weapon masteries'!$B$20:$B$29,"",0),"") -> If a weapon has the Thrown property, you can throw the weapon to make a ranged attack, and you can draw that weapon as part of the attack. If the weapon is a Melee weapon, use the same ability modifier for the attack and damage rolls that you use for a melee attack with that weapon. | W48: {=IFERROR(INDEX(_xlfn.TEXTSPLIT(Q48," "),,1),"")} -> Versatile | X48: =IF(NOT(W48=""),_xlfn.XLOOKUP(W48,'weapon masteries'!$A$20:$A$29,'weapon masteries'!$B$20:$B$29,"",0),"") -> A Versatile weapon can be used with one or two hands. A damage value in parentheses appears with the property. The weapon deals that damage when used with two hands to make a melee attack. | Y48: {=IFERROR(INDEX(_xlfn.TEXTSPLIT(R48," "),,1),"")} | Z48: =IF(NOT(Y48=""),_xlfn.XLOOKUP(Y48,'weapon masteries'!$A$20:$A$29,'weapon masteries'!$B$20:$B$29,"",0),"") | AA48: {=IFERROR(INDEX(_xlfn.TEXTSPLIT(S48," "),,1),"")} | AB48: =IF(NOT(AA48=""),_xlfn.XLOOKUP(AA48,'weapon masteries'!$A$20:$A$29,'weapon masteries'!$B$20:$B$29,"",0),"") | AC48: {=IFERROR(INDEX(_xlfn.TEXTSPLIT(T48," "),,1),"")} | AD48: =IF(NOT(AC48=""),_xlfn.XLOOKUP(AC48,'weapon masteries'!$A$20:$A$29,'weapon masteries'!$B$20:$B$29,"",0),"")
A49: Ranged Weapon Attack | B49: Light Crossbow (2024 edition) | C49: Dexterity | D49: range 80/320 ft | E49: 1d8 | F49: piercing | G49: Ammunition (Range 80/320; Bolt), Loading, Two-Handed | H49: Slow | J49: =A49&": [ATK_MOD] to hit, "&D49&", one target. Hit: [DAMAGE] "&F49&" damage. "&I49 -> Ranged Weapon Attack: [ATK_MOD] to hit, range 80/320 ft, one target. Hit: [DAMAGE] piercing damage. | K49: ="Mastery: "&H49&". "&_xlfn.XLOOKUP(H49,'weapon masteries'!A$2:A$9,'weapon masteries'!B$2:B$9,"",0) -> Mastery: Slow. If the [MON] hits a creature with this weapon and deals damage to it, it can reduce the target's speed by 10 feet until the start of the [MON]'s next turn. If the creature is hit more than once by weapons that have this property, the speed reduction doesn’t exceed 10 feet. | L49: =IF(NOT(G49=""),IF(COUNTA(P49:T49)>1,"Properties: ","Property: ")&U49&" ("&V49&")"&IF(NOT(W49=""),", "&W49&" ("&X49&")"&IF(NOT(Y49=""),", "&Y49&" ("&Z49&")"&IF(NOT(AA49=""),", "&AB49&" ("&AC49&")",""),""),""),"") -> Properties: Ammunition (You can use a weapon that has the Ammunition property to make a ranged attack only if you have ammunition to fire from it. The type of ammunition required is specified with the weapon's range. Each attack expends one piece of ammunition. Drawing the ammunition is part of the attack (you need a free hand to load a one-handed weapon). After a fight, you can spend 1 minute to recover half the ammunition (round down) you used in the fight; the rest is lost.), Loading (You can fire only one piece of ammunition from a Loading weapon when you use an action, a Bonus Action, or a Reaction to fire it, regardless of the number of attacks you can normally make.), Two-Handed (A Two-Handed weapon requires two hands when you attack with it.) | P49: {=IFERROR(_xlfn.TEXTSPLIT(G49,", ",,TRUE),"")} -> Ammunition (Range 80/320; Bolt) | Q49: Loading | R49: Two-Handed | U49: {=IFERROR(INDEX(_xlfn.TEXTSPLIT(P49," "),,1),"")} -> Ammunition | V49: =IF(NOT(U49=""),_xlfn.XLOOKUP(U49,'weapon masteries'!$A$20:$A$29,'weapon masteries'!$B$20:$B$29,"",0),"") -> You can use a weapon that has the Ammunition property to make a ranged attack only if you have ammunition to fire from it. The type of ammunition required is specified with the weapon's range. Each attack expends one piece of ammunition. Drawing the ammunition is part of the attack (you need a free hand to load a one-handed weapon). After a fight, you can spend 1 minute to recover half the ammunition (round down) you used in the fight; the rest is lost. | W49: {=IFERROR(INDEX(_xlfn.TEXTSPLIT(Q49," "),,1),"")} -> Loading | X49: =IF(NOT(W49=""),_xlfn.XLOOKUP(W49,'weapon masteries'!$A$20:$A$29,'weapon masteries'!$B$20:$B$29,"",0),"") -> You can fire only one piece of ammunition from a Loading weapon when you use an action, a Bonus Action, or a Reaction to fire it, regardless of the number of attacks you can normally make. | Y49: {=IFERROR(INDEX(_xlfn.TEXTSPLIT(R49," "),,1),"")} -> Two-Handed | Z49: =IF(NOT(Y49=""),_xlfn.XLOOKUP(Y49,'weapon masteries'!$A$20:$A$29,'weapon masteries'!$B$20:$B$29,"",0),"") -> A Two-Handed weapon requires two hands when you attack with it. | AA49: {=IFERROR(INDEX(_xlfn.TEXTSPLIT(S49," "),,1),"")} | AB49: =IF(NOT(AA49=""),_xlfn.XLOOKUP(AA49,'weapon masteries'!$A$20:$A$29,'weapon masteries'!$B$20:$B$29,"",0),"") | AC49: {=IFERROR(INDEX(_xlfn.TEXTSPLIT(T49," "),,1),"")} | AD49: =IF(NOT(AC49=""),_xlfn.XLOOKUP(AC49,'weapon masteries'!$A$20:$A$29,'weapon masteries'!$B$20:$B$29,"",0),"")
A50: Ranged Weapon Attack | B50: Dart (2024 edition) | C50: Dexterity | D50: range 20/60 ft | E50: 1d4 | F50: piercing | G50: Finesse, Thrown (Range 20/60) | H50: Vex | J50: =A50&": [ATK_MOD] to hit, "&D50&", one target. Hit: [DAMAGE] "&F50&" damage. "&I50 -> Ranged Weapon Attack: [ATK_MOD] to hit, range 20/60 ft, one target. Hit: [DAMAGE] piercing damage. | K50: ="Mastery: "&H50&". "&_xlfn.XLOOKUP(H50,'weapon masteries'!A$2:A$9,'weapon masteries'!B$2:B$9,"",0) -> Mastery: Vex. If the [MON] hits a creature with this weapon and deals damage to the creature, it has Advantage on its next attack roll against that creature before the end of its next turn. | L50: =IF(NOT(G50=""),IF(COUNTA(P50:T50)>1,"Properties: ","Property: ")&U50&" ("&V50&")"&IF(NOT(W50=""),", "&W50&" ("&X50&")"&IF(NOT(Y50=""),", "&Y50&" ("&Z50&")"&IF(NOT(AA50=""),", "&AB50&" ("&AC50&")",""),""),""),"") -> Properties: Finesse (When making an attack with a Finesse weapon, use your choice of your Strength or Dexterity modifier for the attack and damage rolls. You must use the same modifier for both rolls.), Thrown (If a weapon has the Thrown property, you can throw the weapon to make a ranged attack, and you can draw that weapon as part of the attack. If the weapon is a Melee weapon, use the same ability modifier for the attack and damage rolls that you use for a melee attack with that weapon.) | P50: {=IFERROR(_xlfn.TEXTSPLIT(G50,", ",,TRUE),"")} -> Finesse | Q50: Thrown (Range 20/60) | U50: {=IFERROR(INDEX(_xlfn.TEXTSPLIT(P50," "),,1),"")} -> Finesse | V50: =IF(NOT(U50=""),_xlfn.XLOOKUP(U50,'weapon masteries'!$A$20:$A$29,'weapon masteries'!$B$20:$B$29,"",0),"") -> When making an attack with a Finesse weapon, use your choice of your Strength or Dexterity modifier for the attack and damage rolls. You must use the same modifier for both rolls. | W50: {=IFERROR(INDEX(_xlfn.TEXTSPLIT(Q50," "),,1),"")} -> Thrown | X50: =IF(NOT(W50=""),_xlfn.XLOOKUP(W50,'weapon masteries'!$A$20:$A$29,'weapon masteries'!$B$20:$B$29,"",0),"") -> If a weapon has the Thrown property, you can throw the weapon to make a ranged attack, and you can draw that weapon as part of the attack. If the weapon is a Melee weapon, use the same ability modifier for the attack and damage rolls that you use for a melee attack with that weapon. | Y50: {=IFERROR(INDEX(_xlfn.TEXTSPLIT(R50," "),,1),"")} | Z50: =IF(NOT(Y50=""),_xlfn.XLOOKUP(Y50,'weapon masteries'!$A$20:$A$29,'weapon masteries'!$B$20:$B$29,"",0),"") | AA50: {=IFERROR(INDEX(_xlfn.TEXTSPLIT(S50," "),,1),"")} | AB50: =IF(NOT(AA50=""),_xlfn.XLOOKUP(AA50,'weapon masteries'!$A$20:$A$29,'weapon masteries'!$B$20:$B$29,"",0),"") | AC50: {=IFERROR(INDEX(_xlfn.TEXTSPLIT(T50," "),,1),"")} | AD50: =IF(NOT(AC50=""),_xlfn.XLOOKUP(AC50,'weapon masteries'!$A$20:$A$29,'weapon masteries'!$B$20:$B$29,"",0),"")
A51: Ranged Weapon Attack | B51: Shortbow (2024 edition) | C51: Dexterity | D51: range 80/320 ft | E51: 1d6 | F51: piercing | G51: Ammunition (Range 80/320; Arrow), Two-Handed | H51: Vex | J51: =A51&": [ATK_MOD] to hit, "&D51&", one target. Hit: [DAMAGE] "&F51&" damage. "&I51 -> Ranged Weapon Attack: [ATK_MOD] to hit, range 80/320 ft, one target. Hit: [DAMAGE] piercing damage. | K51: ="Mastery: "&H51&". "&_xlfn.XLOOKUP(H51,'weapon masteries'!A$2:A$9,'weapon masteries'!B$2:B$9,"",0) -> Mastery: Vex. If the [MON] hits a creature with this weapon and deals damage to the creature, it has Advantage on its next attack roll against that creature before the end of its next turn. | L51: =IF(NOT(G51=""),IF(COUNTA(P51:T51)>1,"Properties: ","Property: ")&U51&" ("&V51&")"&IF(NOT(W51=""),", "&W51&" ("&X51&")"&IF(NOT(Y51=""),", "&Y51&" ("&Z51&")"&IF(NOT(AA51=""),", "&AB51&" ("&AC51&")",""),""),""),"") -> Properties: Ammunition (You can use a weapon that has the Ammunition property to make a ranged attack only if you have ammunition to fire from it. The type of ammunition required is specified with the weapon's range. Each attack expends one piece of ammunition. Drawing the ammunition is part of the attack (you need a free hand to load a one-handed weapon). After a fight, you can spend 1 minute to recover half the ammunition (round down) you used in the fight; the rest is lost.), Two-Handed (A Two-Handed weapon requires two hands when you attack with it.) | P51: {=IFERROR(_xlfn.TEXTSPLIT(G51,", ",,TRUE),"")} -> Ammunition (Range 80/320; Arrow) | Q51: Two-Handed | U51: {=IFERROR(INDEX(_xlfn.TEXTSPLIT(P51," "),,1),"")} -> Ammunition | V51: =IF(NOT(U51=""),_xlfn.XLOOKUP(U51,'weapon masteries'!$A$20:$A$29,'weapon masteries'!$B$20:$B$29,"",0),"") -> You can use a weapon that has the Ammunition property to make a ranged attack only if you have ammunition to fire from it. The type of ammunition required is specified with the weapon's range. Each attack expends one piece of ammunition. Drawing the ammunition is part of the attack (you need a free hand to load a one-handed weapon). After a fight, you can spend 1 minute to recover half the ammunition (round down) you used in the fight; the rest is lost. | W51: {=IFERROR(INDEX(_xlfn.TEXTSPLIT(Q51," "),,1),"")} -> Two-Handed | X51: =IF(NOT(W51=""),_xlfn.XLOOKUP(W51,'weapon masteries'!$A$20:$A$29,'weapon masteries'!$B$20:$B$29,"",0),"") -> A Two-Handed weapon requires two hands when you attack with it. | Y51: {=IFERROR(INDEX(_xlfn.TEXTSPLIT(R51," "),,1),"")} | Z51: =IF(NOT(Y51=""),_xlfn.XLOOKUP(Y51,'weapon masteries'!$A$20:$A$29,'weapon masteries'!$B$20:$B$29,"",0),"") | AA51: {=IFERROR(INDEX(_xlfn.TEXTSPLIT(S51," "),,1),"")} | AB51: =IF(NOT(AA51=""),_xlfn.XLOOKUP(AA51,'weapon masteries'!$A$20:$A$29,'weapon masteries'!$B$20:$B$29,"",0),"") | AC51: {=IFERROR(INDEX(_xlfn.TEXTSPLIT(T51," "),,1),"")} | AD51: =IF(NOT(AC51=""),_xlfn.XLOOKUP(AC51,'weapon masteries'!$A$20:$A$29,'weapon masteries'!$B$20:$B$29,"",0),"")
A52: Ranged Weapon Attack | B52: Sling (2024 edition) | C52: Dexterity | D52: range 30/120 ft | E52: 1d4 | F52: bludgeoning | G52: Ammunition (Range 30/120; Bullet) | H52: Slow | J52: =A52&": [ATK_MOD] to hit, "&D52&", one target. Hit: [DAMAGE] "&F52&" damage. "&I52 -> Ranged Weapon Attack: [ATK_MOD] to hit, range 30/120 ft, one target. Hit: [DAMAGE] bludgeoning damage. | K52: ="Mastery: "&H52&". "&_xlfn.XLOOKUP(H52,'weapon masteries'!A$2:A$9,'weapon masteries'!B$2:B$9,"",0) -> Mastery: Slow. If the [MON] hits a creature with this weapon and deals damage to it, it can reduce the target's speed by 10 feet until the start of the [MON]'s next turn. If the creature is hit more than once by weapons that have this property, the speed reduction doesn’t exceed 10 feet. | L52: =IF(NOT(G52=""),IF(COUNTA(P52:T52)>1,"Properties: ","Property: ")&U52&" ("&V52&")"&IF(NOT(W52=""),", "&W52&" ("&X52&")"&IF(NOT(Y52=""),", "&Y52&" ("&Z52&")"&IF(NOT(AA52=""),", "&AB52&" ("&AC52&")",""),""),""),"") -> Property: Ammunition (You can use a weapon that has the Ammunition property to make a ranged attack only if you have ammunition to fire from it. The type of ammunition required is specified with the weapon's range. Each attack expends one piece of ammunition. Drawing the ammunition is part of the attack (you need a free hand to load a one-handed weapon). After a fight, you can spend 1 minute to recover half the ammunition (round down) you used in the fight; the rest is lost.) | P52: {=IFERROR(_xlfn.TEXTSPLIT(G52,", ",,TRUE),"")} -> Ammunition (Range 30/120; Bullet) | U52: {=IFERROR(INDEX(_xlfn.TEXTSPLIT(P52," "),,1),"")} -> Ammunition | V52: =IF(NOT(U52=""),_xlfn.XLOOKUP(U52,'weapon masteries'!$A$20:$A$29,'weapon masteries'!$B$20:$B$29,"",0),"") -> You can use a weapon that has the Ammunition property to make a ranged attack only if you have ammunition to fire from it. The type of ammunition required is specified with the weapon's range. Each attack expends one piece of ammunition. Drawing the ammunition is part of the attack (you need a free hand to load a one-handed weapon). After a fight, you can spend 1 minute to recover half the ammunition (round down) you used in the fight; the rest is lost. | W52: {=IFERROR(INDEX(_xlfn.TEXTSPLIT(Q52," "),,1),"")} | X52: =IF(NOT(W52=""),_xlfn.XLOOKUP(W52,'weapon masteries'!$A$20:$A$29,'weapon masteries'!$B$20:$B$29,"",0),"") | Y52: {=IFERROR(INDEX(_xlfn.TEXTSPLIT(R52," "),,1),"")} | Z52: =IF(NOT(Y52=""),_xlfn.XLOOKUP(Y52,'weapon masteries'!$A$20:$A$29,'weapon masteries'!$B$20:$B$29,"",0),"") | AA52: {=IFERROR(INDEX(_xlfn.TEXTSPLIT(S52," "),,1),"")} | AB52: =IF(NOT(AA52=""),_xlfn.XLOOKUP(AA52,'weapon masteries'!$A$20:$A$29,'weapon masteries'!$B$20:$B$29,"",0),"") | AC52: {=IFERROR(INDEX(_xlfn.TEXTSPLIT(T52," "),,1),"")} | AD52: =IF(NOT(AC52=""),_xlfn.XLOOKUP(AC52,'weapon masteries'!$A$20:$A$29,'weapon masteries'!$B$20:$B$29,"",0),"")
A53: Melee Weapon Attack | B53: Battleaxe (2024 edition) | C53: Strength | D53: reach 5 ft | E53: 1d8 | F53: slashing | G53: Versatile (1d10) | H53: Topple | J53: =A53&": [ATK_MOD] to hit, "&D53&", one target. Hit: [DAMAGE] "&F53&" damage. "&I53 -> Melee Weapon Attack: [ATK_MOD] to hit, reach 5 ft, one target. Hit: [DAMAGE] slashing damage. | K53: ="Mastery: "&H53&". "&_xlfn.XLOOKUP(H53,'weapon masteries'!A$2:A$9,'weapon masteries'!B$2:B$9,"",0) -> Mastery: Topple. If the [MON] hits a creature with this weapon, it can force the creature to make a Constitution saving throw (DC 8 plus the ability modifier used to make the attack roll and your Proficiency Bonus). On a failed save, the creature has the Prone condition. | L53: =IF(NOT(G53=""),IF(COUNTA(P53:T53)>1,"Properties: ","Property: ")&U53&" ("&V53&")"&IF(NOT(W53=""),", "&W53&" ("&X53&")"&IF(NOT(Y53=""),", "&Y53&" ("&Z53&")"&IF(NOT(AA53=""),", "&AB53&" ("&AC53&")",""),""),""),"") -> Property: Versatile (A Versatile weapon can be used with one or two hands. A damage value in parentheses appears with the property. The weapon deals that damage when used with two hands to make a melee attack.) | P53: {=IFERROR(_xlfn.TEXTSPLIT(G53,", ",,TRUE),"")} -> Versatile (1d10) | U53: {=IFERROR(INDEX(_xlfn.TEXTSPLIT(P53," "),,1),"")} -> Versatile | V53: =IF(NOT(U53=""),_xlfn.XLOOKUP(U53,'weapon masteries'!$A$20:$A$29,'weapon masteries'!$B$20:$B$29,"",0),"") -> A Versatile weapon can be used with one or two hands. A damage value in parentheses appears with the property. The weapon deals that damage when used with two hands to make a melee attack. | W53: {=IFERROR(INDEX(_xlfn.TEXTSPLIT(Q53," "),,1),"")} | X53: =IF(NOT(W53=""),_xlfn.XLOOKUP(W53,'weapon masteries'!$A$20:$A$29,'weapon masteries'!$B$20:$B$29,"",0),"") | Y53: {=IFERROR(INDEX(_xlfn.TEXTSPLIT(R53," "),,1),"")} | Z53: =IF(NOT(Y53=""),_xlfn.XLOOKUP(Y53,'weapon masteries'!$A$20:$A$29,'weapon masteries'!$B$20:$B$29,"",0),"") | AA53: {=IFERROR(INDEX(_xlfn.TEXTSPLIT(S53," "),,1),"")} | AB53: =IF(NOT(AA53=""),_xlfn.XLOOKUP(AA53,'weapon masteries'!$A$20:$A$29,'weapon masteries'!$B$20:$B$29,"",0),"") | AC53: {=IFERROR(INDEX(_xlfn.TEXTSPLIT(T53," "),,1),"")} | AD53: =IF(NOT(AC53=""),_xlfn.XLOOKUP(AC53,'weapon masteries'!$A$20:$A$29,'weapon masteries'!$B$20:$B$29,"",0),"")
A54: Melee Weapon Attack | B54: Flail (2024 edition) | C54: Strength | D54: reach 5 ft | E54: 1d8 | F54: bludgeoning | H54: Sap | J54: =A54&": [ATK_MOD] to hit, "&D54&", one target. Hit: [DAMAGE] "&F54&" damage. "&I54 -> Melee Weapon Attack: [ATK_MOD] to hit, reach 5 ft, one target. Hit: [DAMAGE] bludgeoning damage. | K54: ="Mastery: "&H54&". "&_xlfn.XLOOKUP(H54,'weapon masteries'!A$2:A$9,'weapon masteries'!B$2:B$9,"",0) -> Mastery: Sap. If the [MON] hits a creature with this weapon, that creature has disadvantage on its next attack roll before the start of the [MON]'s next turn. | L54: =IF(NOT(G54=""),IF(COUNTA(P54:T54)>1,"Properties: ","Property: ")&U54&" ("&V54&")"&IF(NOT(W54=""),", "&W54&" ("&X54&")"&IF(NOT(Y54=""),", "&Y54&" ("&Z54&")"&IF(NOT(AA54=""),", "&AB54&" ("&AC54&")",""),""),""),"") | P54: {=IFERROR(_xlfn.TEXTSPLIT(G54,", ",,TRUE),"")} | U54: {=IFERROR(INDEX(_xlfn.TEXTSPLIT(P54," "),,1),"")} | V54: =IF(NOT(U54=""),_xlfn.XLOOKUP(U54,'weapon masteries'!$A$20:$A$29,'weapon masteries'!$B$20:$B$29,"",0),"") | W54: {=IFERROR(INDEX(_xlfn.TEXTSPLIT(Q54," "),,1),"")} | X54: =IF(NOT(W54=""),_xlfn.XLOOKUP(W54,'weapon masteries'!$A$20:$A$29,'weapon masteries'!$B$20:$B$29,"",0),"") | Y54: {=IFERROR(INDEX(_xlfn.TEXTSPLIT(R54," "),,1),"")} | Z54: =IF(NOT(Y54=""),_xlfn.XLOOKUP(Y54,'weapon masteries'!$A$20:$A$29,'weapon masteries'!$B$20:$B$29,"",0),"") | AA54: {=IFERROR(INDEX(_xlfn.TEXTSPLIT(S54," "),,1),"")} | AB54: =IF(NOT(AA54=""),_xlfn.XLOOKUP(AA54,'weapon masteries'!$A$20:$A$29,'weapon masteries'!$B$20:$B$29,"",0),"") | AC54: {=IFERROR(INDEX(_xlfn.TEXTSPLIT(T54," "),,1),"")} | AD54: =IF(NOT(AC54=""),_xlfn.XLOOKUP(AC54,'weapon masteries'!$A$20:$A$29,'weapon masteries'!$B$20:$B$29,"",0),"")
A55: Melee Weapon Attack | B55: Glaive (2024 edition) | C55: Strength | D55: reach 10 ft | E55: 1d10 | F55: slashing | G55: Heavy, Reach, Two-Handed | H55: Graze | J55: =A55&": [ATK_MOD] to hit, "&D55&", one target. Hit: [DAMAGE] "&F55&" damage. "&I55 -> Melee Weapon Attack: [ATK_MOD] to hit, reach 10 ft, one target. Hit: [DAMAGE] slashing damage. | K55: ="Mastery: "&H55&". "&_xlfn.XLOOKUP(H55,'weapon masteries'!A$2:A$9,'weapon masteries'!B$2:B$9,"",0) -> Mastery: Graze. If the [MON]'s attack roll with this weapon misses a creature, it can deal damage to that creature equal to the ability modifier it used to make the attack roll. This damage is the same type dealt by the weapon, and the damage can be increased only by increasing the ability modifier. | L55: =IF(NOT(G55=""),IF(COUNTA(P55:T55)>1,"Properties: ","Property: ")&U55&" ("&V55&")"&IF(NOT(W55=""),", "&W55&" ("&X55&")"&IF(NOT(Y55=""),", "&Y55&" ("&Z55&")"&IF(NOT(AA55=""),", "&AB55&" ("&AC55&")",""),""),""),"") -> Properties: Heavy (You have Disadvantage on attack rolls with a Heavy weapon if it's a Melee weapon and your Strength score isn't at least 13 or if it's a Ranged weapon and your Dexterity score isn't at least 13.), Reach (A Reach weapon adds 5 feet to your reach when you attack with it, as well as when determining your reach for Opportunity Attacks with it.), Two-Handed (A Two-Handed weapon requires two hands when you attack with it.) | P55: {=IFERROR(_xlfn.TEXTSPLIT(G55,", ",,TRUE),"")} -> Heavy | Q55: Reach | R55: Two-Handed | U55: {=IFERROR(INDEX(_xlfn.TEXTSPLIT(P55," "),,1),"")} -> Heavy | V55: =IF(NOT(U55=""),_xlfn.XLOOKUP(U55,'weapon masteries'!$A$20:$A$29,'weapon masteries'!$B$20:$B$29,"",0),"") -> You have Disadvantage on attack rolls with a Heavy weapon if it's a Melee weapon and your Strength score isn't at least 13 or if it's a Ranged weapon and your Dexterity score isn't at least 13. | W55: {=IFERROR(INDEX(_xlfn.TEXTSPLIT(Q55," "),,1),"")} -> Reach | X55: =IF(NOT(W55=""),_xlfn.XLOOKUP(W55,'weapon masteries'!$A$20:$A$29,'weapon masteries'!$B$20:$B$29,"",0),"") -> A Reach weapon adds 5 feet to your reach when you attack with it, as well as when determining your reach for Opportunity Attacks with it. | Y55: {=IFERROR(INDEX(_xlfn.TEXTSPLIT(R55," "),,1),"")} -> Two-Handed | Z55: =IF(NOT(Y55=""),_xlfn.XLOOKUP(Y55,'weapon masteries'!$A$20:$A$29,'weapon masteries'!$B$20:$B$29,"",0),"") -> A Two-Handed weapon requires two hands when you attack with it. | AA55: {=IFERROR(INDEX(_xlfn.TEXTSPLIT(S55," "),,1),"")} | AB55: =IF(NOT(AA55=""),_xlfn.XLOOKUP(AA55,'weapon masteries'!$A$20:$A$29,'weapon masteries'!$B$20:$B$29,"",0),"") | AC55: {=IFERROR(INDEX(_xlfn.TEXTSPLIT(T55," "),,1),"")} | AD55: =IF(NOT(AC55=""),_xlfn.XLOOKUP(AC55,'weapon masteries'!$A$20:$A$29,'weapon masteries'!$B$20:$B$29,"",0),"")
A56: Melee Weapon Attack | B56: Greataxe (2024 edition) | C56: Strength | D56: reach 5 ft | E56: 1d12 | F56: slashing | G56: Heavy, Two-Handed | H56: Cleave | J56: =A56&": [ATK_MOD] to hit, "&D56&", one target. Hit: [DAMAGE] "&F56&" damage. "&I56 -> Melee Weapon Attack: [ATK_MOD] to hit, reach 5 ft, one target. Hit: [DAMAGE] slashing damage. | K56: ="Mastery: "&H56&". "&_xlfn.XLOOKUP(H56,'weapon masteries'!A$2:A$9,'weapon masteries'!B$2:B$9,"",0) -> Mastery: Cleave. If the [MON] hits a creature with a melee attack roll using this weapon, it can make a melee attack roll with the weapon against a second creature within 5 feet of the first that is also within its reach. On a hit, the second creature takes the weapon’s damage, but don't add the [MON]'s ability modifier to that damage unless that modifier is negative. The [MON] can make this extra attack only once per turn. | L56: =IF(NOT(G56=""),IF(COUNTA(P56:T56)>1,"Properties: ","Property: ")&U56&" ("&V56&")"&IF(NOT(W56=""),", "&W56&" ("&X56&")"&IF(NOT(Y56=""),", "&Y56&" ("&Z56&")"&IF(NOT(AA56=""),", "&AB56&" ("&AC56&")",""),""),""),"") -> Properties: Heavy (You have Disadvantage on attack rolls with a Heavy weapon if it's a Melee weapon and your Strength score isn't at least 13 or if it's a Ranged weapon and your Dexterity score isn't at least 13.), Two-Handed (A Two-Handed weapon requires two hands when you attack with it.) | P56: {=IFERROR(_xlfn.TEXTSPLIT(G56,", ",,TRUE),"")} -> Heavy | Q56: Two-Handed | U56: {=IFERROR(INDEX(_xlfn.TEXTSPLIT(P56," "),,1),"")} -> Heavy | V56: =IF(NOT(U56=""),_xlfn.XLOOKUP(U56,'weapon masteries'!$A$20:$A$29,'weapon masteries'!$B$20:$B$29,"",0),"") -> You have Disadvantage on attack rolls with a Heavy weapon if it's a Melee weapon and your Strength score isn't at least 13 or if it's a Ranged weapon and your Dexterity score isn't at least 13. | W56: {=IFERROR(INDEX(_xlfn.TEXTSPLIT(Q56," "),,1),"")} -> Two-Handed | X56: =IF(NOT(W56=""),_xlfn.XLOOKUP(W56,'weapon masteries'!$A$20:$A$29,'weapon masteries'!$B$20:$B$29,"",0),"") -> A Two-Handed weapon requires two hands when you attack with it. | Y56: {=IFERROR(INDEX(_xlfn.TEXTSPLIT(R56," "),,1),"")} | Z56: =IF(NOT(Y56=""),_xlfn.XLOOKUP(Y56,'weapon masteries'!$A$20:$A$29,'weapon masteries'!$B$20:$B$29,"",0),"") | AA56: {=IFERROR(INDEX(_xlfn.TEXTSPLIT(S56," "),,1),"")} | AB56: =IF(NOT(AA56=""),_xlfn.XLOOKUP(AA56,'weapon masteries'!$A$20:$A$29,'weapon masteries'!$B$20:$B$29,"",0),"") | AC56: {=IFERROR(INDEX(_xlfn.TEXTSPLIT(T56," "),,1),"")} | AD56: =IF(NOT(AC56=""),_xlfn.XLOOKUP(AC56,'weapon masteries'!$A$20:$A$29,'weapon masteries'!$B$20:$B$29,"",0),"")
A57: Melee Weapon Attack | B57: Greatsword (2024 edition) | C57: Strength | D57: reach 5 ft | E57: 2d6 | F57: slashing | G57: Heavy, Two-Handed | H57: Graze | J57: =A57&": [ATK_MOD] to hit, "&D57&", one target. Hit: [DAMAGE] "&F57&" damage. "&I57 -> Melee Weapon Attack: [ATK_MOD] to hit, reach 5 ft, one target. Hit: [DAMAGE] slashing damage. | K57: ="Mastery: "&H57&". "&_xlfn.XLOOKUP(H57,'weapon masteries'!A$2:A$9,'weapon masteries'!B$2:B$9,"",0) -> Mastery: Graze. If the [MON]'s attack roll with this weapon misses a creature, it can deal damage to that creature equal to the ability modifier it used to make the attack roll. This damage is the same type dealt by the weapon, and the damage can be increased only by increasing the ability modifier. | L57: =IF(NOT(G57=""),IF(COUNTA(P57:T57)>1,"Properties: ","Property: ")&U57&" ("&V57&")"&IF(NOT(W57=""),", "&W57&" ("&X57&")"&IF(NOT(Y57=""),", "&Y57&" ("&Z57&")"&IF(NOT(AA57=""),", "&AB57&" ("&AC57&")",""),""),""),"") -> Properties: Heavy (You have Disadvantage on attack rolls with a Heavy weapon if it's a Melee weapon and your Strength score isn't at least 13 or if it's a Ranged weapon and your Dexterity score isn't at least 13.), Two-Handed (A Two-Handed weapon requires two hands when you attack with it.) | P57: {=IFERROR(_xlfn.TEXTSPLIT(G57,", ",,TRUE),"")} -> Heavy | Q57: Two-Handed | U57: {=IFERROR(INDEX(_xlfn.TEXTSPLIT(P57," "),,1),"")} -> Heavy | V57: =IF(NOT(U57=""),_xlfn.XLOOKUP(U57,'weapon masteries'!$A$20:$A$29,'weapon masteries'!$B$20:$B$29,"",0),"") -> You have Disadvantage on attack rolls with a Heavy weapon if it's a Melee weapon and your Strength score isn't at least 13 or if it's a Ranged weapon and your Dexterity score isn't at least 13. | W57: {=IFERROR(INDEX(_xlfn.TEXTSPLIT(Q57," "),,1),"")} -> Two-Handed | X57: =IF(NOT(W57=""),_xlfn.XLOOKUP(W57,'weapon masteries'!$A$20:$A$29,'weapon masteries'!$B$20:$B$29,"",0),"") -> A Two-Handed weapon requires two hands when you attack with it. | Y57: {=IFERROR(INDEX(_xlfn.TEXTSPLIT(R57," "),,1),"")} | Z57: =IF(NOT(Y57=""),_xlfn.XLOOKUP(Y57,'weapon masteries'!$A$20:$A$29,'weapon masteries'!$B$20:$B$29,"",0),"") | AA57: {=IFERROR(INDEX(_xlfn.TEXTSPLIT(S57," "),,1),"")} | AB57: =IF(NOT(AA57=""),_xlfn.XLOOKUP(AA57,'weapon masteries'!$A$20:$A$29,'weapon masteries'!$B$20:$B$29,"",0),"") | AC57: {=IFERROR(INDEX(_xlfn.TEXTSPLIT(T57," "),,1),"")} | AD57: =IF(NOT(AC57=""),_xlfn.XLOOKUP(AC57,'weapon masteries'!$A$20:$A$29,'weapon masteries'!$B$20:$B$29,"",0),"")
A58: Melee Weapon Attack | B58: Halberd (2024 edition) | C58: Strength | D58: reach 10 ft | E58: 1d10 | F58: slashing | G58: Heavy, Reach, Two-Handed | H58: Cleave | J58: =A58&": [ATK_MOD] to hit, "&D58&", one target. Hit: [DAMAGE] "&F58&" damage. "&I58 -> Melee Weapon Attack: [ATK_MOD] to hit, reach 10 ft, one target. Hit: [DAMAGE] slashing damage. | K58: ="Mastery: "&H58&". "&_xlfn.XLOOKUP(H58,'weapon masteries'!A$2:A$9,'weapon masteries'!B$2:B$9,"",0) -> Mastery: Cleave. If the [MON] hits a creature with a melee attack roll using this weapon, it can make a melee attack roll with the weapon against a second creature within 5 feet of the first that is also within its reach. On a hit, the second creature takes the weapon’s damage, but don't add the [MON]'s ability modifier to that damage unless that modifier is negative. The [MON] can make this extra attack only once per turn. | L58: =IF(NOT(G58=""),IF(COUNTA(P58:T58)>1,"Properties: ","Property: ")&U58&" ("&V58&")"&IF(NOT(W58=""),", "&W58&" ("&X58&")"&IF(NOT(Y58=""),", "&Y58&" ("&Z58&")"&IF(NOT(AA58=""),", "&AB58&" ("&AC58&")",""),""),""),"") -> Properties: Heavy (You have Disadvantage on attack rolls with a Heavy weapon if it's a Melee weapon and your Strength score isn't at least 13 or if it's a Ranged weapon and your Dexterity score isn't at least 13.), Reach (A Reach weapon adds 5 feet to your reach when you attack with it, as well as when determining your reach for Opportunity Attacks with it.), Two-Handed (A Two-Handed weapon requires two hands when you attack with it.) | P58: {=IFERROR(_xlfn.TEXTSPLIT(G58,", ",,TRUE),"")} -> Heavy | Q58: Reach | R58: Two-Handed | U58: {=IFERROR(INDEX(_xlfn.TEXTSPLIT(P58," "),,1),"")} -> Heavy | V58: =IF(NOT(U58=""),_xlfn.XLOOKUP(U58,'weapon masteries'!$A$20:$A$29,'weapon masteries'!$B$20:$B$29,"",0),"") -> You have Disadvantage on attack rolls with a Heavy weapon if it's a Melee weapon and your Strength score isn't at least 13 or if it's a Ranged weapon and your Dexterity score isn't at least 13. | W58: {=IFERROR(INDEX(_xlfn.TEXTSPLIT(Q58," "),,1),"")} -> Reach | X58: =IF(NOT(W58=""),_xlfn.XLOOKUP(W58,'weapon masteries'!$A$20:$A$29,'weapon masteries'!$B$20:$B$29,"",0),"") -> A Reach weapon adds 5 feet to your reach when you attack with it, as well as when determining your reach for Opportunity Attacks with it. | Y58: {=IFERROR(INDEX(_xlfn.TEXTSPLIT(R58," "),,1),"")} -> Two-Handed | Z58: =IF(NOT(Y58=""),_xlfn.XLOOKUP(Y58,'weapon masteries'!$A$20:$A$29,'weapon masteries'!$B$20:$B$29,"",0),"") -> A Two-Handed weapon requires two hands when you attack with it. | AA58: {=IFERROR(INDEX(_xlfn.TEXTSPLIT(S58," "),,1),"")} | AB58: =IF(NOT(AA58=""),_xlfn.XLOOKUP(AA58,'weapon masteries'!$A$20:$A$29,'weapon masteries'!$B$20:$B$29,"",0),"") | AC58: {=IFERROR(INDEX(_xlfn.TEXTSPLIT(T58," "),,1),"")} | AD58: =IF(NOT(AC58=""),_xlfn.XLOOKUP(AC58,'weapon masteries'!$A$20:$A$29,'weapon masteries'!$B$20:$B$29,"",0),"")
A59: Melee Weapon Attack | B59: Lance (2024 edition) | C59: Strength | D59: reach 10 ft | E59: 1d12 | F59: piercing | G59: Heavy, Reach, Two-Handed (unless mounted) | H59: Topple | J59: =A59&": [ATK_MOD] to hit, "&D59&", one target. Hit: [DAMAGE] "&F59&" damage. "&I59 -> Melee Weapon Attack: [ATK_MOD] to hit, reach 10 ft, one target. Hit: [DAMAGE] piercing damage. | K59: ="Mastery: "&H59&". "&_xlfn.XLOOKUP(H59,'weapon masteries'!A$2:A$9,'weapon masteries'!B$2:B$9,"",0) -> Mastery: Topple. If the [MON] hits a creature with this weapon, it can force the creature to make a Constitution saving throw (DC 8 plus the ability modifier used to make the attack roll and your Proficiency Bonus). On a failed save, the creature has the Prone condition. | L59: =IF(NOT(G59=""),IF(COUNTA(P59:T59)>1,"Properties: ","Property: ")&U59&" ("&V59&")"&IF(NOT(W59=""),", "&W59&" ("&X59&")"&IF(NOT(Y59=""),", "&Y59&" ("&Z59&")"&IF(NOT(AA59=""),", "&AB59&" ("&AC59&")",""),""),""),"") -> Properties: Heavy (You have Disadvantage on attack rolls with a Heavy weapon if it's a Melee weapon and your Strength score isn't at least 13 or if it's a Ranged weapon and your Dexterity score isn't at least 13.), Reach (A Reach weapon adds 5 feet to your reach when you attack with it, as well as when determining your reach for Opportunity Attacks with it.), Two-Handed (A Two-Handed weapon requires two hands when you attack with it.) | P59: {=IFERROR(_xlfn.TEXTSPLIT(G59,", ",,TRUE),"")} -> Heavy | Q59: Reach | R59: Two-Handed (unless mounted) | U59: {=IFERROR(INDEX(_xlfn.TEXTSPLIT(P59," "),,1),"")} -> Heavy | V59: =IF(NOT(U59=""),_xlfn.XLOOKUP(U59,'weapon masteries'!$A$20:$A$29,'weapon masteries'!$B$20:$B$29,"",0),"") -> You have Disadvantage on attack rolls with a Heavy weapon if it's a Melee weapon and your Strength score isn't at least 13 or if it's a Ranged weapon and your Dexterity score isn't at least 13. | W59: {=IFERROR(INDEX(_xlfn.TEXTSPLIT(Q59," "),,1),"")} -> Reach | X59: =IF(NOT(W59=""),_xlfn.XLOOKUP(W59,'weapon masteries'!$A$20:$A$29,'weapon masteries'!$B$20:$B$29,"",0),"") -> A Reach weapon adds 5 feet to your reach when you attack with it, as well as when determining your reach for Opportunity Attacks with it. | Y59: {=IFERROR(INDEX(_xlfn.TEXTSPLIT(R59," "),,1),"")} -> Two-Handed | Z59: =IF(NOT(Y59=""),_xlfn.XLOOKUP(Y59,'weapon masteries'!$A$20:$A$29,'weapon masteries'!$B$20:$B$29,"",0),"") -> A Two-Handed weapon requires two hands when you attack with it. | AA59: {=IFERROR(INDEX(_xlfn.TEXTSPLIT(S59," "),,1),"")} | AB59: =IF(NOT(AA59=""),_xlfn.XLOOKUP(AA59,'weapon masteries'!$A$20:$A$29,'weapon masteries'!$B$20:$B$29,"",0),"") | AC59: {=IFERROR(INDEX(_xlfn.TEXTSPLIT(T59," "),,1),"")} | AD59: =IF(NOT(AC59=""),_xlfn.XLOOKUP(AC59,'weapon masteries'!$A$20:$A$29,'weapon masteries'!$B$20:$B$29,"",0),"")
A60: Melee Weapon Attack | B60: Longsword (2024 edition) | C60: Strength | D60: reach 5 ft | E60: 1d8 | F60: slashing | G60: Versatile (1d10) | H60: Sap | J60: =A60&": [ATK_MOD] to hit, "&D60&", one target. Hit: [DAMAGE] "&F60&" damage. "&I60 -> Melee Weapon Attack: [ATK_MOD] to hit, reach 5 ft, one target. Hit: [DAMAGE] slashing damage. | K60: ="Mastery: "&H60&". "&_xlfn.XLOOKUP(H60,'weapon masteries'!A$2:A$9,'weapon masteries'!B$2:B$9,"",0) -> Mastery: Sap. If the [MON] hits a creature with this weapon, that creature has disadvantage on its next attack roll before the start of the [MON]'s next turn. | L60: =IF(NOT(G60=""),IF(COUNTA(P60:T60)>1,"Properties: ","Property: ")&U60&" ("&V60&")"&IF(NOT(W60=""),", "&W60&" ("&X60&")"&IF(NOT(Y60=""),", "&Y60&" ("&Z60&")"&IF(NOT(AA60=""),", "&AB60&" ("&AC60&")",""),""),""),"") -> Property: Versatile (A Versatile weapon can be used with one or two hands. A damage value in parentheses appears with the property. The weapon deals that damage when used with two hands to make a melee attack.) | P60: {=IFERROR(_xlfn.TEXTSPLIT(G60,", ",,TRUE),"")} -> Versatile (1d10) | U60: {=IFERROR(INDEX(_xlfn.TEXTSPLIT(P60," "),,1),"")} -> Versatile | V60: =IF(NOT(U60=""),_xlfn.XLOOKUP(U60,'weapon masteries'!$A$20:$A$29,'weapon masteries'!$B$20:$B$29,"",0),"") -> A Versatile weapon can be used with one or two hands. A damage value in parentheses appears with the property. The weapon deals that damage when used with two hands to make a melee attack. | W60: {=IFERROR(INDEX(_xlfn.TEXTSPLIT(Q60," "),,1),"")} | X60: =IF(NOT(W60=""),_xlfn.XLOOKUP(W60,'weapon masteries'!$A$20:$A$29,'weapon masteries'!$B$20:$B$29,"",0),"") | Y60: {=IFERROR(INDEX(_xlfn.TEXTSPLIT(R60," "),,1),"")} | Z60: =IF(NOT(Y60=""),_xlfn.XLOOKUP(Y60,'weapon masteries'!$A$20:$A$29,'weapon masteries'!$B$20:$B$29,"",0),"") | AA60: {=IFERROR(INDEX(_xlfn.TEXTSPLIT(S60," "),,1),"")} | AB60: =IF(NOT(AA60=""),_xlfn.XLOOKUP(AA60,'weapon masteries'!$A$20:$A$29,'weapon masteries'!$B$20:$B$29,"",0),"") | AC60: {=IFERROR(INDEX(_xlfn.TEXTSPLIT(T60," "),,1),"")} | AD60: =IF(NOT(AC60=""),_xlfn.XLOOKUP(AC60,'weapon masteries'!$A$20:$A$29,'weapon masteries'!$B$20:$B$29,"",0),"")
A61: Melee Weapon Attack | B61: Maul (2024 edition) | C61: Strength | D61: reach 5 ft | E61: 2d6 | F61: bludgeoning | G61: Heavy, Two-Handed | H61: Topple | J61: =A61&": [ATK_MOD] to hit, "&D61&", one target. Hit: [DAMAGE] "&F61&" damage. "&I61 -> Melee Weapon Attack: [ATK_MOD] to hit, reach 5 ft, one target. Hit: [DAMAGE] bludgeoning damage. | K61: ="Mastery: "&H61&". "&_xlfn.XLOOKUP(H61,'weapon masteries'!A$2:A$9,'weapon masteries'!B$2:B$9,"",0) -> Mastery: Topple. If the [MON] hits a creature with this weapon, it can force the creature to make a Constitution saving throw (DC 8 plus the ability modifier used to make the attack roll and your Proficiency Bonus). On a failed save, the creature has the Prone condition. | L61: =IF(NOT(G61=""),IF(COUNTA(P61:T61)>1,"Properties: ","Property: ")&U61&" ("&V61&")"&IF(NOT(W61=""),", "&W61&" ("&X61&")"&IF(NOT(Y61=""),", "&Y61&" ("&Z61&")"&IF(NOT(AA61=""),", "&AB61&" ("&AC61&")",""),""),""),"") -> Properties: Heavy (You have Disadvantage on attack rolls with a Heavy weapon if it's a Melee weapon and your Strength score isn't at least 13 or if it's a Ranged weapon and your Dexterity score isn't at least 13.), Two-Handed (A Two-Handed weapon requires two hands when you attack with it.) | P61: {=IFERROR(_xlfn.TEXTSPLIT(G61,", ",,TRUE),"")} -> Heavy | Q61: Two-Handed | U61: {=IFERROR(INDEX(_xlfn.TEXTSPLIT(P61," "),,1),"")} -> Heavy | V61: =IF(NOT(U61=""),_xlfn.XLOOKUP(U61,'weapon masteries'!$A$20:$A$29,'weapon masteries'!$B$20:$B$29,"",0),"") -> You have Disadvantage on attack rolls with a Heavy weapon if it's a Melee weapon and your Strength score isn't at least 13 or if it's a Ranged weapon and your Dexterity score isn't at least 13. | W61: {=IFERROR(INDEX(_xlfn.TEXTSPLIT(Q61," "),,1),"")} -> Two-Handed | X61: =IF(NOT(W61=""),_xlfn.XLOOKUP(W61,'weapon masteries'!$A$20:$A$29,'weapon masteries'!$B$20:$B$29,"",0),"") -> A Two-Handed weapon requires two hands when you attack with it. | Y61: {=IFERROR(INDEX(_xlfn.TEXTSPLIT(R61," "),,1),"")} | Z61: =IF(NOT(Y61=""),_xlfn.XLOOKUP(Y61,'weapon masteries'!$A$20:$A$29,'weapon masteries'!$B$20:$B$29,"",0),"") | AA61: {=IFERROR(INDEX(_xlfn.TEXTSPLIT(S61," "),,1),"")} | AB61: =IF(NOT(AA61=""),_xlfn.XLOOKUP(AA61,'weapon masteries'!$A$20:$A$29,'weapon masteries'!$B$20:$B$29,"",0),"") | AC61: {=IFERROR(INDEX(_xlfn.TEXTSPLIT(T61," "),,1),"")} | AD61: =IF(NOT(AC61=""),_xlfn.XLOOKUP(AC61,'weapon masteries'!$A$20:$A$29,'weapon masteries'!$B$20:$B$29,"",0),"")
A62: Melee Weapon Attack | B62: Morningstar (2024 edition) | C62: Strength | D62: reach 5 ft | E62: 1d8 | F62: piercing | H62: Sap | J62: =A62&": [ATK_MOD] to hit, "&D62&", one target. Hit: [DAMAGE] "&F62&" damage. "&I62 -> Melee Weapon Attack: [ATK_MOD] to hit, reach 5 ft, one target. Hit: [DAMAGE] piercing damage. | K62: ="Mastery: "&H62&". "&_xlfn.XLOOKUP(H62,'weapon masteries'!A$2:A$9,'weapon masteries'!B$2:B$9,"",0) -> Mastery: Sap. If the [MON] hits a creature with this weapon, that creature has disadvantage on its next attack roll before the start of the [MON]'s next turn. | L62: =IF(NOT(G62=""),IF(COUNTA(P62:T62)>1,"Properties: ","Property: ")&U62&" ("&V62&")"&IF(NOT(W62=""),", "&W62&" ("&X62&")"&IF(NOT(Y62=""),", "&Y62&" ("&Z62&")"&IF(NOT(AA62=""),", "&AB62&" ("&AC62&")",""),""),""),"") | P62: {=IFERROR(_xlfn.TEXTSPLIT(G62,", ",,TRUE),"")} | U62: {=IFERROR(INDEX(_xlfn.TEXTSPLIT(P62," "),,1),"")} | V62: =IF(NOT(U62=""),_xlfn.XLOOKUP(U62,'weapon masteries'!$A$20:$A$29,'weapon masteries'!$B$20:$B$29,"",0),"") | W62: {=IFERROR(INDEX(_xlfn.TEXTSPLIT(Q62," "),,1),"")} | X62: =IF(NOT(W62=""),_xlfn.XLOOKUP(W62,'weapon masteries'!$A$20:$A$29,'weapon masteries'!$B$20:$B$29,"",0),"") | Y62: {=IFERROR(INDEX(_xlfn.TEXTSPLIT(R62," "),,1),"")} | Z62: =IF(NOT(Y62=""),_xlfn.XLOOKUP(Y62,'weapon masteries'!$A$20:$A$29,'weapon masteries'!$B$20:$B$29,"",0),"") | AA62: {=IFERROR(INDEX(_xlfn.TEXTSPLIT(S62," "),,1),"")} | AB62: =IF(NOT(AA62=""),_xlfn.XLOOKUP(AA62,'weapon masteries'!$A$20:$A$29,'weapon masteries'!$B$20:$B$29,"",0),"") | AC62: {=IFERROR(INDEX(_xlfn.TEXTSPLIT(T62," "),,1),"")} | AD62: =IF(NOT(AC62=""),_xlfn.XLOOKUP(AC62,'weapon masteries'!$A$20:$A$29,'weapon masteries'!$B$20:$B$29,"",0),"")
A63: Melee Weapon Attack | B63: Pike (2024 edition) | C63: Strength | D63: reach 10 ft | E63: 1d10 | F63: piercing | G63: Heavy, Reach, Two-Handed | H63: Push | J63: =A63&": [ATK_MOD] to hit, "&D63&", one target. Hit: [DAMAGE] "&F63&" damage. "&I63 -> Melee Weapon Attack: [ATK_MOD] to hit, reach 10 ft, one target. Hit: [DAMAGE] piercing damage. | K63: ="Mastery: "&H63&". "&_xlfn.XLOOKUP(H63,'weapon masteries'!A$2:A$9,'weapon masteries'!B$2:B$9,"",0) -> Mastery: Push. If the [MON] hits a creature with this weapon, it can push the creature up to 10 feet straight away from itself if it is Large or smaller. | L63: =IF(NOT(G63=""),IF(COUNTA(P63:T63)>1,"Properties: ","Property: ")&U63&" ("&V63&")"&IF(NOT(W63=""),", "&W63&" ("&X63&")"&IF(NOT(Y63=""),", "&Y63&" ("&Z63&")"&IF(NOT(AA63=""),", "&AB63&" ("&AC63&")",""),""),""),"") -> Properties: Heavy (You have Disadvantage on attack rolls with a Heavy weapon if it's a Melee weapon and your Strength score isn't at least 13 or if it's a Ranged weapon and your Dexterity score isn't at least 13.), Reach (A Reach weapon adds 5 feet to your reach when you attack with it, as well as when determining your reach for Opportunity Attacks with it.), Two-Handed (A Two-Handed weapon requires two hands when you attack with it.) | P63: {=IFERROR(_xlfn.TEXTSPLIT(G63,", ",,TRUE),"")} -> Heavy | Q63: Reach | R63: Two-Handed | U63: {=IFERROR(INDEX(_xlfn.TEXTSPLIT(P63," "),,1),"")} -> Heavy | V63: =IF(NOT(U63=""),_xlfn.XLOOKUP(U63,'weapon masteries'!$A$20:$A$29,'weapon masteries'!$B$20:$B$29,"",0),"") -> You have Disadvantage on attack rolls with a Heavy weapon if it's a Melee weapon and your Strength score isn't at least 13 or if it's a Ranged weapon and your Dexterity score isn't at least 13. | W63: {=IFERROR(INDEX(_xlfn.TEXTSPLIT(Q63," "),,1),"")} -> Reach | X63: =IF(NOT(W63=""),_xlfn.XLOOKUP(W63,'weapon masteries'!$A$20:$A$29,'weapon masteries'!$B$20:$B$29,"",0),"") -> A Reach weapon adds 5 feet to your reach when you attack with it, as well as when determining your reach for Opportunity Attacks with it. | Y63: {=IFERROR(INDEX(_xlfn.TEXTSPLIT(R63," "),,1),"")} -> Two-Handed | Z63: =IF(NOT(Y63=""),_xlfn.XLOOKUP(Y63,'weapon masteries'!$A$20:$A$29,'weapon masteries'!$B$20:$B$29,"",0),"") -> A Two-Handed weapon requires two hands when you attack with it. | AA63: {=IFERROR(INDEX(_xlfn.TEXTSPLIT(S63," "),,1),"")} | AB63: =IF(NOT(AA63=""),_xlfn.XLOOKUP(AA63,'weapon masteries'!$A$20:$A$29,'weapon masteries'!$B$20:$B$29,"",0),"") | AC63: {=IFERROR(INDEX(_xlfn.TEXTSPLIT(T63," "),,1),"")} | AD63: =IF(NOT(AC63=""),_xlfn.XLOOKUP(AC63,'weapon masteries'!$A$20:$A$29,'weapon masteries'!$B$20:$B$29,"",0),"")
A64: Melee Weapon Attack | B64: Rapier (2024 edition) | C64: Max of Strength or Dexterity | D64: reach 5 ft | E64: 1d8 | F64: piercing | G64: Finesse | H64: Vex | J64: =A64&": [ATK_MOD] to hit, "&D64&", one target. Hit: [DAMAGE] "&F64&" damage. "&I64 -> Melee Weapon Attack: [ATK_MOD] to hit, reach 5 ft, one target. Hit: [DAMAGE] piercing damage. | K64: ="Mastery: "&H64&". "&_xlfn.XLOOKUP(H64,'weapon masteries'!A$2:A$9,'weapon masteries'!B$2:B$9,"",0) -> Mastery: Vex. If the [MON] hits a creature with this weapon and deals damage to the creature, it has Advantage on its next attack roll against that creature before the end of its next turn. | L64: =IF(NOT(G64=""),IF(COUNTA(P64:T64)>1,"Properties: ","Property: ")&U64&" ("&V64&")"&IF(NOT(W64=""),", "&W64&" ("&X64&")"&IF(NOT(Y64=""),", "&Y64&" ("&Z64&")"&IF(NOT(AA64=""),", "&AB64&" ("&AC64&")",""),""),""),"") -> Property: Finesse (When making an attack with a Finesse weapon, use your choice of your Strength or Dexterity modifier for the attack and damage rolls. You must use the same modifier for both rolls.) | P64: {=IFERROR(_xlfn.TEXTSPLIT(G64,", ",,TRUE),"")} -> Finesse | U64: {=IFERROR(INDEX(_xlfn.TEXTSPLIT(P64," "),,1),"")} -> Finesse | V64: =IF(NOT(U64=""),_xlfn.XLOOKUP(U64,'weapon masteries'!$A$20:$A$29,'weapon masteries'!$B$20:$B$29,"",0),"") -> When making an attack with a Finesse weapon, use your choice of your Strength or Dexterity modifier for the attack and damage rolls. You must use the same modifier for both rolls. | W64: {=IFERROR(INDEX(_xlfn.TEXTSPLIT(Q64," "),,1),"")} | X64: =IF(NOT(W64=""),_xlfn.XLOOKUP(W64,'weapon masteries'!$A$20:$A$29,'weapon masteries'!$B$20:$B$29,"",0),"") | Y64: {=IFERROR(INDEX(_xlfn.TEXTSPLIT(R64," "),,1),"")} | Z64: =IF(NOT(Y64=""),_xlfn.XLOOKUP(Y64,'weapon masteries'!$A$20:$A$29,'weapon masteries'!$B$20:$B$29,"",0),"") | AA64: {=IFERROR(INDEX(_xlfn.TEXTSPLIT(S64," "),,1),"")} | AB64: =IF(NOT(AA64=""),_xlfn.XLOOKUP(AA64,'weapon masteries'!$A$20:$A$29,'weapon masteries'!$B$20:$B$29,"",0),"") | AC64: {=IFERROR(INDEX(_xlfn.TEXTSPLIT(T64," "),,1),"")} | AD64: =IF(NOT(AC64=""),_xlfn.XLOOKUP(AC64,'weapon masteries'!$A$20:$A$29,'weapon masteries'!$B$20:$B$29,"",0),"")
A65: Melee Weapon Attack | B65: Scimitar (2024 edition) | C65: Max of Strength or Dexterity | D65: reach 5 ft | E65: 1d6 | F65: slashing | G65: Finesse, Light | H65: Nick | J65: =A65&": [ATK_MOD] to hit, "&D65&", one target. Hit: [DAMAGE] "&F65&" damage. "&I65 -> Melee Weapon Attack: [ATK_MOD] to hit, reach 5 ft, one target. Hit: [DAMAGE] slashing damage. | K65: ="Mastery: "&H65&". "&_xlfn.XLOOKUP(H65,'weapon masteries'!A$2:A$9,'weapon masteries'!B$2:B$9,"",0) -> Mastery: Nick. When the [MON] makes the extra attack of the Light property, it can make it as part of the Attack action instead of as a Bonus Action. It can make this extra attack only once per turn. | L65: =IF(NOT(G65=""),IF(COUNTA(P65:T65)>1,"Properties: ","Property: ")&U65&" ("&V65&")"&IF(NOT(W65=""),", "&W65&" ("&X65&")"&IF(NOT(Y65=""),", "&Y65&" ("&Z65&")"&IF(NOT(AA65=""),", "&AB65&" ("&AC65&")",""),""),""),"") -> Properties: Finesse (When making an attack with a Finesse weapon, use your choice of your Strength or Dexterity modifier for the attack and damage rolls. You must use the same modifier for both rolls.), Light (When you take the Attack action on your turn and attack with a Light weapon, you can make one extra attack as a Bonus Action later on the same turn. That extra attack must be made with a different Light weapon, and you don’t add your ability modifier to the extra attack’s damage unless that modifier is negative. For example, you can attack with a Shortsword in one hand and a Dagger in the other using the Attack action and a Bonus Action, but you don't add your Strength or Dexterity modifier to the damage roll of the Bonus Action unless that modifier is negative.) | P65: {=IFERROR(_xlfn.TEXTSPLIT(G65,", ",,TRUE),"")} -> Finesse | Q65: Light | U65: {=IFERROR(INDEX(_xlfn.TEXTSPLIT(P65," "),,1),"")} -> Finesse | V65: =IF(NOT(U65=""),_xlfn.XLOOKUP(U65,'weapon masteries'!$A$20:$A$29,'weapon masteries'!$B$20:$B$29,"",0),"") -> When making an attack with a Finesse weapon, use your choice of your Strength or Dexterity modifier for the attack and damage rolls. You must use the same modifier for both rolls. | W65: {=IFERROR(INDEX(_xlfn.TEXTSPLIT(Q65," "),,1),"")} -> Light | X65: =IF(NOT(W65=""),_xlfn.XLOOKUP(W65,'weapon masteries'!$A$20:$A$29,'weapon masteries'!$B$20:$B$29,"",0),"") -> When you take the Attack action on your turn and attack with a Light weapon, you can make one extra attack as a Bonus Action later on the same turn. That extra attack must be made with a different Light weapon, and you don’t add your ability modifier to the extra attack’s damage unless that modifier is negative. For example, you can attack with a Shortsword in one hand and a Dagger in the other using the Attack action and a Bonus Action, but you don't add your Strength or Dexterity modifier to the damage roll of the Bonus Action unless that modifier is negative. | Y65: {=IFERROR(INDEX(_xlfn.TEXTSPLIT(R65," "),,1),"")} | Z65: =IF(NOT(Y65=""),_xlfn.XLOOKUP(Y65,'weapon masteries'!$A$20:$A$29,'weapon masteries'!$B$20:$B$29,"",0),"") | AA65: {=IFERROR(INDEX(_xlfn.TEXTSPLIT(S65," "),,1),"")} | AB65: =IF(NOT(AA65=""),_xlfn.XLOOKUP(AA65,'weapon masteries'!$A$20:$A$29,'weapon masteries'!$B$20:$B$29,"",0),"") | AC65: {=IFERROR(INDEX(_xlfn.TEXTSPLIT(T65," "),,1),"")} | AD65: =IF(NOT(AC65=""),_xlfn.XLOOKUP(AC65,'weapon masteries'!$A$20:$A$29,'weapon masteries'!$B$20:$B$29,"",0),"")
A66: Melee Weapon Attack | B66: Shortsword (2024 edition) | C66: Max of Strength or Dexterity | D66: reach 5 ft | E66: 1d6 | F66: piercing | G66: Finesse, Light | H66: Vex | J66: =A66&": [ATK_MOD] to hit, "&D66&", one target. Hit: [DAMAGE] "&F66&" damage. "&I66 -> Melee Weapon Attack: [ATK_MOD] to hit, reach 5 ft, one target. Hit: [DAMAGE] piercing damage. | K66: ="Mastery: "&H66&". "&_xlfn.XLOOKUP(H66,'weapon masteries'!A$2:A$9,'weapon masteries'!B$2:B$9,"",0) -> Mastery: Vex. If the [MON] hits a creature with this weapon and deals damage to the creature, it has Advantage on its next attack roll against that creature before the end of its next turn. | L66: =IF(NOT(G66=""),IF(COUNTA(P66:T66)>1,"Properties: ","Property: ")&U66&" ("&V66&")"&IF(NOT(W66=""),", "&W66&" ("&X66&")"&IF(NOT(Y66=""),", "&Y66&" ("&Z66&")"&IF(NOT(AA66=""),", "&AB66&" ("&AC66&")",""),""),""),"") -> Properties: Finesse (When making an attack with a Finesse weapon, use your choice of your Strength or Dexterity modifier for the attack and damage rolls. You must use the same modifier for both rolls.), Light (When you take the Attack action on your turn and attack with a Light weapon, you can make one extra attack as a Bonus Action later on the same turn. That extra attack must be made with a different Light weapon, and you don’t add your ability modifier to the extra attack’s damage unless that modifier is negative. For example, you can attack with a Shortsword in one hand and a Dagger in the other using the Attack action and a Bonus Action, but you don't add your Strength or Dexterity modifier to the damage roll of the Bonus Action unless that modifier is negative.) | P66: {=IFERROR(_xlfn.TEXTSPLIT(G66,", ",,TRUE),"")} -> Finesse | Q66: Light | U66: {=IFERROR(INDEX(_xlfn.TEXTSPLIT(P66," "),,1),"")} -> Finesse | V66: =IF(NOT(U66=""),_xlfn.XLOOKUP(U66,'weapon masteries'!$A$20:$A$29,'weapon masteries'!$B$20:$B$29,"",0),"") -> When making an attack with a Finesse weapon, use your choice of your Strength or Dexterity modifier for the attack and damage rolls. You must use the same modifier for both rolls. | W66: {=IFERROR(INDEX(_xlfn.TEXTSPLIT(Q66," "),,1),"")} -> Light | X66: =IF(NOT(W66=""),_xlfn.XLOOKUP(W66,'weapon masteries'!$A$20:$A$29,'weapon masteries'!$B$20:$B$29,"",0),"") -> When you take the Attack action on your turn and attack with a Light weapon, you can make one extra attack as a Bonus Action later on the same turn. That extra attack must be made with a different Light weapon, and you don’t add your ability modifier to the extra attack’s damage unless that modifier is negative. For example, you can attack with a Shortsword in one hand and a Dagger in the other using the Attack action and a Bonus Action, but you don't add your Strength or Dexterity modifier to the damage roll of the Bonus Action unless that modifier is negative. | Y66: {=IFERROR(INDEX(_xlfn.TEXTSPLIT(R66," "),,1),"")} | Z66: =IF(NOT(Y66=""),_xlfn.XLOOKUP(Y66,'weapon masteries'!$A$20:$A$29,'weapon masteries'!$B$20:$B$29,"",0),"") | AA66: {=IFERROR(INDEX(_xlfn.TEXTSPLIT(S66," "),,1),"")} | AB66: =IF(NOT(AA66=""),_xlfn.XLOOKUP(AA66,'weapon masteries'!$A$20:$A$29,'weapon masteries'!$B$20:$B$29,"",0),"") | AC66: {=IFERROR(INDEX(_xlfn.TEXTSPLIT(T66," "),,1),"")} | AD66: =IF(NOT(AC66=""),_xlfn.XLOOKUP(AC66,'weapon masteries'!$A$20:$A$29,'weapon masteries'!$B$20:$B$29,"",0),"")
A67: Melee or Ranged Weapon Attack | B67: Trident (2024 edition) | C67: Strength | D67: reach 5 ft or range 20/60 ft | E67: 1d6 | F67: piercing | G67: Thrown (Range 20/60), Versatile (1d10) | H67: Topple | J67: =A67&": [ATK_MOD] to hit, "&D67&", one target. Hit: [DAMAGE] "&F67&" damage. "&I67 -> Melee or Ranged Weapon Attack: [ATK_MOD] to hit, reach 5 ft or range 20/60 ft, one target. Hit: [DAMAGE] piercing damage. | K67: ="Mastery: "&H67&". "&_xlfn.XLOOKUP(H67,'weapon masteries'!A$2:A$9,'weapon masteries'!B$2:B$9,"",0) -> Mastery: Topple. If the [MON] hits a creature with this weapon, it can force the creature to make a Constitution saving throw (DC 8 plus the ability modifier used to make the attack roll and your Proficiency Bonus). On a failed save, the creature has the Prone condition. | L67: =IF(NOT(G67=""),IF(COUNTA(P67:T67)>1,"Properties: ","Property: ")&U67&" ("&V67&")"&IF(NOT(W67=""),", "&W67&" ("&X67&")"&IF(NOT(Y67=""),", "&Y67&" ("&Z67&")"&IF(NOT(AA67=""),", "&AB67&" ("&AC67&")",""),""),""),"") -> Properties: Thrown (If a weapon has the Thrown property, you can throw the weapon to make a ranged attack, and you can draw that weapon as part of the attack. If the weapon is a Melee weapon, use the same ability modifier for the attack and damage rolls that you use for a melee attack with that weapon.), Versatile (A Versatile weapon can be used with one or two hands. A damage value in parentheses appears with the property. The weapon deals that damage when used with two hands to make a melee attack.) | P67: {=IFERROR(_xlfn.TEXTSPLIT(G67,", ",,TRUE),"")} -> Thrown (Range 20/60) | Q67: Versatile (1d10) | U67: {=IFERROR(INDEX(_xlfn.TEXTSPLIT(P67," "),,1),"")} -> Thrown | V67: =IF(NOT(U67=""),_xlfn.XLOOKUP(U67,'weapon masteries'!$A$20:$A$29,'weapon masteries'!$B$20:$B$29,"",0),"") -> If a weapon has the Thrown property, you can throw the weapon to make a ranged attack, and you can draw that weapon as part of the attack. If the weapon is a Melee weapon, use the same ability modifier for the attack and damage rolls that you use for a melee attack with that weapon. | W67: {=IFERROR(INDEX(_xlfn.TEXTSPLIT(Q67," "),,1),"")} -> Versatile | X67: =IF(NOT(W67=""),_xlfn.XLOOKUP(W67,'weapon masteries'!$A$20:$A$29,'weapon masteries'!$B$20:$B$29,"",0),"") -> A Versatile weapon can be used with one or two hands. A damage value in parentheses appears with the property. The weapon deals that damage when used with two hands to make a melee attack. | Y67: {=IFERROR(INDEX(_xlfn.TEXTSPLIT(R67," "),,1),"")} | Z67: =IF(NOT(Y67=""),_xlfn.XLOOKUP(Y67,'weapon masteries'!$A$20:$A$29,'weapon masteries'!$B$20:$B$29,"",0),"") | AA67: {=IFERROR(INDEX(_xlfn.TEXTSPLIT(S67," "),,1),"")} | AB67: =IF(NOT(AA67=""),_xlfn.XLOOKUP(AA67,'weapon masteries'!$A$20:$A$29,'weapon masteries'!$B$20:$B$29,"",0),"") | AC67: {=IFERROR(INDEX(_xlfn.TEXTSPLIT(T67," "),,1),"")} | AD67: =IF(NOT(AC67=""),_xlfn.XLOOKUP(AC67,'weapon masteries'!$A$20:$A$29,'weapon masteries'!$B$20:$B$29,"",0),"")
A68: Melee Weapon Attack | B68: War Pick (2024 edition) | C68: Strength | D68: reach 5 ft | E68: 1d8 | F68: piercing | G68: Versatile (1d10) | H68: Push | J68: =A68&": [ATK_MOD] to hit, "&D68&", one target. Hit: [DAMAGE] "&F68&" damage. "&I68 -> Melee Weapon Attack: [ATK_MOD] to hit, reach 5 ft, one target. Hit: [DAMAGE] piercing damage. | K68: ="Mastery: "&H68&". "&_xlfn.XLOOKUP(H68,'weapon masteries'!A$2:A$9,'weapon masteries'!B$2:B$9,"",0) -> Mastery: Push. If the [MON] hits a creature with this weapon, it can push the creature up to 10 feet straight away from itself if it is Large or smaller. | L68: =IF(NOT(G68=""),IF(COUNTA(P68:T68)>1,"Properties: ","Property: ")&U68&" ("&V68&")"&IF(NOT(W68=""),", "&W68&" ("&X68&")"&IF(NOT(Y68=""),", "&Y68&" ("&Z68&")"&IF(NOT(AA68=""),", "&AB68&" ("&AC68&")",""),""),""),"") -> Property: Versatile (A Versatile weapon can be used with one or two hands. A damage value in parentheses appears with the property. The weapon deals that damage when used with two hands to make a melee attack.) | P68: {=IFERROR(_xlfn.TEXTSPLIT(G68,", ",,TRUE),"")} -> Versatile (1d10) | U68: {=IFERROR(INDEX(_xlfn.TEXTSPLIT(P68," "),,1),"")} -> Versatile | V68: =IF(NOT(U68=""),_xlfn.XLOOKUP(U68,'weapon masteries'!$A$20:$A$29,'weapon masteries'!$B$20:$B$29,"",0),"") -> A Versatile weapon can be used with one or two hands. A damage value in parentheses appears with the property. The weapon deals that damage when used with two hands to make a melee attack. | W68: {=IFERROR(INDEX(_xlfn.TEXTSPLIT(Q68," "),,1),"")} | X68: =IF(NOT(W68=""),_xlfn.XLOOKUP(W68,'weapon masteries'!$A$20:$A$29,'weapon masteries'!$B$20:$B$29,"",0),"") | Y68: {=IFERROR(INDEX(_xlfn.TEXTSPLIT(R68," "),,1),"")} | Z68: =IF(NOT(Y68=""),_xlfn.XLOOKUP(Y68,'weapon masteries'!$A$20:$A$29,'weapon masteries'!$B$20:$B$29,"",0),"") | AA68: {=IFERROR(INDEX(_xlfn.TEXTSPLIT(S68," "),,1),"")} | AB68: =IF(NOT(AA68=""),_xlfn.XLOOKUP(AA68,'weapon masteries'!$A$20:$A$29,'weapon masteries'!$B$20:$B$29,"",0),"") | AC68: {=IFERROR(INDEX(_xlfn.TEXTSPLIT(T68," "),,1),"")} | AD68: =IF(NOT(AC68=""),_xlfn.XLOOKUP(AC68,'weapon masteries'!$A$20:$A$29,'weapon masteries'!$B$20:$B$29,"",0),"")
A69: Melee Weapon Attack | B69: Warhammer (2024 edition) | C69: Strength | D69: reach 5 ft | E69: 1d8 | F69: bludgeoning | G69: Versatile (1d10) | H69: Sap | J69: =A69&": [ATK_MOD] to hit, "&D69&", one target. Hit: [DAMAGE] "&F69&" damage. "&I69 -> Melee Weapon Attack: [ATK_MOD] to hit, reach 5 ft, one target. Hit: [DAMAGE] bludgeoning damage. | K69: ="Mastery: "&H69&". "&_xlfn.XLOOKUP(H69,'weapon masteries'!A$2:A$9,'weapon masteries'!B$2:B$9,"",0) -> Mastery: Sap. If the [MON] hits a creature with this weapon, that creature has disadvantage on its next attack roll before the start of the [MON]'s next turn. | L69: =IF(NOT(G69=""),IF(COUNTA(P69:T69)>1,"Properties: ","Property: ")&U69&" ("&V69&")"&IF(NOT(W69=""),", "&W69&" ("&X69&")"&IF(NOT(Y69=""),", "&Y69&" ("&Z69&")"&IF(NOT(AA69=""),", "&AB69&" ("&AC69&")",""),""),""),"") -> Property: Versatile (A Versatile weapon can be used with one or two hands. A damage value in parentheses appears with the property. The weapon deals that damage when used with two hands to make a melee attack.) | P69: {=IFERROR(_xlfn.TEXTSPLIT(G69,", ",,TRUE),"")} -> Versatile (1d10) | U69: {=IFERROR(INDEX(_xlfn.TEXTSPLIT(P69," "),,1),"")} -> Versatile | V69: =IF(NOT(U69=""),_xlfn.XLOOKUP(U69,'weapon masteries'!$A$20:$A$29,'weapon masteries'!$B$20:$B$29,"",0),"") -> A Versatile weapon can be used with one or two hands. A damage value in parentheses appears with the property. The weapon deals that damage when used with two hands to make a melee attack. | W69: {=IFERROR(INDEX(_xlfn.TEXTSPLIT(Q69," "),,1),"")} | X69: =IF(NOT(W69=""),_xlfn.XLOOKUP(W69,'weapon masteries'!$A$20:$A$29,'weapon masteries'!$B$20:$B$29,"",0),"") | Y69: {=IFERROR(INDEX(_xlfn.TEXTSPLIT(R69," "),,1),"")} | Z69: =IF(NOT(Y69=""),_xlfn.XLOOKUP(Y69,'weapon masteries'!$A$20:$A$29,'weapon masteries'!$B$20:$B$29,"",0),"") | AA69: {=IFERROR(INDEX(_xlfn.TEXTSPLIT(S69," "),,1),"")} | AB69: =IF(NOT(AA69=""),_xlfn.XLOOKUP(AA69,'weapon masteries'!$A$20:$A$29,'weapon masteries'!$B$20:$B$29,"",0),"") | AC69: {=IFERROR(INDEX(_xlfn.TEXTSPLIT(T69," "),,1),"")} | AD69: =IF(NOT(AC69=""),_xlfn.XLOOKUP(AC69,'weapon masteries'!$A$20:$A$29,'weapon masteries'!$B$20:$B$29,"",0),"")
A70: Melee Weapon Attack | B70: Whip (2024 edition) | C70: Max of Strength or Dexterity | D70: reach 5 ft | E70: 1d4 | F70: slashing | G70: Finesse, Reach | H70: Slow | J70: =A70&": [ATK_MOD] to hit, "&D70&", one target. Hit: [DAMAGE] "&F70&" damage. "&I70 -> Melee Weapon Attack: [ATK_MOD] to hit, reach 5 ft, one target. Hit: [DAMAGE] slashing damage. | K70: ="Mastery: "&H70&". "&_xlfn.XLOOKUP(H70,'weapon masteries'!A$2:A$9,'weapon masteries'!B$2:B$9,"",0) -> Mastery: Slow. If the [MON] hits a creature with this weapon and deals damage to it, it can reduce the target's speed by 10 feet until the start of the [MON]'s next turn. If the creature is hit more than once by weapons that have this property, the speed reduction doesn’t exceed 10 feet. | L70: =IF(NOT(G70=""),IF(COUNTA(P70:T70)>1,"Properties: ","Property: ")&U70&" ("&V70&")"&IF(NOT(W70=""),", "&W70&" ("&X70&")"&IF(NOT(Y70=""),", "&Y70&" ("&Z70&")"&IF(NOT(AA70=""),", "&AB70&" ("&AC70&")",""),""),""),"") -> Properties: Finesse (When making an attack with a Finesse weapon, use your choice of your Strength or Dexterity modifier for the attack and damage rolls. You must use the same modifier for both rolls.), Reach (A Reach weapon adds 5 feet to your reach when you attack with it, as well as when determining your reach for Opportunity Attacks with it.) | P70: {=IFERROR(_xlfn.TEXTSPLIT(G70,", ",,TRUE),"")} -> Finesse | Q70: Reach | U70: {=IFERROR(INDEX(_xlfn.TEXTSPLIT(P70," "),,1),"")} -> Finesse | V70: =IF(NOT(U70=""),_xlfn.XLOOKUP(U70,'weapon masteries'!$A$20:$A$29,'weapon masteries'!$B$20:$B$29,"",0),"") -> When making an attack with a Finesse weapon, use your choice of your Strength or Dexterity modifier for the attack and damage rolls. You must use the same modifier for both rolls. | W70: {=IFERROR(INDEX(_xlfn.TEXTSPLIT(Q70," "),,1),"")} -> Reach | X70: =IF(NOT(W70=""),_xlfn.XLOOKUP(W70,'weapon masteries'!$A$20:$A$29,'weapon masteries'!$B$20:$B$29,"",0),"") -> A Reach weapon adds 5 feet to your reach when you attack with it, as well as when determining your reach for Opportunity Attacks with it. | Y70: {=IFERROR(INDEX(_xlfn.TEXTSPLIT(R70," "),,1),"")} | Z70: =IF(NOT(Y70=""),_xlfn.XLOOKUP(Y70,'weapon masteries'!$A$20:$A$29,'weapon masteries'!$B$20:$B$29,"",0),"") | AA70: {=IFERROR(INDEX(_xlfn.TEXTSPLIT(S70," "),,1),"")} | AB70: =IF(NOT(AA70=""),_xlfn.XLOOKUP(AA70,'weapon masteries'!$A$20:$A$29,'weapon masteries'!$B$20:$B$29,"",0),"") | AC70: {=IFERROR(INDEX(_xlfn.TEXTSPLIT(T70," "),,1),"")} | AD70: =IF(NOT(AC70=""),_xlfn.XLOOKUP(AC70,'weapon masteries'!$A$20:$A$29,'weapon masteries'!$B$20:$B$29,"",0),"")
A71: Ranged Weapon Attack | B71: Blowgun (2024 edition) | C71: Dexterity | D71: range 25/100 ft | E71: 1 | F71: piercing | G71: Ammunition (Range 25/100; Needle), Loading | H71: Vex | J71: =A71&": [ATK_MOD] to hit, "&D71&", one target. Hit: [DAMAGE] "&F71&" damage. "&I71 -> Ranged Weapon Attack: [ATK_MOD] to hit, range 25/100 ft, one target. Hit: [DAMAGE] piercing damage. | K71: ="Mastery: "&H71&". "&_xlfn.XLOOKUP(H71,'weapon masteries'!A$2:A$9,'weapon masteries'!B$2:B$9,"",0) -> Mastery: Vex. If the [MON] hits a creature with this weapon and deals damage to the creature, it has Advantage on its next attack roll against that creature before the end of its next turn. | L71: =IF(NOT(G71=""),IF(COUNTA(P71:T71)>1,"Properties: ","Property: ")&U71&" ("&V71&")"&IF(NOT(W71=""),", "&W71&" ("&X71&")"&IF(NOT(Y71=""),", "&Y71&" ("&Z71&")"&IF(NOT(AA71=""),", "&AB71&" ("&AC71&")",""),""),""),"") -> Properties: Ammunition (You can use a weapon that has the Ammunition property to make a ranged attack only if you have ammunition to fire from it. The type of ammunition required is specified with the weapon's range. Each attack expends one piece of ammunition. Drawing the ammunition is part of the attack (you need a free hand to load a one-handed weapon). After a fight, you can spend 1 minute to recover half the ammunition (round down) you used in the fight; the rest is lost.), Loading (You can fire only one piece of ammunition from a Loading weapon when you use an action, a Bonus Action, or a Reaction to fire it, regardless of the number of attacks you can normally make.) | P71: {=IFERROR(_xlfn.TEXTSPLIT(G71,", ",,TRUE),"")} -> Ammunition (Range 25/100; Needle) | Q71: Loading | U71: {=IFERROR(INDEX(_xlfn.TEXTSPLIT(P71," "),,1),"")} -> Ammunition | V71: =IF(NOT(U71=""),_xlfn.XLOOKUP(U71,'weapon masteries'!$A$20:$A$29,'weapon masteries'!$B$20:$B$29,"",0),"") -> You can use a weapon that has the Ammunition property to make a ranged attack only if you have ammunition to fire from it. The type of ammunition required is specified with the weapon's range. Each attack expends one piece of ammunition. Drawing the ammunition is part of the attack (you need a free hand to load a one-handed weapon). After a fight, you can spend 1 minute to recover half the ammunition (round down) you used in the fight; the rest is lost. | W71: {=IFERROR(INDEX(_xlfn.TEXTSPLIT(Q71," "),,1),"")} -> Loading | X71: =IF(NOT(W71=""),_xlfn.XLOOKUP(W71,'weapon masteries'!$A$20:$A$29,'weapon masteries'!$B$20:$B$29,"",0),"") -> You can fire only one piece of ammunition from a Loading weapon when you use an action, a Bonus Action, or a Reaction to fire it, regardless of the number of attacks you can normally make. | Y71: {=IFERROR(INDEX(_xlfn.TEXTSPLIT(R71," "),,1),"")} | Z71: =IF(NOT(Y71=""),_xlfn.XLOOKUP(Y71,'weapon masteries'!$A$20:$A$29,'weapon masteries'!$B$20:$B$29,"",0),"") | AA71: {=IFERROR(INDEX(_xlfn.TEXTSPLIT(S71," "),,1),"")} | AB71: =IF(NOT(AA71=""),_xlfn.XLOOKUP(AA71,'weapon masteries'!$A$20:$A$29,'weapon masteries'!$B$20:$B$29,"",0),"") | AC71: {=IFERROR(INDEX(_xlfn.TEXTSPLIT(T71," "),,1),"")} | AD71: =IF(NOT(AC71=""),_xlfn.XLOOKUP(AC71,'weapon masteries'!$A$20:$A$29,'weapon masteries'!$B$20:$B$29,"",0),"")
